Workbook

Sheet New Meetings
A1: SUB | B1: Opener | C1: Status | D1: Date Added | E1: Company Name | F1: Authorized Person | G1: Phone | H1: EMAIL | I1: Meeting Time | J1: Opener Summary | K1: George's Notes | L1: Auto Scheduler | M1: Last Call | N1: Action | O1: Checkbox | P1: Log | Q1: NPI
A2: ORT+CGM+LYMPH W | B2: Jasmine | D2: 46197 | E2: DENISE V. LYONS MEDICAL SUPPLY HOUSE | F2: DENISE V. LYONS | G2: 303-257-1938 | H2: denisevlyons@outlook.com | I2: Mon 10:30 | J2: ort cgm lymphedema / medicaid aetna humana united healthcare CO based | Q2: 1366915209
A3: IMMUNE | B3: Jane | C3: Follow Up | D3: 46092 | E3: SYNERGENIX DIAGNOSTICS | F3: JOEY JENKINS | G3: 202-607-3875 | H3: jenkinslifetree@gmail.com | I3: Fri 7:00 PM | J3: MD based has the ngs machine and do the immune deficiency test, medicare licensed, and accept patients from most states, asked to send email meeting fri | K3: set a meeting next thursday same time 2:00 PM, he will Out source it for one of his parnter to do it in his lab and get the reimbursements and pay for us , I will send him the email and everything now , we discussed the payment cycle as upfront would be difficult for them , 50% and they will circle back and get back to us , 03/26/2026 , someone try to reschedule the meeting , we agreed on 50% we are still agreeing on the capacity 12- 17 - 25 patients, he still waiting on some capital to fund this project 3/30, i spoke with him and he said that he want to work with us and want to built trust he want us to send atleastsome leads to get started then he will pay, itold him about the 50percent but he said still to much , i told hime about the uti he said he can doi it and it less pricy so we cant start with it if we have ready pts and if he finds our work went well he will work with us the ngs and pgx meeting on friday 12pm est | M3: 46223.763 | O3: FALSE | Q3: 1174419758
A4: ORT | B4: Selene | D4: 46231 | E4: EPIC PROSTHETICS AND ORTHOTICS LLC | F4: JAKE COBURN DAVIS | G4: 801-820-0045 | H4: jake@epicpo.com | I4: =HYPERLINK("https://calendar.google.com/calendar/u/0/r/eventedit/Mm8zMmNqNmJidG8zZWZyODlubXNtMzFydGUgYzM5ZjIxNjY2YTJjNzBkNjQ0MDI0YmQyOWM3ZmM5ODM3OTY2MmY3OTJlNWEwNDdjZGIzNTdhNDJiM2M1N2QwNEBn?pli=1", "FRI 8:00 PM") -> FRI 8:00 PM | J4: UT Based ,supply ORT ,Mediacre liscenced ,supply locally said he does marketing himself but interested to know more said to give him a call at 11 am his time on friday 7/28 | Q4: 1629722889
A5: Lab | B5: Jane | D5: 46233 | E5: ADVANCED LABORATORY SERVICES INC. | F5: JASBIR ARORA JASBIR ARORA | G5: 484-324-6680 | H5: jasbir.arora@advanced-lab.com | I5: =HYPERLINK("https://calendar.google.com/calendar/u/0/r/eventedit/NjdvNWowNGZkdGtwZmtxMzk2MnM5c3F0ZTIgYzM5ZjIxNjY2YTJjNzBkNjQ0MDI0YmQyOWM3ZmM5ODM3OTY2MmY3OTJlNWEwNDdjZGIzNTdhNDJiM2M1N2QwNEBn", "Wed 10:00 PM") -> Wed 10:00 PM | J5: ,Pa based do pgx, can bill medicare, but never billed for pgx able to do that , work all stattes accept for the ny will get licsence by end of the year fopr ny, meeting on wednesday to discuss with his team | K5: he apolagized and will reschedule on my calender by this week | M5: 46240.741 | Q5: 1265365829
A6: Lab | B6: Selene | D6: 46239 | E6: MICROSEQDX | F6: RAHUL SHARMA | G6: 225-573-2690 | H6: rsharma@microseqdx.com | I6: =HYPERLINK("https://calendar.google.com/calendar/u/0/r/eventedit/M3ZvM2Q1M2JiazRjc285MGZmZWU4Z2w2NjcgYzM5ZjIxNjY2YTJjNzBkNjQ0MDI0YmQyOWM3ZmM5ODM3OTY2MmY3OTJlNWEwNDdjZGIzNTdhNDJiM2M1N2QwNEBn?pli=1", "FRI 11:00 PM") -> FRI 11:00 PM | J6: TX Based, accepts nationwide medicare patients does UTI,PGX meeting TUES 9 PM pm our time 8/5 | K6: He provides UTI PGX inhouse and NGS to his partner lab ,he has an issue with telemedicine and wants PCP and wants the same person prescribing the test to prescribe the medicine ,he said he can start with any test but he has an isuue with the prices he sees it high he says he only pays 30 percent marketing fee, he said he wants to work as a refrence lab and find another lab to bill. Next meeting we will ask if he read the codes and checked with the reimbursemnet and will explain that we do tele only and explain to him the overhead costs (telemdicine service ,ads,guide patient ) meeting next tuesday 9 pm 8/11sent him samples and marketing plan he has an issue with the TMS he wants the TMS to prescribe medication to the patient and he has issues with the pricing so next time we will hope on a call with mike and we will discuss that TMS is not an issue and we provide (ads,kitchasing,TMS) and thats its not expensive | M6: 46248.797 | Q6: 1033037254
A7: MLA | B7: Jimmy | D7: 46241 | E7: Life assure | F7: Brandon | G7: Ph: 204-982-0095 | H7: brandon.leblanc@lifeassure.com | I7: THU 8:00 PM | J7: Good afternoon, A colleague passed your contact information to me because you reached out about working together. I'm interested in learning more about how Prime Ad and Life Assure could explore a partnership. Do you have time for a call tomorrow or early next week to discuss this?
A8: ORT+CGM+LYMPH W | B8: Nora | D8: 46241 | E8: 86TH STREET COMMUNITY PHARMACY CORP. | F8: ABAID CHEEMA (President) | G8: (347) 543-3955 | H8: 86thstpharmacy@gmail.com | I8: Mon 7:00 PM | J8: NY based. He supplies ORT, CGM, and Lymph. He has Medicare and PPO and can ship nationwide 8/7 He said Mondays are a bit busy so rescheduled for tom at 6 pm 8/10 | Q8: 1093732513
A9: Lab | B9: Jane | D9: 46244 | E9: ORANGE COUNTY LABS INC. | F9: Bryan Muhlenbruch | G9: 714-519-1466 | H9: bm@orangecountylabs.com | I9: =HYPERLINK("https://calendar.google.com/calendar/u/0/r/eventedit/NWdmZDZpbjVjcGxidGhjcDUydmNwaDlyOHMgamFuZS5teWxlcy53aXpAbQ", "Wed 10:30 PM") -> Wed 10:30 PM | J9: ca based do genetic testing,immune and uti,pgx,accept medicare pts nv ca mi fl az, tx, he can apply for credation for other states according to the capacity if it needs, meeting tomw 10:30pm | K9: rescheduled for tomowrow 10;30 | M9: 46253.891 | Q9: 1023439809
A10: Lab | B10: Jimmy | D10: 46245 | E10: DE LA LUZ LABORATORY LLC | F10: MARIA ESMERALDA AMARO HERNANDEZ | G10: 312-415-7097 | H10: mariaeamaro700@gmail.com | I10: THU 8:00 PM | J10: She can do immune, PGx and UTI and accepts medicare and private insurance PTs | Q10: 1326972274
A11: ORT+CGM | B11: Selene | D11: 46247 | E11: GUARDIAN ANGEL DME | F11: MD FAYSAL AHMED | G11: 213-263-1687 | H11: pbreliefmedicalsupply@gmail.com | I11: =HYPERLINK("https://calendar.google.com/calendar/u/0/r/eventedit/MjlvM2kza2xiaDZ2dThybGNva2hmamRkcG8gYzM5ZjIxNjY2YTJjNzBkNjQ0MDI0YmQyOWM3ZmM5ODM3OTY2MmY3OTJlNWEwNDdjZGIzNTdhNDJiM2M1N2QwNEBn?pli=1", "Mon 6:30 PM") -> Mon 6:30 PM | J11: CA Based ,supply ORT, CGM ,Mediacre liscenced ,ships nationwide ,interested to know more said to give him a call at 6.30 pm our time mon 8/13 | Q11: 1922806330
A12: Lab | B12: Nora | D12: 46248 | E12: PRIME DIAGNOSTICS LAB INC. | F12: SYEDA HINA SHAKIL (CEO) | G12: (425) 444-6076 | H12: primelabdiagnostics2019@gmail.com | I12: Fri 11:00 PM | J12: Based in MI. They do UTI testing only and they ship in Michigan. They can bill Medicare and other Michigan-based private insurances. | Q12: 1093351470
A13: ORT+CGM | B13: Selene | D13: 46251 | E13: VELORA DME SOLUTIONS LLC | F13: AZAR TALIBOV | G13: 856-347-7880 | H13: johnalpha601@gmail.com | I13: =HYPERLINK("https://calendar.google.com/calendar/u/0/r/eventedit/NjM1Y2tqZjY0cTd2dW9lZWc1anQ4dXN0bjcgYzM5ZjIxNjY2YTJjNzBkNjQ0MDI0YmQyOWM3ZmM5ODM3OTY2MmY3OTJlNWEwNDdjZGIzNTdhNDJiM2M1N2QwNEBn?pli=1", "Tue 8:00 PM") -> Tue 8:00 PM | J13: NJ Based ,supply ORT, CGM ,Mediacre liscenced ,shipslocally but will consider nationwide ,interested to know more said to give him a call at 8.00 pm our time tues 8/13 | Q13: 1184554750
A14: Lab | B14: Nora | D14: 46251 | E14: DIAGNOSTIC TESTING SOLUTIONS INC | F14: NADEEM AKHTAR | G14: (773) 853-0883 | H14: dnask1@gmail.com | I14: TUE 9:30 PM | J14: Based in IL. They do UTI testing and they accept Medicare patients. They also have nationwide shipping 8/17 He had an emergency will cb tomorrow to reschedule 8/18 | Q14: 1174278238
A15: ORT+CGM | B15: Jane | D15: 46251 | E15: WOUND BOX LLC | F15: JASON/ ADAM JOHN MEIERHOFER | G15: 855-968-6326 | H15: jason@woundbox.com | I15: =HYPERLINK("https://calendar.google.com/calendar/u/0/r/eventedit/NTFnZmo4YWhzb3JmNmt2ZThhNTNhZGttb2MgamFuZS5teWxlcy53aXpAbQ", "Tue 10:00 PM") -> Tue 10:00 PM | J15: Tx based, said he can supply ort,cgm, and i told him our volume of cgm is more, can ship any place, meeting 8/17 | Q15: 1831055482
A16: Lab | B16: Jimmy | D16: 46252 | E16: MNM LABORATORY CONSULTING, LLC | F16: MASHUD OGUNLAJA | G16: 424-999-8698 | H16: info@mnmlabCONSULTING.com | I16: FRI 8:00 PM | J16: NGS, UTI, PGx can accept medicare PT | Q16: 1073367389
A17: ORT+CGM | B17: Selene | D17: 46253 | E17: WELLVORA LLC | F17: FAIZAN KHAN | G17: 949-304-0361 | H17: frksrkhan2@gmail.com | I17: =HYPERLINK("https://calendar.google.com/calendar/u/0/r/eventedit/N2I0bXJxc3VkNGFrZWFyajVxZmMwMjU3ODcgYzM5ZjIxNjY2YTJjNzBkNjQ0MDI0YmQyOWM3ZmM5ODM3OTY2MmY3OTJlNWEwNDdjZGIzNTdhNDJiM2M1N2QwNEBn?pli=1", "FRI 4:00 PM") -> FRI 4:00 PM | J17: CA Based ,supply ORT, CGM ,Mediacre liscenced , nationwide ,interested to know more said to give him a call at 4.00 pm our time FRIDAY 8/13 | Q17: 1528985488
A18: ORT | B18: Nora | D18: 46253 | E18: NUA AESTHETICS LLC | F18: NAYMA LABARCA | G18: (407) 515-7755 | H18: nayma@nuaesthetics.com | I18: THU 9:00 PM | J18: Based in FL. They supply ORT and they have Medicare and Oscar. Local shipping in FL for now 8/19 | Q18: 1689528770
A19: ORT+CGM | B19: Jane | D19: 46253 | E19: VITALFORT LLC | F19: MUHAMMAD KHAN | G19: 917-525-2517 | H19: mr.mianzohaib@gmail.com | I19: =HYPERLINK("https://calendar.google.com/calendar/u/0/r/eventedit/NG04MDVyOGo1bzVnMW03cWJwdHN1bTluamwgYzM5ZjIxNjY2YTJjNzBkNjQ0MDI0YmQyOWM3ZmM5ODM3OTY2MmY3OTJlNWEwNDdjZGIzNTdhNDJiM2M1N2QwNEBn", "Thu 11:00 PM") -> Thu 11:00 PM | J19: Ga based, supply ort , cgm, bill medicare . ship all states, meeting tomw 11 pm 4 pm est tomw
A20: Lab | B20: Nora | D20: 46253 | E20: BENDA HEALTH EDUCATION AND TESTING SERVICES LLC | F20: BENDU DAWOLO | G20: (281) 836-1869 | H20: bendacpr@gmail.com | I20: THU 6:00 PM | J20: Based in WI. They do UTI testing. They accept Medicare patients and operate in WI for now 8/19 | Q20: 1316777543
A21: Lab | B21: Nora | D21: 46253 | E21: WELCARE DIAGNOSTICS LLC | F21: RINABEN VAGHELA MAKANI | G21: (215) 285-8545 | H21: info@welcaredx.com | I21: FRI 9:00 PM | J21: Based in NJ. They have UTI, Immune, and PGx. They accept Medicare and private insurances and they operate in NJ and PA 8/19 | Q21: 1285338731
A22: Lymphadema | B22: Jasmine | D22: 46253 | E22: STRATEGIC ACCESS INTERNATIONAL LLC | F22: Rhonda Mitchell | G22: 202-810-1821 | H22: rhondacmitchell@gmail.com | I22: Mon 9:30 PM | J22: GA based, has lymphedema currently but in the process of getting ORT/CGM , can accept most private insurances and in the process of obtaining the PTAN code for medicare. | Q22: 1568380384

Sheet Follow Ups
A1: SUB | B1: Opener | C1: Status | D1: Date Added | E1: Company Name | F1: Authorized Person | G1: Phone | H1: EMAIL | I1: Meeting Time | J1: Opener Summary | K1: George's Notes | L1: Auto Scheduler | M1: Last Call | N1: Action | O1: Checkbox | P1: Log | Q1: NPI
A2: Campaigns | B2: Selene | C2: Follow Up | D2: 45707 | E2: PROMED SUPPLIES | F2: Zahid James | G2: 215-954-0877 | H2: promed239@gmail.com | I2: Fri 8.00PM | J2: - done from medicare inspection will work i month from now , dme cgm al states pcp tele med fri 21st 1 pm est 8 pm our time -selene 2/19 - Yayyyyyy he got his PTAN and he said he was looking for our contact he wnats to start i resent the email and calender invite meeting today 5 pm est 11 pm our time -selene 3/27 - He was very sick and wanted us to call him 10 am tmrw or 10 am wed-selene 3/28 - He wants medicare to change his number and then start he will return to us by fri about medicare number -selene 4/15 - yayyy Medicare changed his number and everything is all set cb Mon 19th 12 pm EST -selene 5/13 waiting for funds -WILL CB IN AN HOUR 7/28 - broke said not ready to do it he will contact us -selene 8/8 - said to send prices and give him a cb on fri 1/20 -no longer doing DME 8/4 | K2: - send a price list 08/29/2025 - DOC 2/5 VM - schedule a google meet next week 8:30 our time, i sent the proposal + prices again - ben, no answer -VM FULL - ben vm 7/20 | M2: 46223.802 | N2: VM | O2: FALSE | Q2: 1649038878
A3: ORT | B3: Selene | C3: Follow Up | D3: 45713 | E3: REGAL MEDICAL SOLUTIONS INC | F3: Tara | G3: 678-701-7310 | H3: carlytdme2@gmail.com | I3: Fri 8.00:PM | J3: - GA basesd I spoke to tara she works with PCP/ Telemed all states CGM DME and she wanted to know reviews about us and asked if we have US bank acount meeting friday at 1 pm est and 8 pm our time she will dicuss with her partners -selene 2/25 - Meeting Tmrw at 27th feb 3.30 est and 10.30 or time meeting with her business partner -selene 2/26 - cb next monday she said she will think about it and i resent the email-selene 7/31 | K3: Spoke to one of her partners but the other meeting keeps getting reschedule, I should call to follow up around the 10th of March. DOC 3/27/2025 Said that our prices are a bit high, but they aren't that interested at the moment. said she will get back to me Doc (12/11/2025) ,can't reach her - DOC 2/5 VM dis 7/20 | M3: 46223.802 | N3: VM | O3: FALSE | Q3: 1053144022
A4: ORT | B4: Jane | C4: Follow Up | D4: 45714 | E4: Allhealth & Care Medical Supply Inc. | F4: Robert Binyaminov | G4: 917-957-2766 | I4: Mon 5:00 PM | J4: Medicare licensed, DME & CGM, NY based but can do all states, PCP, he was very interested in the contract as he wants to review it with his attorney | K4: waiting for his PTAN DOC 13/3/2025. DOC 4/4/2025 still in the process did fingerprint, any time now he will receive his PTAN. Received his PTAN and will talk with his biller to finalize compliance matters today DOC 4/24/2025 VM (12/11/2025) VM - ben | M4: 46085.887 | O4: FALSE | Q4: 1568221281
A5: ORT | B5: Jane | C5: Follow Up | D5: 45737 | E5: SUNRISE MEDICAL SUPPLY CORP | F5: Liya Yusupova | G5: 917-763-9518 | H5: info@ameristarbilling.com | I5: Mon 5:30 PM | J5: NYBASED, SUPPLU DME ,CGM MEDICARE LICENSED AND, SHE WANT TO SHIP TO ALL STATES BUT THINKS THAT SHER NEED LICESEND, IT OKAY U CAN SEND THEM ALL STATES, PCP, MEETING 5:30 OUTIME, 11 30 AM 3/21 | K5: Finally answered and asked me to call next week same time because her partner is away VM (12/08/2025) Full VM - ben sent an email | M5: 46085.853 | O5: FALSE | Q5: 1639847205
A6: ORT+CGM | B6: Selene | C6: Follow Up | D6: 45754 | E6: IK-MED LLC | F6: Sheikh Aftab | G6: 703-640-8784 | H6: ASAD149@GMAIL.COM | I6: Tue 10:30 PM | J6: Medicare liscenced , nationwide, PCP ,ORTCGM he said he takes between 50 to 100 pts per week meeting 4/8 tuesday 4.30 est 10 .30 our time -selene 4/7 - i gave him a call today he said that he is really interested and to give him a call tmrw at 11.30 am his time 4/24 - he hung up seems NI -selene 4/29 - cb next mon 1 -selene 11/25 | K6: We will have a second call tomorrow to discuss the proposal after we send the pricelist. DOC 4/9/2025 No answer 3 times. DOC 4/10/2025 Call tomorrow. DOC 4/11/2025 No answer DOC 4/14/2025 Will talk later this week on Friday. DOC 4/18/2025. Could start trial on Monday, I will send the contract and the pricelist again and call on Monday. Really not serious, instant VM DOC 4/23/2025 - DOC 2/5 VM - was out of town, wants an email, schedule a google meet for friday 8 pm -said to call him 11:30/12 tomorrow - ben - full vm 7/20 | M6: 46223.802 | O6: FALSE | Q6: 1518788249
A7: ORT+CGM | B7: Ben | C7: Follow Up | D7: 45761 | E7: Family Alliance Medical Equipment And Supply Company | F7: Audrey Fletcher / Spoke to Evan | G7: 267-272-7791 | H7: f.alliancehomecare@gmail.com | I7: Thu 8:00:PM | J7: PA Based. AlL States, went over our email seems v interested wants an email and a call tuesday same time 8/21 | K7: I spoke with Evan, her office manager. Very interested and we will talk again in a video call for the demo. VM - BEN recheduled with evan spoke to audrey about meeting with evan VM | M7: 46248.746 | O7: FALSE | Q7: 1033979000
A8: ORT+CGM | B8: Selene | C8: Follow Up | D8: 45785 | E8: Nex Medical Services Inc | F8: Ms Michelle (Supervisor ) | G8: 281-583-1810 404 Elais | H8: mg@nexmeds.com er@nexmeds.com | I8: Mon 6:00:PM | J8: - I spoke to Michelle supervisor she said Medicare liscenced ,ORT CGM can work all states she said they worked several counties i sent an email -selene 5/7 - I spoke to michelle (ext 402) or could be transferred she said we could have a meeting on Monday around 10 am cst 6 pm our time she said she and her partner handle the business -selene 5/8 - cb next mon 6/11 - spoke to michelle she said to resend the prices and give her a cb on wednesday and she will send it to her partner -selene 6/27 - cb monday sent email to partner 8/7 | K8: We spoke and covered everything, we will send a prive list and talk again on Friday. DOC 5/16/2025, Said she sent the price list to her Partner and we will touch base again on Wedensday instead becuase he isn't available today. - DOC 2/5 VM , set an appointment for next tuesday at 11:00 (google meet ) , she wants us to call back later today as she is waiting for elias to come from an appointment 03/10/2026 | M8: 46091.768 | O8: FALSE | Q8: 1790930857
A9: ORT+CGM | B9: Selene | C9: Follow Up | D9: 45847 | E9: DULUTH MEDICAL SUPPLIES LLC | F9: Raed Hareb | G9: 706-351-5894 | H9: duluthmedicalsupplies@gmail.com | I9: Wed 9:00:PM | J9: - GA Based just got their PTAN and works Part B and PPO really interested and said wants to speak with us with his partner meeting 2 pm est 9 pm our time today 7/9 | K9: interested meeting tomorrow | O9: FALSE | Q9: 1790520120
A10: SUB | B10: Selene | C10: Follow Up | D10: 45847 | E10: Entourage Me UAE | F10: Neil Laithy | G10: 401-206-0481 | H10: nlaithy@gmail.com or zoeyweedspc@gmail.com | I10: Wed 5:00:PM | J10: - Connected via Linkdin asked if we worked in ACA or genetics gave phone number to george so he can talk to him -selene 7/9 | K10: we spoke about ACA & Genetic testing , Really good Guy | O10: FALSE
A11: ORT+CGM | B11: Selene | C11: Follow Up | D11: 45875 | E11: SML MEDICAL SUPPLIES, INC. | F11: SAMIR RAMADAN | G11: 909-559-7200 WA | H11: sawad@smlmedicalsupplies.com | I11: Wed 7:30:PM | J11: CA BASED , MEDICARE LICENSED, SHIP ALL STATES,CGM, ORT wants to know more about prices meeting 7.30 OUR TIME 9.30 PDT HIS TIME -SELENE 8/6 | K11: Send all the Info regarding CGM VM NOT SETUP. ben | M11: 46183.848 | O11: FALSE | Q11: 1558826628
A12: ORT+CGM | B12: Selene | C12: Follow Up | D12: 45875 | E12: SML MEDICAL SUPPLIES, INC. | F12: Sameh Awad | G12: 909-559-7200 WA | H12: sawad@smlmedicalsupplies.com | I12: Wed 7:30:PM | J12: CA BASED , MEDICARE LICENSED, SHIP ALL STATES,CGM, ORT wants to know more about prices meeting 7.30 OUR TIME 9.30 PDT HIS TIME -SELENE 8/6 | K12: Send all the Info regarding CGM ben dnc | M12: 46085.896 | O12: FALSE | Q12: 1558826628
A13: Campaigns | B13: Jane | C13: Follow Up | D13: 45890 | E13: PCP ( DDV Provided ) | F13: Ricky Sharma | G13: Teams | I13: Thu 9:30PM | J13: he will provide the DDV lower payouts than gary thomas | O13: FALSE
A14: Campaigns | B14: Selene | C14: Follow Up | D14: 45890 | E14: uk boliers expert | F14: Qeiser Nazir | I14: Fri 1:00PM | J14: we talked about the chance that we can work together , he gave me dialer and will get me data | K14: he gave us info about the boilers campaign & dialer information | O14: FALSE
A15: ORT+CGM | B15: Selene | C15: Follow Up | D15: 45894 | E15: AMASOL MEDICAL EQUIPMENT & SUPPLY LLC | F15: Moses Carayol | G15: 914-582-2764 | H15: amasolmedicalsupply@gmail.com/ john | I15: Tue 10:30PM | J15: NY Based Medicare liscenced ships all states PCP Telemed ORT ,CGM wants to know the prices Meeting Tuesday 3.30 pmest 10.30 pm our time -selene 8/25 | K15: send all the info on the ORthopedic Braces + Price list + a sample from pcp order and telemed Order Called him 09/09 (VM ) - Spoke to him he said to resend email with prices -selene 2/5 Full VM / sent email - ben vm 7/20 | M15: 46223.803 | O15: FALSE | Q15: 1639503121
A16: ORT+CGM | B16: Jane | C16: Follow Up | D16: 45904 | E16: Jk Care Supplies Llc | F16: Ismail Khan | G16: 646-920-5833 | H16: ismail290k@gmail.com / Kashif.khan15504@gmail.com | I16: Fri 5:00PM | J16: Licensed, all states, DME and CGM, he was excited to talk tomorrow | K16: meeting on wednesday 11:00 am EST , He will be texting the other partners email and we could proceed afterwards VM -ben | M16: 46112.898 | O16: FALSE | Q16: 1952279325
A17: ORT+CGM | B17: Ben | C17: Follow Up | D17: 45919 | E17: Dmg Wellness Inc. | F17: Gregory Ihenacho | G17: 323-676-5360 | H17: dmgwellness2019@gmail.com / david@dmgwellness.com | I17: Mon 10:00PM | J17: medicare all states, Spoke to patner, David, interested, wants email with all info 9/19 BE BACK NEXT WEEK 2/26 | K17: Ben Arthur, send him our process in braces + prices for PCP + the lcodes that we are using ( already written in the pdf that contains the pricing ) L 0647 L 1812 L1820 this is the L codes that he is using , he is interested in braces not CGM , and he is even more interested in the lymphadema wraps be back next week - ben - DAVID FORGOT EVERYTHING, consider as new unless he remembered - ben | M17: 46112.963 | O17: FALSE | Q17: 1568089548
A18: Vacation DNC Camapign | B18: Jane | C18: Follow Up | D18: 45925 | E18: Intellegent Healthcare llc | F18: Adrian | G18: 305-560-3285 | J18: US BASED , TARGET THE US AND CANADA CUSTOMER , PROVIDE DDV AND TRAININD WANTS TO START WITH 3 AGENTS | K18: we spoke over the phone and he sent me the details on whatsapp | O18: FALSE
A19: ORT | B19: Ben | C19: Follow Up | D19: 45708 | E19: A1 Medical Equipment Inc. | F19: Dallas Powers | G19: 616-835-3304 | H19: DallasRpowers@yahoo.com | I19: Fri 9.00:PM | J19: - Medicare licensed, CGM mainly but also does bracing, all states, PCP mainly but said if you say that I can also do telemed as I can do that as well | K19: Interested, CGM CPL 11:00 am, Comparison between Pay per hour (lead generation) ( client would be doing the chasing ) and normal of 9-11 patients per month full VM -ben hungup, sent email , ben | M19: 46183.848 | O19: FALSE | Q19: 1265051916
A20: ORT + Lymphedema | B20: Selene | C20: Follow Up | D20: 45992 | E20: DYNAMEDICS MEDICAL SOLUTIONS, INC | F20: SAM OBINNA SONNY ECHENDU | G20: 919-995-0554 | H20: dmedsolutions@gmail.com / dynamedicshcs@gmail.com | I20: Tue 8:30PM | J20: NC Based, medicare liscenced ships nationwide , supply ort ,lymph meeting tuesday 1.30 est 8.30 our time 12/1 - Meeting changed to next mon 9 pm because he said he needs to fix problems at work 12/2 | K20: 12/10/2025 9 pm our time he didn't receive the email and i got a different email from him he will review and we will touc base on wednesday same time seems to be NI - ben didn't have time to read the email due to internet problems vm full, ben full vm | M20: 46223.804 | O20: FALSE | P20: didn't have time to read the email due to internet problems | Q20: 1902542756
A21: IMMUNE | B21: Jane | C21: Follow Up | D21: 45939 | E21: ADVANTAGE DIAGNOSTICS CLINICAL LABORATORY LLC | F21: POLINA GENKIN | G21: 347-462-4949 | H21: polina.g@advantagediagnosticlaboratory.com, | I21: Fri 5:00PM | J21: she is nj based, serve alll states, bill medicare, she supply immuno deficiency , PCR,UTI polina.g@advantagediagnosticlaboratory.com, MEETING TOMW 10 AM,HER TIME 5 PM OUR TIME, | K21: interest in the uti only, she will call me tomorrow sent her an email follow up on thursday 10/16 | O21: FALSE | Q21: 1497486880
A22: ORT + Lymphedema | B22: Jane | C22: Follow Up | D22: 45980 | E22: KARMA7 MEDICAL SUPPLY LLC | F22: Roman Krive | G22: 847-454-7085 ext 101 | H22: office@k7supply.com | I22: Fri 7:00 PM | J22: IL BASED, MEDICARE LICSEND, SHIP TO ILL WI, IN BUT WILLING TO DO,asked about the link for shipping meeting 5:30 pm our time | K22: interest in the uti only, she will call me tomorrow sent her an email follow up on thursday 10/16, she said our prices was too high put wan toknow the uti pts prices | M22: 46223.75 | O22: FALSE | Q22: 1477024347
A23: IMMUNE | B23: Selene | C23: Follow Up | D23: 45981 | E23: BIO SYSTEMS LABORATORY, LLC | F23: DAMIEN FRALIN | G23: 972-951-6530 | H23: gorilla2018@yahoo.com | I23: Fri 9:00 PM | J23: TX Based, Mediacare Liscenced , Accept All States patients does immuno genetic testing does the tests with telemed has a concern if the bill is not extended meeting tmrw 9 pm 1 pm cst -selene 11/20 | K23: He is well aware about process doesnt want to pay upfront wants to pay little or when the kits arrive at his doorstep | O23: FALSE | Q23: 1275364853
A24: ORT + Lymphedema | B24: Jane | C24: Follow Up | D24: 45985 | E24: BINSON'S FLORIDA, LLC | F24: JAMES E BINSON | G24: 586-933-7598/ matt 5867552300 ext4464/ mattp@binsons.com/ sherry ext 4616 | H24: jimmyb@binsons.com | I24: Tue 6:30PM | J24: Fl based, medicare licsensend supply ort and lymhadema wraps, ship all states, send email, meeting tomw 6:30 our time | K24: ben can you send the price list ( 2 modules + sigvaris catlogue ) they will respond back to the email with their convenient time meeting on friday12/5/2025 / voice mail 01/08/2025 VM -ben | M24: 46094.862 | O24: FALSE | Q24: 1386886554
A25: IMMUNE | B25: Selene | C25: Follow Up | D25: 45987 | E25: LABPHARMA, LLC | F25: OLIVER MIGUEL | G25: 844-522-2031/ (786) 426-3205 | H25: omiguel@labpharmacorp.com | I25: Tue 9:30PM | J25: FL Based , Mediacre liscenced accepts patients nationwide does immune defiency genetic testing meeting tuesday 9.30pm 2.30 est 11/26 | K25: he doesn't do any Genetic testing ( he doesn't have the equipment for it ) but he might be able to do UTI / blood tests / covid and influenza Meeting next friday same time 9:30 our time - vm 7/20 | M25: 46223.806 | O25: FALSE | Q25: 1437917556
A26: ORT | B26: George | C26: Follow Up | E26: Cabretta Llc | F26: SARAH WAGGONER | O26: FALSE | Q26: 1144950106
A27: ORT | B27: George | C27: Follow Up | E27: Cabretta Llc | F27: JILL HAMAKER | O27: FALSE | Q27: 1144950106
A28: ORT+CGM | B28: Selene | C28: Follow Up | D28: 46002 | E28: VERINA CO MEDICAL SUPPLIES LLC | F28: RAMY WAHBA | G28: 818-479-1585 | H28: info@verinacare.com | I28: Tue 8:30PM | J28: - CA BasedSupplies ORT CGM Medicare via another DME he said he is really interested in getting referrals and wants to talk to us and know more about us meeting next tuesday 10.30 pst 8.30 our time 12/11 | O28: FALSE | Q28: 1053165191
A29: IMMUNE | B29: Jane | C29: Follow Up | D29: 46030 | E29: LIFECARE LAB | F29: ALAA KAHALA | G29: 346-317-2949 | H29: abd_nyk2003@yahoo.com | I29: Thu 11:00 PM | J29: Tx based medicare license , do immuno, pgx and uti, accept pt from all states, he said will give us a call with hs director today asked to send email | O29: FALSE | Q29: 1568358547
A30: IMMUNE | B30: Jimmy | C30: Follow Up | D30: 46045 | E30: US LAB HOLDINGS LLC | F30: VINCENT VITATOE | G30: 816-309-0569 | H30: VINCENT@MODUSlaboratorIES.COM | I30: THU 7:00 PM 29/03 | J30: TX Based UTI - AND FOR NGS PGX CAN DO WITH REFRENCE LAB (WANT TO KNOW HOW MANY WE CAN PROVIDE FIRST) | K30: he is not convinced that he should pay an upfront payment he wants to pay weekly after receiving the Patients, Propability 25%, Doc 02/04/2026 he wants to send this to their billing people and then touch base with the reference lab and try to follow up next thursday 02/12/2026 , send a calender invite for next thursday Chad@MODUSlaboratorIES.COM , Vasco@MODUSlaboratorIES.COM,, we sent him the documents needed they will call us today or tomorrow 02/26/2026 , will send chad information about a person that can help them with the validation and instrument set up , 04/02/2026 i spoke to chad he said that they are still interested but maybe the needed a month to move forward and i sent him a contact info to help him with anything that he needs | M30: 46114.836 | O30: FALSE | Q30: 1013678333
A31: ORT+CGM | B31: Ben | C31: Follow Up | D31: 46057 | E31: LIMITLESS MEDICAL SUPPLIES LLC | F31: SALEF SOBHO | G31: 470-567-6727 | H31: saleh.soboh@yahoo.com | J31: Very interested seems to know what he's doing 2/2 | K31: VM - ben sent email VM - ben vm, ben 7/20 | M31: 46223.948 | O31: FALSE | Q31: 1538033469
A32: IMMUNE | B32: Jimmy | C32: Follow Up | D32: 46044 | E32: PREMIER LAB SOLUTIONS BAKERSFIELD LLC | F32: PETER SIMMONS | G32: 781-626-1212 | H32: peter.simmons@lemedix.com | I32: =HYPERLINK("https://calendar.google.com/calendar/u/0/r/eventedit/N2tzN2JxMzhkNGltMDhyNW05OHNuMDF0azkgYzM5ZjIxNjY2YTJjNzBkNjQ0MDI0YmQyOWM3ZmM5ODM3OTY2MmY3OTJlNWEwNDdjZGIzNTdhNDJiM2M1N2QwNEBn", "THU 6:00 PM") -> THU 6:00 PM | J32: He does UTI, and Can do immune through another lab, can accept medicare PT and accept from all states "Called him and reshcedled the meeting to tomorrow 6:00 pm 2/12/26 (2/11/26 6:07) Meeting rescheduled to 9:00 pm our time 2 pm his time George called him and left him a VM and I called him and he did not pickup 5:09 He did not pickup 1/26/26 5:08 | K32: we need to my seq, Pgx , they need to do gene validation, we need to the machine that they are using and gene validation to do this CPT code , two California and one Chicago validation and sample report and what machines required, lab set up and validation for the NGS, we spoke again on the 12th and he is interested to do NGS if he understand the machinary and lap setup needed alongside the validation VM - ben , I will connect him with dr ajaez to on whatsapp and connect him together | M32: 46155.964 | O32: FALSE | Q32: 1548978034
A33: ORT+CGM | B33: Ben | C33: Follow Up | D33: 46056 | E33: ONE O SEVEN LLC | F33: MARZOOQ LAKHANI | G33: 713-498-5462 | H33: oneosevendme@gmail.com | I33: Thu 5:00 PM | J33: CGM & ORT, Med part B, starting in tx, They can work all states, he said he preferrs if a higher percentage would be from his state (texas) to not flag medicare, seems to have experience | K33: speaking on whatsapp auto vm, ben | M33: 46183.893 | O33: FALSE | Q33: 1174483572
A34: IMMUNE | B34: Ben | C34: Follow Up | D34: 46080 | E34: YOUR LAB TEST TX | F34: CLARISSIA JONES | G34: 214-684-9182 | H34: adisyenterprise@gmail.com | I34: Wed 8:30 PM | J34: Insurance, Only Texas ,Not sure of the tests she can do + Renewing her licenses, | K34: she will act as a middle man | M34: 46080.994 | O34: FALSE | Q34: 1265173389
A35: IMMUNE | B35: Ben | C35: Follow Up | D35: 46084 | E35: ALBANYLABS LLC | F35: SUMANTA GOSWAMI | G35: 347-613-3322 | H35: sumanta.goswami@albanylabs.com, / info@albanylabs.com | J35: Rescheduled with him | K35: Calendly. no ngs but he knows people | M35: 46223 | O35: FALSE | Q35: 1770232423
A36: IMMUNE | B36: Jimmy | C36: Follow Up | D36: 46083 | E36: RUSH LAB LLC | F36: WAQAS MIRZA | G36: 312-520-4582 | H36: wwmirza@gmail.com | I36: MON 11:30 PM | J36: "Immune - UTI - PGx - CGx wwmirza@gmail.com azzedine13@yahoo.com" | K36: he has a dme company and a adam travel agency ABDo ibrahim | M36: 46084.016 | O36: FALSE | Q36: 1144173832
A37: IMMUNE | B37: Selene | C37: Follow Up | D37: 46064 | E37: PATRIOT MEDICAL LABORATORIES LLC | F37: SOMBABU MULLAPUDI | G37: 240-422-4164 | H37: sam@ciandx.com | I37: THU 10:30 PM | J37: - MD Based, Medicare liscenced , Accepts nationwide does NGS meeting tmrw 10.30 our time -selene 2/11 - called x2 no anwer 3/18 | K37: tuesday between 10 - 12 , face to face meeting , so he would revise with his team and discuss everything during the meeting - I spoke to sam he said that our gmail email is not professional and he is concerned with the upfront pricing and wanted to discuss it in tmrw meeting-selene 3/5 - sent email for UTI PGX NGS 7/20 | M37: 46223.823 | O37: FALSE | Q37: 1710300579
A38: IMMUNE | B38: Ben | C38: Follow Up | D38: 46066 | E38: GP QUEST HEALTH CENTER LLC | F38: ELAINE PONS | G38: 786-205-7062 | H38: gpquesthealthcenter@gmail.com | I38: Tue 8:30 PM | J38: FL Based NGS, Mediare B, All states 2/12 | K38: they spilled the coffee in the meeting, they also don't know if they have the right machinary to do the NGS testing , and didn't know if they have it or not they need us to send him the machinary | M38: 46070.871 | O38: FALSE | Q38: 1881491447
A39: IMMUNE | B39: Selene | C39: Follow Up | D39: 46063 | E39: PROLINE LABS | F39: JEFFREY RODRIGUEZ | G39: 915-494-2611 | H39: PROLINELABS@gmail.com | I39: WED 6:30 PM | J39: TX Based, Medicare liscenced accepts nationwide he said he is getting the NGS but he seems new to the work but very interested and wants to know the prices meeting tmrw 6.30 pm our time wed -selene 2/10 | K39: what type of license do you need , High complexity, tomorrow 11:00 am Standard time , 10 am tomorrow 02/13/2026 busy wants us to call him in an hour (busy schedule call him tomorrow) - ben - vm 7/20 | M39: 46223.83 | O39: FALSE | Q39: 1427812916
A40: IMMUNE | B40: Selene | C40: Follow Up | D40: 46057 | E40: SYNERGY DIAGNOSTIC LAB | F40: ADNAN SADIQ/Nadeem (decision maker) | G40: 732 470 4310 | H40: waytogocorp@yahoo.com | I40: Thu 9:30 PM | J40: - AR BasedSpoke to Adnan the owner said they do NGS PGX CGX have medicare and serve nationwide said we should speak tmrw to nadeem the decison maker at 1.30 cst 9.30 our time -selene 2/4 - spoke to adnan said nadeem will be availble after 30 min will cb by then -2/5 | K40: DR NAdeem - approved CMS he was asking about percentage - address / contact info - upfront payment is a nono - 96 plate sample to do it together / 3 to 4 weeks after the report are out / 5 to 6 weeks to get paid - he is not working with TMS and RCE - W2 as an employee / - 35% - he was engaged with an egyptian girl and he knows alot of egyptian | M40: 46085.973 | O40: FALSE | Q40: 1922852169
A41: IMMUNE | B41: Selene | C41: Follow Up | D41: 46073 | E41: HOPE DIAGNOSTIC AND WELLNESS CENTER LLC | F41: MOSES O. ADEYANJU | G41: 618-713-6823 | H41: pathologydiagnostics@yahoo.com | I41: Tue 9:00 PM | J41: IL Based, Medicare liscenced accepts nationwide NGS test meeting tuesday 9 pm our time 2/20 | K41: he was asking about | M41: 46083.881 | O41: FALSE | Q41: 1497476683
A42: IMMUNE | B42: Jane | C42: Follow Up | D42: 46065 | E42: GENESIS DIAGNOSTIC SERVICES INC | F42: Dr. SYED NAVEED | G42: 630-776-5027 | H42: Syednaveedmd@gmail.com | I42: THU 10:30 PM | J42: TX BASED, MEDICARE LICENSED, ACCPT PT ALL STTAES, have alot of labs and e will open a lab in miami florida in couple weeks DO NGS, pgx, cgx BUT he worried about billing , he may act as reffrence lab for us, but willing to iscuss with george. HE THINGK ITS BETTERTO DO FOR ONCOLOGY NOT IMMUNE DEFICIENCY CUZ ITS LESS RISCKY WITH MEDICARE PROTOCOL, | K42: - 96 plate sample to do it together texted me, call to reschedule left a vm will send him an email- ben | M42: 46094.82 | O42: FALSE | Q42: 1326694670
A43: ORT+CGM | B43: Jimmy | C43: Follow Up | D43: 46062 | E43: HEXA DME INC | F43: SATPALJEET SINGH | G43: 917-358-8053 | H43: hexadme@gmail.com | I43: THU 8:00 PM | J43: NY based can do braces and CGM | K43: - 3 to 4 weeks after the report are out -vm , ben | M43: 46183.842 | O43: FALSE | Q43: 1689543522
A44: ORT | B44: Jane | C44: Follow Up | D44: 46083 | E44: GV MEDICAL EQUIPMENT AND SUPPLY, INC. | F44: RAMIN BAROUKH | G44: 310-542-6575 | H44: gvmedicalsupply1@yahoo.com | I44: TUE 12:00 PM | J44: CA based, supply ort , bill medicare licenced, ship alsttaes, meeting tomw AFTER 12 PM OUR TIME | K44: he said that he can only work with doctors / hospitals / assisted living , but no middle men,he says in california that'snot how it goes, long shot probability call him back in a month with a lead generation proposal bad connection, ben | M44: 46183.865 | O44: FALSE | Q44: 1326195926
A45: IMMUNE | B45: Selene | C45: Follow Up | D45: 46080 | E45: DREXEL DISTRIBUTION INC | F45: BEDIS ZORMATI | G45: 917-653-8900 | H45: BEDIS@MEDFILO.COM/ cperezfinancial@gmail.com | I45: Mon 9:00 PM | J45: NY Based Mediacre liscenced does NGS meeting monday 9 pm -selene 2/27 | K45: He is interested but his waiting to get some information about the panel and the payouts from the billing team he messaged me on whats app and told me if there is any update he will give me a call - said wants a follow up call 2pm next thurday 6/24 No longer interested because we are overseas and immune reimbursmenst are low 7/6 | M45: 46209.859 | O45: FALSE | Q45: 1336871607
A46: ORT | B46: Selene | C46: Follow Up | D46: 46084 | E46: ALLY MEDICAL SUPPLY INC | F46: FIRAS ABOLGAR | G46: 312-493-5657 | H46: allymedindiana@gmail.com | I46: Thu 9:00 PM | J46: IN Based , Medicare liscenced , ships locally but can expand nationwide meeting thursday 9 pm | K46: SEND Price list and avg reimbursement for ORT And CGM , next tuesday same time , He will talk to george on whatsapp dnc 3/11 said he will review it and give us a cb dnc doesnt seem that interested 6/3 | M46: 46176.705 | O46: FALSE | Q46: 1528693611
A47: IMMUNE | B47: Jane | C47: Follow Up | D47: 46063 | E47: RUTHENIUM DIAGNOSTICS LLC | F47: ROBERT WILLIAM CACAL | G47: 808-386-3669 | H47: robert.cacal@genviewdx.com | I47: THU 10:00 PM | J47: Tx based they do the primary immuno deficeincy ngs, medicare licensed and accept patients from allstates, meething thursday 10 pm our time , 2pm | K47: meeting today pm ourtime, asked to cb after 20 min VM - ben | M47: 46094.827 | O47: FALSE | Q47: 1740940956
... A59: CGM | B59: Ben | C59: Follow Up | D59: 46132 | E59: EXPRESS PHARMACY & DME | F59: DANIEL AMOH | G59: 210-981-9690 | H59: danrph.md@gmail.com / anc@pdmhealthcare.com | I59: THU 19:00 PM | J59: OH Based, CGM, Medicare, dropshipping, knows process and cgm hourly | K59: He wants a presentation for all the service and the billers he is interested in CGM , they are trying to do 30 patients a month , he wants a presentation before wednesday 4 pm 29th , he wants palmetto website , pdf of the states , price module pay per hour and pay per referral , a meeting on friday 2:30 pm to both emails VM | M59: 46248.749 | O59: FALSE | Q59: 1588394605
A60: IMMUNE | B60: Jimmy | C60: Follow Up | D60: 46128 | E60: MEDICON CLINICAL LAB LLC | F60: MAGDA GAD | G60: 973-910-6632 | H60: mediconbroad26@yahoo.com | I60: FOLLOW UP | K60: she wanted to know what tests can we do , and she is interested in toxicology and she is thinking about 25% to 30% from the reimbursements and she wanted a google sheet with all the tests and their average reimbursements , she wants a list of all our test , cpt codes and the average reimbursments and what we charge so she can her percentage on it | M60: 46149.909 | O60: FALSE | Q60: 1902546310
A61: IMMUNE | B61: Jimmy | C61: Follow Up | D61: 46135 | E61: SIX POINT CONSULTING LLC | F61: DONOVAN SHULTZ | G61: 318-884-0552 | 318-237-6572 | 318-475-5425 | H61: dshultz@six-point.org | I61: Fri 8:00 PM | J61: LA Based, Can do NGS and can accept medicare PT | K61: he is doing around couple of hundereds of patients a month he will discuss it with the board he wants another meeting next friday same time and he would review the contract and the doctor order sample with his team and if he is interested next meeting we will talk about numbers | M61: 46136.947 | O61: FALSE | Q61: 1073478590
A62: IMMUNE | B62: Ben | C62: Follow Up | D62: 46133 | E62: XAVIER INTERNATIONAL LABORATORIES | F62: DANIEL XAVIER | G62: 786-320-3328 | H62: xavierinvestmentgroupllc@gmail.com | I62: TUE 9:00 PM | J62: FL Based, Medicare, NGS, can do out of state patients 4/21 | K62: Next tuesday, 3 pm est, good candidate, he will ask about the reimbursement, he do about 50-65, he worked with marketers before, let's do a follow up on thursday same time he got me the reimbursements for PGX and immuno and he wants a a quarter map for how we can do business togetherand what will work best for him and how we can mix it together, ben i need you to look to other emaiils from him and us to be able to send something out today , I SENT HIM A PROPOSAL 05/05/2026 meeting on monday 8/14 | L62: he got me the reimbursements for PGX and immuno and he wants a a quarter map for how we can do business togetherand what will work best for him and how we can mix it together, ben i need you to look to other emaiils from him and us to be able to send something out today | M62: 46248.749 | O62: TRUE | Q62: 1669132809
A63: DMEDESK | B63: Jimmy | C63: Follow Up | D63: 46148 | E63: PRISTINE MEDICAL EQUIPMENT AND ACCESSORIES INC | F63: Kacey | G63: 410-720-9002 | H63: info@pmeACCESSORIES.com | I63: Thu 5:00 PM | J63: She wants to know more about the service and how it can help her business | K63: He will be sending her more infor and she will check with her team and follow up with us ( GEORGE ) . she is not interested any more maybe in couple of months 06/19/2026 | M63: 46192.745 | O63: FALSE | Q63: 1265249098
A64: IMMUNE | B64: Jimmy | C64: Follow Up | D64: 46146 | E64: VK DIAGNOSTICS | F64: AJAY KOHLI | G64: 630-677-4534 | H64: ajay@kohealthtech.com | I64: Tue 8:30 PM | J64: TX based, can bill medicare, and run NGS | K64: cohealth labs , this is the newlab name, he is very skyptical about the compliance and he wants to read the contract with the fixed amount fee and to review it with his team, he wants a specific explanation about the process the fees to be paid, i will send over an email for him | M64: 46147.92 | O64: FALSE | Q64: 1750060505
A65: IMMUNE | B65: Jane | C65: Follow Up | D65: 46134 | E65: EXCELSIOR DIAGNOSTIC LABORATORIES | F65: IRFAN S CHAUDHRY | G65: 917-364-9486/ 718) 808-2822 | H65: excelsiordiagnosticlab@gmail.com | I65: THU 6:00 PM | J65: NJ based he do the ngs and the ngs machine , he said they are caped for now but will be able to start in month, he bill medicare a, accept patients nation wide , and would like to know more about us in a meeting tomw before we start all over when he is ready4/22 | K65: he is interested to resume talks on the 14th of may 12 pm, he is already working with other marketers and looking to expand he wants us to send him our contract for him to send it to his attorney, send the regular email, if you are already send it send the contract in a different email and a calender invit , he is doing immuno neuro and cardio and cgx e on the 14th , you are waiting on audit from 30 to 60 days, still on audit when he is done will reach out to us. | M65: 46232.739 | O65: FALSE | Q65: 1902250186
A66: IMMUNE | B66: Jane | C66: Follow Up | D66: 46139 | E66: GENOME INSIGHT INC | F66: VEENA SINGH | G66: 8582043649 | H66: veesingh08@gmail.com | I66: Wed 12:00 PM | J66: Ca based able to do ngs ,bill medicare ,accept pt allstates | K66: send the CPT codes / what kind of tests and the reimbursmenets , he wants to summarize everything on an email on friday or early next week , need a follow up next week , she will work as a middle man , call her next friday if you find out the reimbursements | M66: 46142.009 | O66: FALSE | Q66: 1881462752
A67: IMMUNE | B67: Jane | C67: Follow Up | D67: 46136 | E67: PINNACLE BIOLABS, INC | F67: ANSHUMAN LUV BAKSHI | G67: 512-909-8867 | H67: banshumanluv@berkeley.edu | I67: Mon 5:00 PM | J67: Tx based, do ngs and has the machine, bill medicare and accept pts from allstates 4/23, sent email | K67: follow up meeting on friday whatsapp group , he will introduce me to a lab in florida, me and him and mike and his referral will talk tomorrow night, he will create a group chat and we will decide the exact time | M67: 46160.932 | O67: FALSE | Q67: 1104693746
A68: IMMUNE | B68: Ben | C68: Follow Up | D68: 46143 | E68: SEHTEJ LLC | F68: HARWINDER KAUR (SONIA) | G68: 386-717-0081 | H68: blooddraw.info@gmail.com | I68: FRI 8 PM | J68: Sonya,NGS, Medicare phlebotomy but said they can do, wants an email first 3/30 got the email, 4/29, wants a meeting | K68: Collection site, will agree on a referral program where she is getting a profit share for free 3-6 months | M68: 46146.765 | O68: FALSE | Q68: 1447023353
A69: ORT+CGM | B69: Selene | C69: Follow Up | D69: 46136 | E69: ROSELITE LLC | F69: MUHAMMAD IMRAN GHAFOOR | G69: 716-787-0552 | H69: imrancallmeny@hotmail.com | I69: =HYPERLINK("https://calendar.google.com/calendar/u/0/r/eventedit/NjFjNGI5Z2kwYWY2anFtdmE1Y2FqZjFmb20gYzM5ZjIxNjY2YTJjNzBkNjQ0MDI0YmQyOWM3ZmM5ODM3OTY2MmY3OTJlNWEwNDdjZGIzNTdhNDJiM2M1N2QwNEBn?pli=1", "Mon 5:30 PM") -> Mon 5:30 PM | J69: NY Based, medicare liscenced , said can ships nationwide supplies ort cgm said wants a call on mon 5.30 our time -selene 4/24 said he will review it this week nd will send us an email said to text him company name and number 5/5 | K69: He wants a road map for our process and the price list for Cgm and orthopedic braces and the contrac also leave my contact information because he will call me to discuss things over said to text him, ben , he wants to see the marketing plan for ORT and CGM and talk again next wednesday same time Said he wants to reschedule he had a busy day, will send him calendly link selene might call him - ben 6/24 | M69: 46197.674 | O69: FALSE | Q69: 1871440354
A70: CGM | B70: Selene | C70: Follow Up | D70: 46142 | E70: FIRST CALL MED SUPPLIES, LLC | F70: Andrew Clayton Ledbetter/sarah | G70: 704-472-0933/980-429-1019 /sarah | H70: FIRSTCALLMEDSUPPLIES@GMAIL.COM / | I70: =HYPERLINK("https://calendar.google.com/calendar/u/0/r/eventedit/NWE3aHN0ZW5yNDQ1aDFtcTBrY2ExMGtvZWogYzM5ZjIxNjY2YTJjNzBkNjQ0MDI0YmQyOWM3ZmM5ODM3OTY2MmY3OTJlNWEwNDdjZGIzNTdhNDJiM2M1N2QwNEBn?pli=1", "Tue 11:00 PM") -> Tue 11:00 PM | J70: NC Based, Medicare liscensced , CGM , ships all states said he wants a video meeting tuesday 4 pm est 4/30 980-429-1019 /sarah | K70: Called Mr Ledbetter to confirm that he recieved the email and he said he is a bit busy and might ot be able to attend the meeting but sarah his partner can she gave me her number and i told her on what we do/ call her at 980-429-1019 /sarah , we need to send the contract and the two proposal the pay per hour and pay per referral, next meeting friday same time , 05/08/2026 , I TRIED CALLING both andrew and sarah but no luck | M70: 46150.961 | O70: FALSE | Q70: 1063143303
A71: ORT+CGM | B71: Selene | C71: Meeting Attended | D71: 46136 | E71: MBS TRADERS | F71: BUSHRA NAWAZ | G71: 929-645-5952 | H71: mbstradersllc@hotmail.com | I71: Mon 10:00 PM | J71: NY Based, medicare liscenced , said can ships nationwide supplies ort cgm said wants a video call on mon 10 pm our time -selene 4/24 | K71: they are pakistanians, they have a call center in pakistan and a biller from pakistan, they got everything covered but they want to see our prices, they won't agree on an upfront payment, probability is low to work with us , call you back later | M71: 46175.825 | O71: FALSE | Q71: 1164399648
A72: IMMUNE | B72: Jimmy | C72: Follow Up | D72: 46154 | E72: HEALTHQUEST DIAGNOSTIC LABORATORY INC | F72: SONNY PATEL | G72: 909-203-9763 | H72: sonnyp007@gmail.com | I72: Tue 7:30 PM | J72: He can do immune, PGX, and UTI, he wants to know our volum and discuss further information | K72: they are getting around 1000 samples in a month for all tests, everything about the pricing , about our modules, and the tests that we provide, , tuesday same time , he is also asking about what other tests can we work with and he will check our pricing and come with a counter offer if he don't like it , set the meeting next tuesday same time , voice mail " | M72: 46161.862 | Q72: 1326651670
A73: ORT+CGM | B73: Selene | C73: Follow Up | D73: 46160 | E73: MEDAXIS SOLUTIONS LLC | F73: IQRA MUBEEN | G73: 909-737-1774 | H73: admin@apexhealthsolutions.live | I73: Tue 7:00 PM | J73: CA Based, ORT CGM Medicare liscenced meeting tmrw video 7 pm our time 5/18 -already working with other company that give him leads /billing he wanted to know our prices and asked me if we know suppliers who will help him drop ship 5/20 - Still discussing with his team said will reach out if they want to discuss more 6/2 said to give him a acb 7/28 | K73: he is interested to know the prices the two modules for orthopedic braces Ben Arthur please send them over , they are still discussing this with the team, follow up 06/09/2026 said call in an hour, ben - wants to talk evebing time 4 pm isuuse is he is in ca 7/29 | M73: 46232.684 | Q73: 1396686432
A74: IMMUNE | B74: Jimmy | C74: Follow Up | D74: 46163 | E74: H&M MOLECULAR DIAGNOSTICS, LLC | F74: JOHN BELLANO | G74: 267-337-0576 | H74: johnbellano@integrity-sciences.com | I74: FRI 7:30 PM | J74: He booked the meeting himself | K74: he is only doing PGX ( don't want to focus on medicare only, he wants to get other insurances as well ) he is looking for capital to help him expanding the business, he wants an email containing our scope of work / compliance structure and maybe a quotation for how much he would pay for 100 patients a month ( just an example ) / 898 200$ Reagenet + over head + shipping mobix labs on the ordering physician has to be the treating physician , he wants a marketing plan also | M74: 46184.931 | Q74: 1598260986
A75: ORT+CGM+LYMPH W | B75: Jimmy | C75: Follow Up | D75: 46168 | E75: AJK MEDICAL EQUIPMENT LLC | F75: TABASSUM REHMAN | G75: 312-799-9050 / 8474544975 | H75: trehman@sbcglobal.net Naheed.mir1234@gmail.com | I75: THU 7:00 PM | J75: she can not bill medicare herself but her partner can, she wants to partner up and do business all three, she can do ort+lymph+cgm | K75: she has a private insurance only not medicare and she has a doctor that can bill medicare , and a friend that has medicare license , Send a price list for braces and ort and contract for her to review then follow up with her on wednesday to make sure that she read this , blue cross, humana aetna, | M75: 46176.885 | Q75: 1487506564
A76: DMEDESK | B76: Jane | C76: Follow Up | D76: 46181 | E76: TARR GLOBAL ENTERPRISES LLC | F76: TEREA ROSE | G76: 8328726881 | H76: tmdiagnostics@tarrglobalent.org | I76: Tue 10:00 PM | J76: Tx based, she supply cgm and cpap and wheelchairs, she handles the in bound calls but whant to know more how the outbound call could be handled for her | Q76: 1356288609
A77: ORT+CGM+LYMPH W | B77: Selene | C77: Follow Up | D77: 46185 | E77: JAYCEE DME LLC | F77: JONATHAN CUMBERBATCH | G77: 917-865-6258 | H77: jayceedme@yahoo.com | I77: Mon 9:00 PM | J77: NY Based , ships locally , PPO (will look at the list of insurance he works with and will discuss it in meeting ) supply ORT CGM Lymph meeting mon 9 pm 6/12 | K77: he desn't have any insurance no medicare and 1 private insurance he will apply for more - still applying for inurance still not accepted 7/20 | M77: 46223.872 | Q77: 1861280836
A78: DMEDESK | B78: Jane | C78: Follow Up | D78: 46183 | E78: NET TIME INC | F78: ASHRUF KHAN | G78: 8172391243 | H78: admin@ai1ms.com | I78: Fri 8:00 PM | J78: TX based, asked about the outbound calls and wantto know the price an explore more | Q78: 1558466243
A79: ORT+CGM | B79: Ben | C79: Follow Up | D79: 46154 | E79: DME BRACES LLC | F79: PAUL DIAMOND | G79: 718-864-3150 | H79: dmebracesllc@gmail.com dmemedicaldevices@gmail.com | I79: Tue 8:00 PM | J79: NY Based, Medicare B, wanting to open a new LLC, alr has marketers for his current dme (said they are too expensive), but needs new marketers for the new one 5/12 | K79: he mainly does Private insurance no medicare license, he will open another LLC to work with us will propaly take around 2 months to open but he is mainly interested to work with private insurance but he will try to apply to medicare license, , he got an appliance company that work within the tri state area, he is contacting me via whatsapp and he needs me to send him an email contact information | M79: 46154.876 | Q79: 1689524837
A80: DMEDESK | B80: Ben | C80: Follow Up | D80: 46149 | E80: MEDIHARBOR LLC | F80: THOMAS JOHNSON | G80: 607-795-6447 | H80: contact@mediharbor.net | I80: Mon 5:00 PM | J80: NY, Software Engineering guy, knows some about the stuff 5/7 | Q80: 1659250082
A81: ORT | B81: Ben | C81: Follow Up | D81: 46149 | E81: MOTOLA MEDICAL SUPPLY INC. | F81: ABIODUN DAYISI | G81: 718-613-9095 | H81: motolamedical@outlook.com | I81: FRI 5:30 PM | J81: NY, Medicare active, gave him info about dmedesk but he said he didnt have that many patients and he does braces, couldn't not offer him patients | K81: doesnt believe palmetto nor free zone states, need to send him those and try to talk him into shipping all states he didnt see the email, spoke with him reexplanied and asked him to check his biller, still fears about medicare and the states thing, also wants us to refer him a biller vm | M81: 46248.75 | O81: FALSE | Q81: 1396320032
A82: ORT+CGM+LYMPH W | B82: Selene | C82: Follow Up | D82: 46174 | E82: GERMAN CARE MEDICAL SUPPLIES LLC | F82: CHOWDHURY FOYSAL AHMED | G82: 929-569-7139 | H82: foysal.chowdhury292@gmail.com | I82: Tue 8:00 PM | J82: NY Based, Medicare liscence, Nationwide supplies ORT ,CGM,Lymph compression meeting tmrw 8 pm video -selene 6/1 | K82: he wants another email and he wants to speak to his partners, he wants to know more info about the prices and what we do and let's do another call on thursday to talk it over / VM 06/04/2026 said will call me back 7/20 said to give him a acb 7/28 said to send him prices and marketing plan via email and what sapp cb tmrw 7/29 | M82: 46232.689 | Q82: 1912841677
A83: DMEDESK | B83: Jane | C83: Follow Up | D83: 46156 | E83: ATZ MEDICAL & RESPIRATORY INC | F83: Mr. Joel Katz | G83: tel:855-272-1900,ext101 | H83: office@atzmedical.com | I83: Thu 8:00 PM | J83: He was interested to know the price for this services | Q83: 1528713112
A84: DMEDESK | B84: Jane | C84: Follow Up | D84: 46155 | E84: CARTER MEDICAL EQUIPMENT & SUPPLIES | F84: Latitia Carter | G84: 214-527-6621 | H84: cartermedicalsupply@gmail.com | I84: THU 9:00 PM | J84: She usually works alone and want the ai assistant as receptionist , taking nots and do the verfication for insuransea and takes notes, thats what she was looking for because her patients are frustrated she is not answereing while she is out of store, she wanted to know the prices and how it works | Q84: 1770281214
A85: DMEDESK | B85: Ben | C85: Follow Up | D85: 46157 | E85: DIGITIXMD LLC | F85: YOUSAF ZUBAIR | G85: 267-277-7536 | H85: yousaf@digitixmd.com | I85: Mon 5:00 PM | J85: PA Based, he get around 10-20 inbound calls a week, he still waiting to get the medicare license, he only have private insurances like humana and also got medicaid , main concern is to be complient and also the pricing must be good as he is a new company and not making alot of revenues | Q85: 1801692546
A86: IMMUNE | B86: Jane | C86: Follow Up | D86: 46148 | E86: SAFEHAUL SCREEN LLC | F86: QUACHANDRA HAWKINS | G86: 229-938-2486 | H86: quachandrahawkins@yahoo.com | I86: Tue 6:00 PM | J86: Ga based, do ngs immune defiency and pgx a, bill medicare and accept patients all states,meeting on tuesday 11am est 5/6 | K86: reschduled today 11 pm, she was a bit irritated on the call and kept asking for how much not interested to hear the process so i will send her the price list and if she agrees she will replay to the email , 06/09/2026 voice mail | M86: 46182.902 | O86: FALSE | Q86: 1962375709
A87: ORT | B87: Jasmine | C87: Follow Up | D87: 46195 | E87: ZYPHRA HEALTH LLC | F87: DALJIT SINGH | G87: 479-262-0410 | H87: uchimata770@gmail.com | I87: TUE 7:00 PM | J87: He has off the shelf braces and is interested in knowing more about what we do / accepts medicare patients and operates nation wide. | K87: his real name is yacoub from pakistan, he is interested about doing ORT PPO only and he asks us if we can provide them with a biller, i need to send him Marketing plan for ORT and a contract + ask him 3 questions in the email , List of insurances that he can cover , list of good states , what products he wants to promote for ( ORT , CGM , Lymph , Wheel chairs ), Also i will talk to him later today to introduce a biller | M87: 46196.851 | Q87: 1013848647
A88: Lymphadema | B88: Jane | C88: Follow Up | D88: 46168 | E88: LYMPHMED LLC | F88: Moshe Blinder / noah (operation manager) | G88: 718-387-5504 / 516-347-4271 | H88: moshe@discountsurgical.com / noah@lymphrx.com | I88: Tue 5:00 PM | J88: Ny based, medicare licensec, ship allstaes supply lymphadema wraps | K88: he wants to get on a google meet to discuss everything friday afternoon, waiting for his text to confirm the exact time Doc 01/13/2026/ now only interested with lymphadema wrap but if we had surplus paitents for lymphedema wrapsd we can contact him 2/5, i spoke to noah he was a bit interested and he told me he will try fto get moshe over the phone and then call me | M88: 46168.884 | Q88: 1073363875
A89: ORT+CGM | B89: Selene | C89: Follow Up | D89: 46164 | E89: B & A PHARMACY CORP | F89: DAVID NNAWUIHE | G89: 856-278-1899 | H89: BAPHARMACY22@GMAIL.COM | I89: Tue 7:00 PM | J89: PA Based, Medicare liscenced , ORT ,CGM meeting tuesday 7 pm our time video meeting -selene 5/22 | K89: I spoke to david he only said that he is interested in the CGM, He wants to know the reimbursements and the cost and how many can we get him , also send him the presentation / hung up cb later 7/20 | M89: 46223.874 | Q89: 1215307772
A90: ORT+CGM | B90: Selene | C90: Follow Up | D90: 46160 | E90: USA DME SUPPLY INC | F90: AKWASI APPIAH | G90: 267-560-0562 | H90: akwasi@1800dme.com | I90: Tue 10:30 PM | J90: PA Based, Medicare liscenced , ORT ,CGM said wants to recieve a phone call tmrw 10.30 our time | K90: - said cb in 30 min , send the presentation / modules for pricing for both CGM and ort , call back tomorrow vm 7/20 | M90: 46223.875 | Q90: 1609735430
A91: ORT + Lymphedema | B91: Selene | C91: Follow Up | D91: 46156 | E91: MED SUPPLY PROS LLC | F91: FRANCKY BASTIEN | G91: 407-963-7299 | H91: medsupplyprosllc@gmail.com | I91: FRI 6:00 PM | J91: FL Based, Medicare liscenced ships nationwide ort meting 6.00 pm our time fri (wazowski lead) -selene 5/14 - Spoke to francky said that he supplies Lymph products but he only works as PPO (humana /eitna ) said wants to know more details about prices and how it works 6/2 | K91: he has 2 companies, one he worked with a pakistanian call center and they scammed him and another one he just opened, he is not sure that he is medicare licensed most probably he isn't he is only doing private insurances, he is looking for a biller but once he starts working again , we will have another meeting on tuesday same time so he can check which insurances does he have and get back to me, - spoke to francky said will email george today,spoke to his partner about the work 6/15 , he has a realestate business also / vm 7/29 | M91: 46232.72 | O91: FALSE | Q91: 1962296715
A92: Lymphadema | B92: Ben | C92: Follow Up | D92: 46174 | E92: ILY-LARC LLC | F92: YVONNE NKWEN-TAMO | G92: 702-985-9120 | H92: ilylerc@gmail.com | I92: THU 12:00 AM (Wednesday) | J92: NV, Provide ORT CGM, she said she Bills for medicare then she said its still in process discussed lymphadema priv insurance, didnt explain much | Q92: 1033091152
A93: ORT+CGM+LYMPH W | B93: Jasmine | C93: Follow Up | D93: 46195 | E93: REGIONS HEALTHCURE LLC | F93: FARAZ ZAHEER | G93: (732) 762-9955 | H93: deepbluehealthcare@gmail.com | I93: Tue 9:00 PM | J93: He mentioned having ORT/CGM/LYMPHEDEMA and is interested in knowing more and has some questions regarding the quality wants to try it for a week first and see the results as he has 5 DMES (humana/aetna/welmed/welfare commercial insurances) ships nation wide | K93: he has a couple of dmes that he is managing + 2 labs, He can work in private insurances in the dme space insurances are ( humana / cigma . anthem / zing / well med) , and medicare in labs , he is interested to know more about our pricing, so have ben send out the marketing plan for ORT and the Price per brace + the marketing plan for the labs , Also in the email send him the question about what prices do you have in mind for the Private insurance ( pay per referral module) and the calender link to book an appropiate timing with him | M93: 46196.908 | Q93: 1982490520
A94: DMEDESK | B94: Jimmy | C94: Follow Up | D94: 46189 | E94: GOOD SAMARITAN MEDICAL | F94: ANGELA KING | G94: 734-604-8688 260-960-9055" | H94: aking@goodsammed.com | I94: WED 9:00 PM | J94: She wants to discover the AI service and how it can help her Business | Q94: 1962453134
A95: ORT+CGM+LYMPH W | B95: Jimmy | C95: Follow Up | D95: 46196 | E95: STRYKEFOX MEDICAL | F95: ADAM STRYKER | G95: 612-499-6561 | H95: adam@strykefox.com | I95: WED 8:00 PM | J95: Can do all products, can accept medicare PT and asked me if we can do private I said yes we can | Q95: 1821959420
A96: ORT+CGM+LYMPH W | B96: Jimmy | C96: Follow Up | D96: 46199 | E96: WELLNESS MOBILITY SOLUTIONS INC | F96: SABRINA MORGAN | G96: 302-342-0828 | H96: WELLNESSMOBILITYSOLUTIONS@Gmail.com | I96: MON 6:30 PM | J96: OK Based can do all 3 products, can ship nation wide, and can accept medicare PT. she will get her partner included in the meeting | K96: Send the contract and the pricings and follow up on tuesday same time if she did not get back to us she wants to start with sth of 20 PTs | M96: 46202.794 | Q96: 1225901960
A97: ORT | B97: Jimmy | C97: Follow Up | D97: 46037 | E97: JFB DISTRIBUTORS & DELIVERY SERVICES INC | F97: JULIET KALUNGI | G97: 617-502-0784 | H97: jfbDISTRIBUTORS@outlook.com | I97: MON 9th 6:00 PM | J97: MA based supply ort , shipp alls states,medicare licensed | K97: she doesn't have credentials for both orthopedic braces and cgm devices, I talked to stephanie ( her biller ) and she said the same thing | M97: 46084.92 | O97: FALSE | Q97: 1790494649
A98: ORT | B98: Jane | C98: Follow Up | D98: 46213 | E98: CIMA CARE DME, INC | F98: ANA VAZQUEZ MORALES | G98: 786-326-7017 | H98: mainoffice@cimacaredme.com | I98: Mon 5:30 PM | J98: FL based, medicarebill, ship localy and willing to drop ship to other states, supply only ort, MEETING ON MONDAY 10 AM EST | K98: she didnt review it yet and want to disscus it with her partner and call me back by end of the week, she moved out and doing her accredzation, so she can work now | M98: 46251.745 | Q98: 1629742614
A99: ORT + Lymphedema | B99: Jasmine | C99: Follow Up | D99: 46203 | E99: DOCTORS EQUIPMENT SERVICE INC | F99: Anthony Gorsek | G99: 816-523-6644 | H99: anthony@drsequip.net | I99: TUE 8:00 | J99: MO,KS BASED BUT CAN SHIP NATIONWIDE / ORT/LYMPHEDEMA (medicare, humana, aetna, some united and more) Anthony Flathers is the operation manager and he mentioned that they are interested in marketing recently they have a little background with marketing | K99: Meeting attended he wants ORT and can dropship nationwide so sent him an email containing the marketing plan for ORT and the contract to review and will follow-up with him on Friday 7/10 | M99: 46210.956 | Q99: 1487855532
A100: CGM | B100: Selene | C100: Follow Up | D100: 46203 | E100: MEDICO PHARMACY LLC | F100: ALEX OUZA | G100: 313-587-0212 | H100: ouza22@gmail.com | I100: Wed 6:00 PM | J100: MI Based, CGM Only, Medicare liscenced and all insurance too work MI only meeting tmrw 5.30 our time | K100: Meeting attended wants ORT sent marketing plan meeting follow up 11 am tmrw 7/1 , he wants to follow up on monday , he is super sick , but he is interested - George put him in whatsapp group and george will send the info 7/20 - call to get whats app 7/24 | M100: 46227.822 | Q100: 1386356368
A101: ORT | B101: Selene | C101: Follow Up | D101: 46198 | E101: GREEN MEDICAL SUPPLY LLC | F101: HAMID HAMID | G101: 313-844-0948 | H101: greenmedicalsupplyllc@gmail.com | I101: Thu 8:00 PM | J101: MI BASED wants to work PPO in MI only for braces works with humana / Bluecross blue shield | K101: he gave me the prices and the insurances that he can work with, I told him i will check with the team and get back with him, So we need to send him a price list ( i will prepare it ) for the PPO leads + contract , tomorrow 12:30 EST MI State only Humana meriedian mclaren BCBS commercial plan PPO, he might work with medicare ( strict criteria ) vm 7/29 some of them BSBC they get billed with north wood and they can't accept it if it's BCBS | M101: 46232.726 | Q101: 1245961226
A102: ORT | B102: Selene | C102: Follow Up | D102: 46210 | E102: GLOBAL E-LINK LLC | F102: SHUJAD ZAIDI | G102: 346-332-7278 | H102: iceman625@hotmail.com | I102: FRI 7:00 PM | J102: TX Based, Medicare LIscenced , PPO but more comfertable with PPO because of medicare issues ORT CGM and they also have immune lab nationwide meeting Friday 7 pm our time 7/7 | K102: Spoke with mike send prescriptions ORT / Lab samples / contarct for immune / ORT call back next week / said will review it today/ left a vm 7/16 said that he is interested in uti sti pgx / ngs bit difficult / fraud concern / asked prices / cb next monday to set date / left vm and email 7/29 spoke to zaidi said he has problem with medicare and he ows them 65000 dollars said he will fix his problems and will get back to us 7/29 | M102: 46232.829 | Q102: 1750238564
A103: ORT+CGM | B103: Selene | C103: Follow Up | D103: 46209 | E103: REVIVE PHARMACY LLC | F103: ZIAD GAMAL ABDELNABI | G103: 973-449-0091 | H103: revivepharmacy3@gmail.com | I103: Tue 10:30 PM | J103: NY Based, CGM and ORT , Medicare liscenced , locally meeting tmrw 10.30 our time 7/6 | K103: he is an egyptian pharmacist , he is interested but he will check with the billing team what insurance and what states to work with , and to see the availability to do audits , please send him my contact information | M103: 46218.892 | Q103: 1740003052
A104: IMMUNE | B104: Jane | C104: Follow Up | D104: 46209 | E104: NFINITY INNOVATIVE SOLUTIONS LLC | F104: KIMBERLY GHOLAR | G104: (844) 244-2430/ 912-294-1284 | H104: KGHOLAR@NFINITYSOLUTIONS.INFO | I104: THU 8:00 pm | J104: Ms based do immune deficiency test, she owns two labs but dont have the machine do it in other lab, medicare licensed, accept allstates , meeting on thursday | K104: called back and asked to reschedule on thursday 1;30 cst, send a marketing plan for immune , set a meeting on tuesday 9:30 our time, i called her and she said she cant pay upront she dont have the budget for that, she said it a great oppourtunity but she dont have the money can cover that even to pay 50|% up Front , i told her will check with the team if their is discount | M104: 46233.736 | Q104: 1114781408
A105: IMMUNE | B105: Jimmy | C105: Follow Up | D105: 46202 | E105: TEST AND GO LABS | F105: BREYONA STEWART | G105: 317-746-3263 | H105: testandgolabs@gmail.com | I105: TUE 8:00 PM | J105: Called her she said that last time she was having a probelm with her phone that is why she could not attend WED 8:30 PM 7/6/26 10:46 She is a collection site, she works with Lap corp and CRL I mentioned that we ask for a marketing fee and she said that this is sth acceptable from her side | Q105: 1629919642
A106: IMMUNE | B106: Jane | C106: Follow Up | D106: 45993 | E106: WEST DIAGNOSTICS L L C | F106: SAED SADEGHI | G106: 310-962-9523/ 310-882-6132 | H106: contact@sholdingsllc.com/ admin@amgdx.com/, saedsadeghi2721@gmail.com | I106: Wed 6:30 PM | J106: CA based, medicare licensed, accwepts pt all states,he can provide the test we need what know what we want and the volume of samples he open a lab every 3 month and now working on doing on new one asked to call him 8;30pst | K106: he will aquire a Lab a florida, he is interested but he would be able to work in july , he is interested in PGX and immuno | M106: 46066.894 | O106: FALSE | Q106: 1831989458
A107: IMMUNE | B107: Jane | C107: Follow Up | D107: 45943 | E107: PRECISION DIAGNOSTICS LABORATORY LLC | F107: Raul Pardo handle everything amd marketing / MICHELLE ROCHA owner | G107: raul 7862626143 / office 7866236886 | H107: rpardo@precisiondiagnosticslab.com | I107: Tue 9:00PM | J107: Fl based , do genetic testing for immuno deficiency, uti, pgx, cgx, bill medicare and serve for allstates except new york asked about the volume of referrals, said tomw 2 pm meeting | K107: wants an email for everything that we do , they handle very large volume from 200-300, he do everything inhouse but he might think that our prices are a bit high Send him an email with a contract and everything (meeting friday 2:00 pm ) they are not taking any new clients, george's proposal - ben, he said the pipe line is full for now but if ther is anychance for uti , will get me an update and call me | M107: 46223.951 | O107: FALSE | Q107: 1467294769
A108: Lab | B108: Jasmine | C108: Follow Up | D108: 46220 | E108: LUX Diagnostics (APL) | F108: JONATHAN GOSS M.D. | G108: (713) 819-6417 | H108: jonathan@gossmd.com | I108: MON 9:30 PM | J108: NY and GA BASED / metabolic tests, UTI, STI, molecular / medicare and private insurances he has worked with similar companies before so a little skeptical and will have questions | K108: GA based lab, he wants to work mainly on PCT (UTI specifically), we sent him the marketing plan and the contract so he and his lawyers can review them and scheduled a follow-up meeting for WED 9:30 our time, also asked him in the email his preferred states and insurances and whether he wants to proceed in the annual contract only with UTI or add another test | M108: 46223.92
A109: ORT + Lymphedema | B109: Jane | C109: Follow Up | D109: 46212 | E109: ANGIOGENESIS MEDICAL LLC | F109: PATRICK SCALLAN | G109: 225-364-2400 | H109: patrick@agenmed.com | I109: Tue 7:00 PM | J109: LA BASED supply ort and lymphadema wrap, bill medicare , ship alstates, meeting 7 tuesday | K109: he said he is swapmed with patients now asked to call end of the week to rescdule another one, still busy will all me when avalible at end of week call him back, HE IS INTERESTED MORE IN ORT BACK BRACE, WANT TO TAKE 5 OR 10 PT ASKED TO FOR THE PRICES PER LEAD OR PT, SAID TO CALL HIM BACK NEXT WEEK HE WANT TO WORK WITH US BUT WANT TO DO MORE RESEARCH ABOUT US, ask to call him tomw he is busy today, asked to call him back after 10days, he will give me his last desicion after checking this if its okay to do that with medicare | M109: 46245.736 | Q109: 1427561679
A110: Lab | B110: Jasmine | C110: Follow Up | D110: 46232 | E110: LIHIM TECHNOLOGIES, LLC | F110: Cassandra (Office Manager) | G110: 877-361-3627 | H110: info@lihimtech.com | I110: Thu 7:30 PM | J110: TX BASED / she confirmed UTI, CMP BMP (metabolic) and maybe NGS and Immunodeficiency / they accept medicare and private insurances(Follow-up rescheduled for thursday 7:30) | K110: Licensed in TX, LA, AR / can do PGx and UTI, but still waiting for confirmation about the immunodeficiency (NGS) / sent her the marketingplan for all three and the contract for review and scheduled a follow-up meeting for WED 6:00 / she confirmed that they can do NGS in-house | M110: 46237.785
A111: MLA | B111: Jimmy | C111: Follow Up | D111: 46234 | E111: ADT | F111: Jerome | G111: 352 443 9760 | H111: JARich@adt.com | I111: MON 10:30 | J111: Have been following up with him thru the email and we sat a time to discuss how we can do business together
...

Sheet Contract Sent
A1: SUB | B1: Opener | C1: Status | D1: Date Added | E1: Company Name | F1: Authorized Person | G1: Phone | H1: EMAIL | I1: Meeting Time | J1: Opener Summary | K1: George's Notes | L1: Auto Scheduler | M1: Last Call | N1: Action | O1: Checkbox | P1: Log | Q1: NPI
A2: ORT+CGM | B2: Ben | C2: Contract Sent | D2: 45554 | E2: Aa Medical Supply Inc | F2: Richard Yousif | G2: 586-933-6565 | H2: richard@aamedsupplies.com | K2: He is on vacation now, he will be back to the office next Monday 6/10/26 8:14 (jimmy) Left him a message on whatsapp said he's in the hospital 🤦‍♂️ - ben, he said that he is in a vacation and he will call me back _ George 03/26/2026 wants 3 agents to start with | M2: 46183.842 | O2: FALSE | P2: wants 3 agents to start with | Q2: 1053817924
A3: IMMUNE | B3: Selene | C3: Contract Sent | D3: 45944 | E3: DIAGNOSTIC SOLUTIONS | F3: Jessica Wilks | G3: 325-222-0621 | H3: jessicawilks@mediplus1.com | I3: Wed 5:00PM | J3: Jessica Wilks (Office Manager) - TX Based accepts medicare patients from other states works on PGX sent email meeting 5pm our time wed 10/14 - tried to find another number its discoonected | K3: NA left a VM (jimmy) 6/10/26 8:16 wants an email and to see the draft and the Contract sent an email follow up tomorrow, left a voice mail , left a voice mail | M3: 46183.844 | O3: FALSE | P3: no answer | Q3: 1396419933
A4: ORT | B4: Selene | C4: Contract Sent | D4: 46008 | E4: SHAPIRO Z ENTERPRISE INCORPORATED | F4: Zinoviy Eduardovich Shapiro | G4: 440-461-2648/440-278-0793 mr shapiro number | H4: alinamedicalsupply@gmail.com | I4: Thu 6:00 PM | J4: OH Based , Medicare liscenced, Ships all states meeting Thursday 11am EST 6 pm our time 12/15 | K4: He said that our price is very high, I tild him we can a gree on a lower budget and told me to say what he has in mind. Called him to connect him with George, but he did not answer. 6/10/26 8:25 He said to reschedule to monday 2 pm est, Doc 02/04/2026, left a voice mail shapiro wanted to review the prices and the contract and respond back to us, call back next wednesday same time 1/29, friday 5:30 same time , he wants some calculations to be sent to know whether it will be profitable to him or not Send him the price list one more time with examples what would be the case if he recieved 5-7 patients a week and what is expected in return , Calcucate Net profit Or ROI ( return on investment) , Avg Reimbursements - (Our cost + cost of the item ) = Net profit sent the email ill call tomorrow - ben He said he is currently interested in working for cpap /bipap /wound supply /cathethers /pure suply will give acb friday 7/29 | M4: 46232.744 | O4: FALSE | P4: no answer | Q4: 1518216126
A5: Lymphadema | B5: Selene | C5: Contract Sent | D5: 45979 | E5: SV MEDICAL SOLUTIONS INC | F5: Vanik Meliksetyan | G5: 929-556-3030 / | H5: SVMEDICALSOLUTIONSINC@gmail.com | I5: Wed 7:00PM | J5: NY based , Medicare liscenced , ships all states supplies lymph wraps interested to know more and he wanted to know about prices too meeting next wed at 5pm our time 10 am est 11/13 - said to give acb fri thats when he will be availble 1/7 - They said he is in the broklyn office cb next mon 2/5 | K5: He is on pause, he should be ready back by the end of june or by the first week of july asked for a call back by then (jimmy) 6/10/26 8:29 Really good Calliber , He wants us to send him the Cataelogue from sgivaris and the contracrt if we didn't already send him and he also wants to see how many patients can we send monthly voice mail 12/09/2025 left a voice mail , he is in vacation, left a message with his assistant and he will let him know call back in a week guy moved to another location, gatekeeper did not want to give me his phone told me to send an email - ben , so i called him and he is changing stores and it will take him a month to be able to work with anyone cb 4/12 he is waiting to complete the merge in the broklyn location , he took my numder and he would give me a call back / call back on monday Still no liscence cb at the end of august 7/24 | M5: 46227.927 | O5: FALSE | P5: he is waiting to complete the merge in the broklyn location , he took my numder and he would give me a call back | Q5: 1750183372
A6: ORT + Lymphedema | B6: Jane | C6: Contract Sent | D6: 46009 | E6: SAN BENITO RX LLC | F6: Oscar (biller) | G6: 956-399-2453 ext 304 | H6: frysdme311@gmail.com / oscarmeza80513@yahoo.com | I6: Thu 8:00 PM | J6: Tx based , medicare licensed, oscar is the biller handels every thing ,he is not sure if he can ship to all staes but interested to do that , supply ort and lymphedema, meeting 8 pm | K6: Call back Friday 12:00 pm He can onl bill for specific states. Oscar said to send him all the details with the pricing and he will discuss it with the owner and he asked if we can call him tomorrow 1 pm ( his time ) sent it again prices 1/9, he said he received it and will call us back this week, waiting for a call back ( george : 02/25/2026) he will check with the owner a good time for him to get to the meeting (propably will not go for it ) | M6: 46183.857 | O6: FALSE | P6: oscar is always not available | Q6: 1851139034
A7: ORT | B7: Jane | C7: Contract Sent | D7: 46027 | E7: GREAT HELP MEDICAL SUPPLY LLC | F7: Uzor | G7: 202-779-4560 | H7: greathelpmedicalsupplyllc@gmail.com | I7: Mon 5:00PM | J7: Md based, supply ort, medical liscensed ,he said he can ship allstates, but not sure when checked , meeting today 10 pm | K7: he has talk to his Partner, /sample + recordings + pricing + contract / DOC 01/09/2025 hanged up on me didnt have time to look,schedule a meeting next week 7:30 phone call - ben | M7: 46084.82 | O7: FALSE | Q7: 1669236436
A8: ORT+CGM+LYMPH W | B8: Ben | C8: Contract Sent | D8: 46031 | E8: STEMLYFT PARTNERS LLC | F8: GERARD MOHAMMED | G8: 832-656-4410 | H8: jmohammed@wellness1stpharmacy.com | I8: Fri 9:30 PM | J8: Jerry's the husband (i think) TX Based, Part B nationwide, the works | K8: NA left a VM 6/10/26 8:49 send the contract and the pricing ( for CGM ) , he is also interested in the braces 01/30/2025, he saw the price list and the reimbursements and he would give me a call back in an hour and also i could contact him on whats app daughter is sick - ben 2/27 - VM | M8: 46183.867 | O8: FALSE | P8: follow up on tuesday 9:00 pm our time to see if he is credentialed to do Orthopedic braces, if he is he can start right away | Q8: 1396414199
A9: ORT | B9: Selene | C9: Contract Sent | D9: 46041 | E9: FIRST CHOICE ORTHOTICS PROSTHETICS AND DME | F9: JAMAR WILLIAMS | G9: 810-282-8323 | H9: roc2723@gmail.com | I9: Tue 9:30PM | J9: - MI Based, Medicare Liscenced Ships all states ORT meeting tmrw 9.30 our time 1/19 | K9: NA left a VM 6/10/26 8:53 he is interested in doing the braces he wants to review the document and then we can call back 2:00 pm , he wants a contract the price list and the palmetto states where he could know which states can he work in, he wants to talk on saturday, he said he will call me back after 45 min , he will call me back after he recieve some money , he hanged up on me and sent me to the voice mail , - He was busy he said to give him a cb later3/3 | M9: 46183.869 | O9: FALSE | P9: no answer | Q9: 1780324830
A10: ORT+CGM | B10: Russ | C10: Contract Sent | D10: 46052 | E10: ORTHOTIC & PROSTHETIC ARTS | F10: ALTAGRACIA PENA-ATRISTAIN | G10: 845-459-0212 | H10: Nidia@ORTHOTICPROSTHETICARTS.Com | I10: WED 7:00 PM | K10: NA left a VM 6/10/26 8:57 Nidia is out on the field, be back tmrw - ben | M10: 46183.872 | O10: FALSE | Q10: 1649919010
A11: ORT | B11: Selene | C11: Contract Sent | D11: 46006 | E11: EXPO MEDICAL SUPPLY LLC | F11: SHARDAE KNIPS | G11: 305-336-1809 | H11: SHARDAE@EXPOMEDICALSUPPLY.COM | I11: Tue 10:00PM | J11: FL Based , Medicare, Ships all states meeting tuesday 3pm EST 10 pm our time 12/15 -Still didnt get Medicare CB at the End of Feb -selene 1/29 | K11: She said she never got the contract and wants a call back after 30 mins 6/10/26 9:08 more interested in CGM , needs better pricing , Might be interested in getting 2 agents 1/20/2025 she had to redo her accrediation, she is waiting for this to happen by the end of march | M11: 46183.896 | O11: FALSE | P11: she is interested to get around 15 patient a month then 40 patients next month with discounted price, she has an estimate for two weeks , waiting for the suspension to end upon accredidation because of the BOC , follow on thursday 9:30 our time, do a calender invite and ask about the good states that she can work with / she still didn't have an updte from medicare about her license | Q11: 1184352965
A12: ORT+CGM | B12: Ben | C12: Contract Sent | D12: 46077 | E12: STARMONET ESSENTIALS LLC | F12: DAVID SHAHZAD | G12: 314-656-6510 | H12: hxdavid1@gmail.com | I12: WED 7:00 PM | J12: MO Based, Dropshipping Medicare B | K12: He said that he is still in process of finishing his papers and asked me to call back after 2 weeks 6/10/26 9:30 he wants the Price list + avg Reimbursments + contract for BOth ORT & CGM , call back next thursday busy now didn't see the paperwork will call is (cb in 10 days if he didnt call) - ben | M12: 46240.888 | O12: FALSE | P12: call back in may | Q12: 1578352183
A13: ORT | B13: Selene | C13: Contract Sent | D13: 46084 | E13: MED SUPPLIES EXPRESS INC | F13: Mbaukwu U Anaba | G13: 678-377-5660 | H13: support@medsuppliesincs.com | I13: WED 5:00 PM | J13: GA Based, Medicare liscenced , Nationwide ORT said she wants a call meeting at 10 am est 5 pm our time -selene 3/3 - She said she is very busy during the day but she said 15 min before closing time is more suitable for her she said to call her tmrw at 1.45 our time -selene 3/16 | K13: Tomorrow 11:00 am EST she does not understand how to by agent and she said that the price is so high per prescription agreed on a meeting tomorrow 6/10/26 10:03 send the price list + contact and she will reply to the email about a good time for a followup call , she said that she didn't set an exact time with selene , she had a walk in so she asked to call her later 03/13/2026, 06/22/2026 she wants to approve the order first , new Template for ORT + contract + she only wants to work in GA , reschedule on monday | M13: 46198.756 | O13: FALSE | P13: no answer | Q13: 1619088796
A14: ORT+CGM | B14: Jane | C14: Contract Sent | D14: 46086 | E14: PADEK HOLDINGS LLC | F14: PRINCE AYODELE ADEKOYA | G14: 240-731-3766 | H14: prince@padekhealth.com / padek.healthcare@gmail.com | I14: Tue 8:00 PM | J14: MD based supply ort,cgm, ship allstates , medicasre liecned sent email,meeting tuesday | K14: NA vm is full 6/10/26 10:17 he has two other locations, he is only problem is to convince him to do an upfront payment send price list for ort & CGM devices and a contract , they will respond back with an email 06/30/2026 just talked to him right now, send him the marketing template for ort and CGM and we will talk to him at the end of the day or tomorrow, send the email and remember to call him to ask him if he reviewed the document today | M14: 46203.792 | O14: FALSE | P14: no answer | Q14: 1326912833
A15: ORT + Lymphedema | B15: Jimmy | C15: Contract Sent | D15: 46043 | E15: MERCY MEDICAL SUPPLIES LLC | F15: DONNA M CHANG | G15: 904-476-3305 | H15: suppliesMERCYMEDICAL@gmail.com | I15: FRI 7:00 PM | J15: - FL Based, Medicare Liscenced Ships nation wide | K15: NA 6/10/26 10:44 I called her again she apolozied for not showing up, she said her brother died, and she had a lot going on with her now, we a greed on a reset next WED 11/03 11:30 Her time 6:30 our time 3/4/26 10:22 She did not show up 2/4/26 8:30 1 pm fl NA 1/27/26 7:24 She did not answer 1/26/26 7:22 "Mail sent and meeting set She still at the beggining of running the business asked me for the mail and a meeting next monday at 12 pm suppliesMERCYMEDICAL@gmail.com " she didn't show up in the meeting | M15: 46183.946 | P15: no answer | Q15: 1912706565
A16: IMMUNE | B16: Jane | C16: Contract Sent | D16: 46147 | E16: GENE MATRIX LLC | F16: TAREK YOUNIS/ Lammy | G16: lammy no. 7732170877 office 847-302-9668/ tarek no 312-998-9275 | H16: lammy@genematrix.io , tarek@genematrix.io | I16: FRI 7:00 PM | J16: IL based, lammy called one of the desicion maker, saide the do ngs and pgx and has the machine, bill medicare and accept pt allstates, meeting on friday 11pm cst | K16: next meeting Monday 11:00 am EST (add mike to the meeting) , I spoke to tarek younis , he said that he already have a contract with hospitals and clinics for pgx doing 4000 Sample, and he can accept around 25 patients immuno and another 25-50 patient Cancer , he is interested but what i am afraid of since he already got this volume it wouldn't make sense for him to pay alot of many for extra samples,, MEETING NEXT UESDAY, WILL SEND THE MARKETING PLAN+ CONTRACT | M16: 46177.819 | O16: FALSE | Q16: 1225729312
A17: ORT+CGM | B17: Jane | C17: Contract Sent | D17: 46161 | E17: MTS DIRECT INC | F17: VICTORIA GATLIN | G17: 708-252-1958 | H17: v.gatling@yahoo.com | I17: Wed 10:00 PM | J17: IL based, supply ort and cgm, bill medicare part b, shipsnationwide, she can handle many pts .meeting tomw 10 pm | K17: Send her sample for both ort + CGM ( recordings ) + contract + pricing for both ort and CGM , she is interested and she wants to review these documents today and talk tomorrow at 10:00 am her time | M17: 46163.969 | Q17: 1972926012
A18: Lymphadema | B18: Selene | C18: Contract Sent | D18: 46175 | E18: SA MEDICAL SUPPLY | F18: SAUD ANWER | G18: 763-600-2858 | H18: saud.mittens@gmail.com | I18: THU 8:30 PM | J18: MN Based, Medicare liscenced, nationwide , will ask his team about the lymphedema supplier will join with his team to the meeting thu 6/3 - Still discusiing it with his team and will get back to us -selene 6/16 | K18: send the presentation + ask him about the capacity (how many patients he wants to receive 0 + states that he can cover + products that he wants to work with , so we can send him a marketing plan and a quotation and the contract and ask him in the email what would be a good time to talk again | M18: 46181.867 | Q18: 1821935933
A19: ORT+CGM | B19: Selene | C19: Contract Sent | D19: 46189 | E19: ORTHO PLUS LLC | F19: NETANEL SHIMONOV | G19: 347-707-8439 | H19: nathansvoice7@gmail.com | I19: Wed 9:00 PM | J19: NY Based , supply ORT CGM , Medicare Liscenced , supply locally but said will dropship nationwide if its worth it said give him a call tmrw our time 9 pm 6/16 | K19: it would be for another company that can do medicare , he has one called arial and sons , we talked for an hour, he is interested but he is facing an audit from medicare and his license might get revoked , send him the contract + presentation + marketing plan for orthopedic braces and marketing plan for CGM devices + some calculations that we did together over the meeting SEND GEORGE INFO CONTACT PHONE NUMBER / he is going to the accreditation process must be done in a month in order not medicare revoke them, he will only know 2-3 week , call back 07/10/2026, he wants to give him a call next week 07/07/2026 he needs to see if he would pass medicare inspection - Said that he was expecting a call from us regarding something profetable / no cgm no ort wants wound careor lymphedema8/3 | M19: 46237.939 | Q19: 1952136806
A20: CGM | B20: Selene | C20: Contract Sent | D20: 46182 | E20: JILANI MEDICAL | F20: Usman Jilani | G20: 773-931-7286 | H20: info@jilanimedical.com | I20: Wed 12:00 PM | J20: - IL Based, wants to really work with PPO BlueCross Blueshield and humana for CGM he wanted this for a really long time was interested to talk about it wants email and meeting wed 12 am -selene 6/9, products | K20: humana ppo, BCBS HMO and PPO , he wants to start with BCBS in illinois with a set budget for ORT and CGM, he will do a trial of a certain amount for the optin data for both campaigns so he wants us to send him an invoice and a contract called jilani siad to resend the the invoice and he wants bcbs and humana 7/29 | M20: 46232.785 | Q20: 1427679182
A21: Lab | B21: Jane | C21: Contract Sent | D21: 46234 | E21: GSB DIAGNOSTICS LLC | F21: Steven Likos | G21: 610-909-7757 | H21: slikos@gsbdiagnostics.com | I21: Mon 9:00 PM | J21: Fl based, they do ngs, pgx, uti, sti, gi, cgx, respiratory panel and wound care , can bill medicare, accept allstates except ca, ny , pa, nevada , he was interested into do all test with small starter, spoke about our up front payment , for flat fee example of our starter package for the uti only he said it was reinbersment in fl is lower than usual last couple of months, i told him there is pts from other states and will get higher reinbersments usually , he was interested to have google meet video meeting and speak face to face. | K21: george did explained and reassured him again after our last call, he is interested and wantto do busniess with us will inform his partners and will get back to us in 2 weeks maxi, an will get back to us and said we would might try you out, his partner just cam on saturday, and said will get an update by end of the week. | M21: 46251.884
A22: IMMUNE | B22: Jane | C22: Contract Sent | D22: 46230 | E22: DIRECT DIAGNOSTIC LABORATORY LLC | F22: RICHARD ELLIOTT | G22: 404-435-9685 | H22: richard@rasmedicalsolution.com | I22: Tue 9:30 PM | J22: Tx based do uti, pgx, molecular test and other genetic testing , bill medicare, accept pt all states,meeting tomw | K22: he has two labs GA and TX,HE CAN DO IMMUNE WITH PARTNERING OTHER LABS, CAN PROVIDE UTI, PGX AND STI IN HOUSE, MEDICARE PTS, BUT AFRAID OF TELE MEDICINE HE THINKS IT RISCKY,PREFER PCP , BUT WILL SEND HIM OUR SAMPLE OF PGX TELE MEDICINE IF COMPLIANT WITH H IM WILL DO BOTH MODULE, AND WILL SEND ROUGH MARKETING PLAN FOR ALL THREE TEST, the just saw it and will review it will reply to us back, still didnt review it yet, he still insisting on having a refrence labs who worked with us with telehealth module, so he can work with us | M22: 46251.884
A23: IMMUNE | B23: Jane | C23: Contract Sent | D23: 46120 | E23: BIOLIFE DIAGNOSTICS INC | F23: HUSSEIN HICHAM ABUJAJEH | G23: 314-750-5504 | H23: info@biolifemanagement.com | I23: Fri 9:00 PM | J23: Mi based, do ngs test and have the machine, medicare liscensed and accept pt from allstates, meeting tomw 5 pm | K23: mike spoke with him , he explained all the process and he wanted to review the email again and meeting on monday for follow up same time 4/9, he will send email to reschedule for follow up meeeting now he is busy with pts and have bad network, he called yesturday and reschedule today meeting , he wanted to know the prices after reviewed the email. i called him if he is currently doing the uti testing, he said yes asked to send email and booked meeting on friday 9 pm our time, he wants 50per week, but we told him we can do 25 per week,aka 100 month , will calculate it for him and get him a price and send it with contract. and schedeule a meeting on tuesday on thursday 9 pm our time, he spoke with mike and said the uti dont make sense with him , so will chek if he can do immune and pgx, we sent him the sample of immune and pgx prescription. | M23: 46237.797 | O23: FALSE | Q23: 1467346718
A24: ORT+CGM | B24: Selene | C24: Contract Sent | D24: 46205 | E24: CORE COMFORT MEDICAL SUPPLIES | F24: WASEEM KHAN | G24: 434-250-1675 | H24: waseem93@gmail.com | I24: Tue 8:30 PM | J24: FL Based, PPO , ORT .CGM said they can dropship nationwide , never done marketing but interested to learn more about it said wants meeting with his team on tueday 8.30 ourt time -selene 7/2 | K24: Meeting attended by mike send marketing plans, ORT CGM samples, Contract , they will review it and will reach out to us and i can follow up with them on mon 7/8 left a vm 7/16 - spoke to wassem said he really liked the marketing plan but he wants to figure things out on his side and will recah out to us said he will get back to us this week and agreed for me to reach out on him at mon 7/28 - meeting finalizing thursday at 8.30 our time he works with most ppo insurances humana, bcbs, united, wants to start with one agent and start with cgm asked about if we rae w2 i said we are w8 and its upfront payment 8/3 He said that he is interested in working with us and he wants to start in september 8/17 | M24: 46251.719 | Q24: 1336087469
A25: IMMUNE | B25: Selene | C25: Contract Sent | D25: 46043 | E25: EIV DIAGNOSTICS LLC | F25: MUHAMMAD IRFAN KHAN | G25: (559) 704-8024 | H25: irfan@eivdiagnostics.com | I25: Wed 11:00 PM | J25: CA based , accepts nationwide medicare patients provides immune genetic testing said to call him today 11 our time -selene 1/8 | K25: wednesday 11:00 pm he wants to do some duediligence to check if everything checks out, he is kinda skyptical and not very sure that if he did this he will get paid from medicare but we can do a follow up meeting on the 27th 11:00 pm , Doc 01/21/2025 working on stuff for the testing, talking to vendors, working on the panel, once he's ready he'll give us a call.spoke to him said he wants to get the z code approval for billing and it takes time 4/9 said cb 15th of june 6/2 - told him about the uti and pgx said hes interested and meeting tmrw 7/20 - Meeting follow up with george irfan said that california reimbursment is low and require z code so sends samples out of state in medicare ,he prefers cash pay, but we agreed on targeted insurance etna bcbs for CA he said our prices are high but george is willing to negionate follow up august 10 7/21 Mike spoke to him and said he has z code issues turns out its not an isuue but we have to convince him we sent him everything and i will call him to ask if he reviewed the codes and ask him which test doesnt need the z codes 8/12 | M25: 46246.898 | O25: FALSE | Q25: 1912529157
A26: IMMUNE | B26: Selene | C26: Contract Sent | D26: 45943 | E26: GENEWELL LABS LLC | F26: TARIQ HAFEEZ | G26: 404-617-8550 | H26: TARIQ@GENEWELLLABS.COM | I26: Tues 7:00PM | J26: Accept Medicare Nationwide , TX Based , Do GENETIC Testing PGX CGX MEETING SAT 5 PM OUR TIME 10/13 Meeting will be changed to Tuesday 11 cst 7 pm our time | K26: Another meeting on Wed 4 pm CST send contract Interested in UTI, STI ,PGX and Immundefiency test / covid ( influenza A ,b ) RSV , meeting tuesday 11:00 am, SAID WILL START ON FEB, forward to an automatic voice system , forwarded to Automatic voice message 02/25/2026 - Spoke to Mr Hafeez he said that he is busy with projects related to the world cup he said that when he is ready he will give us acall he couldnt give us a time to give him a cb selene 2/25 , voice mail meeting july 30th 11 am cst 7/20/ marketing plan He does immune ,pgx,uti get gets 35 to 40 samples week uti and 10 samples per week pgx we decided to stick to UTI calculated reimbursemts and i told him to discuss it with his biller and to read contract with lawyer he had a bit concerns on price and wether we will be commited or not siad he is applying CA and NY liscence to work therer sent prices contarct and samples follow up next wed 1.30 his time 7/30 He said he reviewed the contarct and the prices and discussed it with his biller briefly he said that he will discuss it in detail with his lawyer and we will have next meeting thursday 8/5 | M26: 46239.909 | O26: FALSE | Q26: 1952156622
A27: ORT+CGM | B27: Selene | C27: Contract Sent | D27: 46234 | E27: VITALCARE ESSENTIAL SUPPLIES CORP | F27: SYED SHAH | G27: 646-567-8371 | H27: vitalcaresuppliescorp@gmail.com | I27: Tue 6:00 PM | J27: NY Based ,supply ORT, CGM ,Mediacre liscenced ,supply locally said he does marketing himself but interested to know more said to give him a call at 11 am his time on Tuesday 7/31 | K27: Interested wants to focus on ORT he is interested to expand nationwide and will look into it .Send him prices ,contract,suppliers,and codes he said he will check the reimbursment and everything and we will speak again with mike and dan next week | M27: 46248.891 | Q27: 1225995830
A28: ORT+CGM | B28: Selene | C28: Contract Sent | D28: 46245 | E28: GRAJAG LLC | F28: RAJA GUL | G28: 713-382-7695 | H28: grajagllc84@gmail.com | I28: Wed 8:30 PM | J28: TX Based ,supply ORT, CGM ,Mediacre liscenced and PPO ,ships nationwide ,interested to know more said to give him a call at 8.30 pm our time 8/11 | K28: Sent him marketing plan and contract and CGM ORT samples said he will review it and we will touch base tommrow (ask him again about marketing ,direct him to CGM ,ask him when he would like to start and states) - He said he will start with CGM starter pack we iwll sedn him the contarct and i will call tmrw to have an onboarding meeting with mike and if its ok we will send the invoice after the meeting - Onboarding meeting set on Tuesday 7 pm our time 8/14 | M28: 46248.902 | Q28: 1306788872
A29: Lab | B29: Selene | C29: Contract Sent | D29: 46241 | E29: UNITED DOCTORS LAB INC | F29: Tony (Manager) | G29: 872-226-0303 | H29: Contact@chicagopath.com | I29: THU 8:00 PM | J29: IL Based, accept nationwide medicare patients does PGX,UTI test meeting Thursday 8.00 pm 8/7 | K29: He only works UTI only said he wants to try out our samples explained our entire process and he said that he will review documents and will get back to us cb next week to confirm meeting time 8/13 he said he will review everything folow up next tuesday 2 pm 8/19 | M29: 46253.782 | Q29: 1891511309

Sheet Invoice Sent
A1: SUB | B1: Opener | C1: Status | D1: Date Added | E1: Company Name | F1: Authorized Person | G1: Phone | H1: EMAIL | I1: Meeting Time | J1: Opener Summary | K1: George's Notes | L1: Auto Scheduler | M1: Last Call | N1: Action | O1: Checkbox | P1: Log | Q1: NPI
A2: ORT | B2: Ben | C2: Invoice Sent | D2: 46059 | E2: NYS DIAGNOSTICS & SUPPLY LLC | F2: MINATA SADDY | G2: 240-299-6339 | H2: info@nysdx.com / msaddy@nysdx.com | I2: Mon 9:30 PM | J2: Med B, all states without extra licenses , ort and cgm, immunology Scheduled a meeting 2/6, | K2: Scheduled for 23rd, sent contract, she said that she will call me tomorrow same time , she is interested in CGM and orthopedic braces, i sent her an invoice for 1.5 agent to do Orthopedic braces waiting for her to pay , call back after 03/11 she will finish the yearly compliance inspection , waiting for her partner to give a greenligh | M2: 46135.874 | N2: we want to send a marketing plan with 3 different prices and what will she get as an outcome | Q2: 1447061346
A3: ORT+CGM+LYMPH W | B3: Jane | C3: Trial Sent | D3: 46009 | E3: ROTTAM LLC | F3: ROLAND OKWEN | G3: 708-506-8292 / 8132707270 (whatspp) | H3: rokwen@rottamllc.com | I3: Fri 10:00PM | J3: IL Based, medicare lisenced, supply ort , cgm, and some lymphedema wraps he said he is interested to ship all statesd but dont know if he is able to do that eeting 10 pm our time | K3: billing option / wound care supplies / "Send palmetto + sample prescription + contract for CGM (usual price) + follow up after christmas DONE" Call back 01/08/2025 / left him a message on whats app, called him and he just hanged up on me 02/06/2026 Waiting for CGM devices stock will be delivered this week, then he'll file a claim and take a look, spoke to george, talk numbers with partners, wants to discuss fees, told him he'd need to speak to george - ben still no reimbursments | M3: 46139.725 | Q3: 1881301430

Sheet Temporary Inactive
A1: SUB | B1: Opener | C1: Status | D1: Date Added | E1: Company Name | F1: Authorized Person | G1: Phone | H1: EMAIL | I1: Meeting Time | J1: Opener Summary | K1: George's Notes | L1: Auto Scheduler | M1: Last Call | N1: Action | O1: Checkbox | P1: Log | Q1: NPI
A2: ORT+CGM | B2: Ben | C2: Pending Medicare | D2: 45714 | E2: Jama Medical Equipment Llc | F2: Ahmed Haji | G2: 312-437-4040 | H2: jamamedicalequipment@gmail.com JME@JAMAMEDICAL.COM ( more important ) | I2: Fri 4:30 PM | J2: IL Based, All States Waiting the Sites Survey ? to get Medicare approved Explained Our Process, Prices discussed licesnure and cgm reimbursements They got medicare, he heard stuff, that medicare doesnt like that | K2: Waiting for License, Waiting for maybe around the 15th of April )DOC(12/11/2025 ) busy with a patient , he will call me back , voice mail | M2: 46099.907 | O2: FALSE
A3: ORT+CGM | B3: Selene | C3: Pending Medicare | D3: 45929 | E3: CARE MEDICAL RESOURCES | F3: David Maurice Smith | G3: 404-476-0026 | H3: david.sourcems@gmail.com | I3: Tues 8:00PM | J3: -Medicare liscenced , ships all states ORT CGM wants UV Wands too owns several DMEs he said he will send our samples to his complaince officer he seems interested and has experience i think wazowski spoke to him before -selene 9/26 meeting 1 est 8 pm our time google meet meeting - spoke to david said he is still very interested buy migt start with less seats for cgm and when i mentioned lymphadema he said he is very interested and wants to speak today at 11/12 | K3: SAID CB BEGGINING OF MARCH /still didnt get medicare/ working ppo braces said prices high and upfront | M3: 46225.694 | O3: FALSE | Q3: 1841098365
A4: ORT+CGM | B4: Selene | C4: Inactive License | D4: 46031 | E4: NASMED LLC | F4: Arslan Minhas | G4: 929-400-0237 | H4: nasmed70@gmail.com | I4: Wed 7:00 PM | J4: NY Based, ships allstates just got their Ptan for their other DME his wife is the owner of the DMEs but he said he handles the work supplies CGM ORT meeting Wednesday 14th 12pm est 7 PM OUR TIME -selene 1/9 | K4: Please send the Contract AND the CGM (sample + Prices) and the ORT (sample + Prices His wife company has the PTan , (marketing Team inhouse, so she wouldn't need us ) he didn't get the PTan yet, he told me to follow up with him in march , I texted him on phound , call on tuesday his wife's company is well but she has everything in house, his company has no license yet,government not accepting any new license, could be delayed 8 months | M4: 46087.859 | O4: FALSE | Q4: 1346056637
A5: Lymphadema | B5: Jane | D5: 46001 | E5: LYMPHMED LLC | F5: Moshe Blinder / noah (operation manager) | G5: 718-387-5504 / 516-347-4271 | H5: moshe@discountsurgical.com | I5: Wed 8:00 PM | J5: Ny based, medicare licensec, ship allstaes supply lymphadema wraps | K5: he wants to get on a google meet to discuss everything friday afternoon, waiting for his text to confirm the exact time Doc 01/13/2026/ now only interested with lymphadema wrap but if we had surplus paitents for lymphedema wrapsd we can contact him 2/5 | M5: 46058.822 | O5: FALSE
A6: Lymphadema | B6: Jane | C6: NOT READY | D6: 45974 | E6: PINK REGALIA, LLC | F6: Miss Stephany Sage Semones | G6: 828-506-9591 | H6: stephany@pinkregalia.com | I6: Fri 10:00PM | J6: NC based , medicare licensed , ship all states , supply lymphadema wraps., meeting 10pm our time 3pm her time, not | K6: not ready now | O6: FALSE
A7: ORT | B7: Selene | C7: NOT READY | D7: 46048 | E7: ALPHA MEDICAL SUPPLIES PLUS CORP | F7: SIAMAK MALEKI-SHAHROKHI | G7: 714-516-2222 | H7: alphausa@alphamedical.com | I7: Fri 9:30 PM | J7: -CA Based , Medicare liscenced , nationwide meeting fri 9.30 our time -selene 1/26 - He reviwed our Documents said he is not ready to work with medicare Cb in 3 Months 1/30 nii in dme desk | N7: FALSE | P7: / | Q7: 1871389627
A8: ORT+CGM | B8: Selene | C8: NOT READY | D8: 45776 | E8: MASS MEDICAL SUPPLY LLC | F8: Michael Massey | G8: 469-532-0530/6789383008 | H8: massmedicalsupply@gmail.com | I8: Fri 6:30PM | J8: -TX BASED Medicare liscenced , ships all states , PCP, CGM ORT he is very interested meeting thursday 10.30 cst 6.30 pm -selene 4/29 - he had an emergency he wants a cb at 10.30 am and 6.30 our time -selene 5/1 - meetingchanged to mon 11.30 am and 7.30 our time and i confirmed with him that he is free and he said he is 5/2 - wants ppo cgm but has medicare said cb on monday 6/12 - vm 11/25 | K8: We discussed Pricing and orders schedule and payment terms. He needs an email with prices and fee schedule. Will talk again on Wednesday and if he is ready we will do a trial. DOC 5/9/2025 said he wants to work with us but he has his money stuck with Medicare and will get back to me when he is ready with the funds -He is going through things will call us back when hes ready men letting me down cb in nov -selene 8/28 -man has audits said cb jan 12/10 - Said to Cb in Middle of march -selene 2/5 | M8: 46058.778 | O8: FALSE | Q8: 1184462806
A9: ORT | B9: Selene | C9: NOT READY | D9: 45719 | E9: GREEN MEDICAL SUPPLY LLC | F9: Hamid Hamid | G9: 313-844-0948 | I9: Thu 8:00 PM | J9: - vm-selene 2/20 - medicare liscence ship JUR B DME and CGM PCP 15 to 20 pts they have a some resourses for referral but willing to know more meeting thurs 6 1 pm est 8 pm our time greenmedicalsupplyllc@gmail.com -selene 3/3 - man is broke waiting on deposit lol cb first of may 4/15 - called again and he said he wants to work with us and i will cb on mid may but he said he will reach out to bassam earlier -selene 4/29 - Interested still cb end of may medicare revoked his liscence -selene 5/15 - still insterested will keep praying medicare return his liscence cb end of june 6/4 - NI for now his partners are sick and travelling and he cant do a decesion now 8/21 - vm 11/25 - Going through Audit CB in 2 Months - 2/5 | K9: Interested in CGM CPL Live transfer, Will talk again on Monday. Very good prospect, lebnon. Willing to start, will talk to his partner and get back to us with the greenlight. DOC 4/14/2025 NO answer 3 times , call back later | M9: 46099.913 | O9: FALSE | Q9: 1245961226
A10: ORT+CGM+LYMPH W | B10: Selene | C10: NOT READY | D10: 45980 | E10: PRISM HEALTH & MEDICAL EQUIPMENT LLC | F10: ALI JUNAID | G10: 888-386-1101 | H10: PRISMHEALTH100@GMAIL.COM | I10: Thu 11:00 PM | J10: RI Based, , Medicare liscenced , ships all states supplies lymph wraps. cgm ,ort interested to know more meeting 4 pm his time 11 pm our time 11/19 - He called me he is in a vacation will return on 21st he said he wants ort prices and will discus with his team and will cb us after 21st -selene 12/2 | K10: interested to see the prices for the braces and the CGM but not to work per hour "Left him a voice mail 12/01/2025 -said he will reach out to george -selene 1/27" - CB early march 2/5 - said he will give us a cb , cb early april -selene 3/3 , he want to pay me a percentage of the reimbursements 03/18/2026 | M10: 46099.846 | O10: FALSE | Q10: 1174311658
A11: ORT+CGM+LYMPH W | B11: Jimmy | C11: NOT READY | D11: 46056 | E11: Precision Ortho Supply Llc | F11: Mohammed Khan | G11: 484-756-0563 | H11: admin@qsmedcare.com | I11: MON 7:00 pM 16/02 | J11: He can do the billing through a billing team, he can ship nationwide | K11: he is not enrolled for medicare part a and part b , he doesn't have a ptan number , but he need to ask another company whether they have or not , call back after 1 week , please send him the price of the braces , cgm and the avg reimbursments + contract | M11: 46216.935 | O11: FALSE
A12: IMMUNE | B12: Jimmy | C12: NOT READY | D12: 46043 | E12: ELITE LABS AND MORE | F12: TECILLA R HICKS | G12: 800-501-5716 | H12: info@ELITElabsorg.com | I12: Fri 8:30 PM | J12: Fl based, can do NGs and UTI | K12: 1/30/2025 she doesn't have money to start with us but she will see if she can get some money either from a loan or somebody to startshe doesn't have money to start with us but she will see if she can get some money either from a loan or somebody to start she doesn't have money to start with us but she will see if she can get some money either from a loan or somebody to start | O12: FALSE
A13: IMMUNE | B13: Jimmy | C13: NOT READY | D13: 46035 | E13: CLINICARE LAB LTD | F13: AMER | G13: (708) 879-9519 | H13: Amerk@clinicarelab.com | I13: WED 5:00 PM | J13: Immune + UTI based in IL, accept from all states | K13: he was interested but he wanted the CPT Codes to know the reimbursmnets and if he can do it through another lab | O13: FALSE
A14: Lymphadema | B14: Ben | C14: NOT READY | D14: 45995 | E14: SEASIDE DME OF NY, INC | F14: Larry Chen | G14: 917-853-1166 | H14: larrychenbdt@gmail.com | J14: NY Based, medicare, larry works with owner "JINGLING TANG" is a decision maker, No manpower at this moment, not ready at the moment 2/24 | K14: he will check with the consultant in a day or two and call me back | O14: FALSE
A15: Lymphadema | B15: Jane | C15: NOT READY | D15: 45995 | E15: CHARITY COMFORT CARE SERVICES. LLC | F15: JOSEPH JOHNSON | G15: 214-699-9607 | H15: dme@charitycomfortcare.com | I15: Fri 6:30 PM | J15: Tx based supply lymph wraps, from wahrhouse , shill allstatesx medicare licensed meeting fri 6:30 pm outrtime, he will be back in | K15: He doesn't have the marketing budget rightnow so he won't be able to work with us / he asked to be contacted in february patients that needs any home health , care giver services , certified nurse or assistant in dalls and fortort area , i called him he said it better to call again april first cause the dme world it changing not ready now aftwer every thing is set with medicare and cms 2/10/2026 | M15: 46063.681 | O15: FALSE
A16: ORT | B16: Selene | C16: NOT READY | D16: 46034 | E16: FIT TO GO LLC | F16: JOSH WHITE | G16: 401-217-9732 | H16: josh.white@orthofeet.com | I16: Wed 6:30 PM | J16: NJ Based, Mediacre liscenced , ships nationwide supplies ORT meeting tmrw 6.30 our time 1/12 follow up in april 1/15 | K16: he so interested in CGM , he wants to do this couple of months -vmx2 4/2 keeps hanging up 4/22 | M16: 46134.706 | O16: FALSE | Q16: 1417436445
A17: ORT+CGM | B17: Ben | C17: NOT READY | D17: 45692 | E17: Peachtree Medical Supply Llc | F17: Azuka Iloh | G17: 908-447-2665 | H17: azuka@peachtreemedicalsupply.com | I17: Fri 8:00 PM | J17: CGM & DME GA Based , Discussed our process, payment cycle, patient trials, She does JUR C but told her about not needing license for others Out of the country 8/18 Still waiting for medicare, cb in may 1 2/24 | K17: Call back on friday 10:00 am (07/21/2025) Going through a medicare review, wants some time Meeting Friday 12/12/2025 10:00 ( his time) Still waiting on report, ben 5/7 | M17: 46149.691 | O17: FALSE
A18: CGM | B18: Jane | C18: NOT READY | D18: 45971 | E18: TRI-STATE MEDICAL SUPPLIES, LLC | F18: justin smith | G18: his number 8643986085 office no 864-579-2899/ | H18: justin@tri-statemedical.net | I18: Tue 5:30PM | J18: -SC based supply cgm, all states,medicare lisenced, asked to send email meeting to mw 5:30 pm, | K18: we need to send him the website for the states that he can work with, some prouct knoweldge about lymphadema wraps and theircodes and the Excel sheet that give the reimbursement for each product he has a law suit right now ( can't do business till couple of months ) | O18: FALSE
A19: ORT+CGM+LYMPH W | B19: Ben | C19: Hold | D19: 46009 | E19: SCRIPT FIT LLC | F19: SHANE RAGLAND | G19: 317-900-4030 | H19: scriptfitindy@gmail.com | I19: Fri 8:30PM | J19: Meeting with Akilah COO, Spoke to Both Owner and COO, Medicare, all items, sent email, number here is company phone for shane :317-316-9951 Called akilah they have a board meeting on march 4th wants a refresh email with contracts. 2/25 want to start on the 3rd quarter of the year 3/12 | K19: they are not ready to do any business till march She will call me back after reviewing the documents with the owner 3:00 pm ( 01/08/2025) / sample prescription + contract for CGM (usual price) + follow up after christmas 01/06/2025 + good states they work wait for ben to reschedule want to start on the 3rd quarter of the year 3/12 | M19: 46114.767 | O19: FALSE
A20: Solar | B20: Selene | C20: Hold | D20: 45798 | E20: Florida Eco Electric LLC | F20: Kedir R Felix | I20: Wed 6:00:PM | J20: FL BASED , WANT TO KNOW MORE ABOUT PRICES 5/21 | O20: FALSE
A21: RE | B21: Jane | C21: Hold | D21: 45729 | E21: Now I Can Buy | F21: Mr. Dwight Williams | G21: 856-699-6595 | H21: dw@nowicanown.com | I21: Fri 8:00 PM | J21: (877) 977-0247 the number I called the first time | K21: 8:30-7:00 EST dw@nowicanown.com call back in 10/19/2025 (Doc 09/19/2025) | O21: FALSE
A22: Home Improvement | B22: Selene | C22: Hold | D22: 45917 | E22: American Home Improvement | F22: Josh Stevens | G22: (818) 661-8785 | H22: info@ahibuilders.com /josh@ahibuilders.com | I22: Wed 9:00PM | J22: Spoke to josh he said that their company is looking for a new Lead Gen services and he qulaifies them first with the prices and everything and then they transfer it to their owner he said we could talk at 9 pm 11 am pdt today -selene 9/17 | K22: kitchen , bathrooms and room bathroom and adu's only LA & venture county | O22: FALSE
A23: Home Improvement | B23: Ben | C23: Hold | D23: 45916 | E23: Lavish Home Remodeling | F23: Parry | G23: (267) 244-5482 | H23: lavishhomephilly@gmail.com | J23: PA based, works in everything, he seemed interested to do marketing, didn't even ask about the prices and was open to have a meeting. | K23: roofing flooring plumbing, kitchen, | O23: FALSE
A24: Home Improvement | B24: Ben | C24: Hold | D24: 45918 | E24: Long's Construction And Remodeling LLC | F24: Damon Long | G24: (412) 505-3464 | H24: longsconstruct@gmail.com | I24: Thu 5:45PM | J24: PA based said that he recently started working in OH as well, does pretty much everything remodelling, istallations, repairing and everything, he was polite and wanted to know the prices | K24: buttler , alangane pitsburg, young town ashabula , clevaland | O24: FALSE
A25: Home Improvement | B25: Selene | C25: Hold | D25: 45905 | F25: Fayez/ Frank | G25: 307-269-2832 | I25: Fri 6:00PM | O25: FALSE
A26: Home Improvement | B26: Jane | C26: Hold | D26: 45909 | E26: Pitchers Media | F26: Kushi Patel | H26: Khushi@pitchersmedia.com | I26: Tue 7:30PM | K26: ivin did send me the prices but it was too low for us to start working with him | O26: FALSE
A27: Home Improvement | B27: Jane | C27: Hold | D27: 45911 | E27: S&S Construction | F27: Abel | G27: (267) 339-2655 | H27: 1snsconstruction@gmail.com | I27: Thu 5:45PM | J27: PA based, they do everything from roofing to plumping to windows to kitchen, I think it's his first time working with marketing before as he seemed impressed about what we do and also wants to know the prices | K27: snsconstructor.com the guy wants a quotation for per appointment and how much could we expect per month , Meeting today after 10:00 pm our time ( 09/11/2025) | O27: FALSE
A28: Solar | B28: Selene | C28: Hold | D28: 45821 | E28: RoofWatt | F28: Robert | G28: (732) 575-2007 | H28: RHALLROOFWATT@gmail.com | I28: Fri 11:00 PM | J28: -NJ Based serves DE too works solar did lead generation but had a bad experience , informed him about all of our services and we do pay per hour and i told him that we its best for him to get a data so ist exlusicve for him and said to give him another call to know more about prices and services meeting 11 pm our time 6/13 | K28: talk to him tuesday 4:00 his timing | O28: FALSE
A29: Solar | B29: Jane | C29: Hold | D29: 45819 | E29: NatEco Solar inc | F29: Mr. Lee | G29: (917) 282-6285 | J29: he is NY based work in NJ, and other bunch of states, he wanted to know the prices | K29: he could only do it on call, He is not having problem with the price but he doesn't have any money to invest with us ( talk in a month) | O29: FALSE
A30: Solar | B30: Jane | C30: Hold | D30: 45819 | E30: Rivertown Solar | F30: Eric | G30: (914) 231-6866 | H30: eric@rivertownsolar.com | I30: Wed 9:30:PM | J30: He's based in westchester . new york city NY and works in CT, spoke about the process, sent him an email, his priority is the quality and also wants to know the prices | K30: he wants to get a quotation for 1 agent to work Payper hour and another one for 3 and 5 call back wednesday same time 09/19/2025, send him some data for the CPA | O30: FALSE
A31: Solar | B31: Jane | C31: Hold | D31: 45812 | E31: Selective Solar | F31: heshi drew/vigi | G31: 347 6704369/ vigi 6468750520 | J31: NY based, serve NJ and NY, expect 2- 3 meeting per day , he said he needs the home owner really intrested, and asked about the prices, he dont do sit appointments , just by calling the home owners | K31: Talk on monday 2:00 pm | O31: FALSE
A32: Solar | B32: Selene | C32: Hold | D32: 45812 | E32: Solarblocks Energy | F32: Mark P. | G32: (347) 226-0695 | I32: Wed 10:30:PM | J32: - works in NY only seemed interested in what we do and he liked our services but he is scared about the politics he said he wanted to know our prices -selene 6/4 | K32: we spoke but he wanted to rengotiate the deal , him and rita | O32: FALSE
A33: Solar | B33: Selene | C33: Hold | D33: 45810 | E33: Prestige Solar Services, LLC | F33: Percy | G33: 8564 252 207 | H33: TheTeam@prestigesolarservices.com | I33: Mon 7:00:PM | J33: - NJ based but works NY PA DE also takes 2 to 3 appt per day seemed interested sent email meeeting at 12 pm est 7 pm our time -selene 6/2 | K33: Does servicing for solar owners mainly, he doesn't install. Maybe we can do a project per hour for appointment setting for servicing | O33: FALSE
A34: Solar | B34: Ben | C34: Hold | D34: 45810 | E34: Lucent Energy Management, Inc. | F34: Steven Schwartz | G34: (908) 758-2368 | H34: steven@lucent-energy.com | J34: All of NJ and southern CT, can handle like 15 clients per day, wants to know the prices, will be available for meeting | K34: Thinks it's expensive, will check his current sit conversion state with the lead gen company that he works with and will get back to me. | O34: FALSE
A35: Solar | B35: Selene | C35: Hold | D35: 45806 | E35: Ray Energy LLC | F35: Mo Husseini | G35: (908) 630-8434 | H35: rayenergysolar4free@gmail.com | I35: Fri 6:00 PM | J35: NJ Based and serves NJ only seems kinda small and he said he accept 2 to 3 appt per day and he was interested and said to give him a call tmrw at 11 AM EST 6 PM our time -selene 5/29 | K35: He has a certain paying after 2 weeks of signing, he works with 2 other providers like that... We will set him aside for now as per my conversation with Chris. | O35: FALSE
A36: Solar | B36: Jane | C36: Hold | D36: 45805 | E36: Mister Solar Guy | F36: Mr Roger | G36: 845 663 4679 | H36: roger@mistersolarguy.com | J36: NY BASED SEVER NY NJ CT MA, 3 APPOINTMENTS PER DAY SEEM INTRESTED, HE WANT HIS LEAD EXCLUSIVE, he said he is intrested and will call us back soon , just stop calling | O36: FALSE
A37: Solar | B37: Selene | C37: Hold | D37: 45799 | E37: Allstate Electric & Solar LLC | F37: Joseph Adcock | G37: (732) 684-8823 | H37: joe@allstateenergy.com | I37: Thu 5:30 PM | J37: - NJ based but works several other states like NJ FL DE CO he said he used lead generation before and it was a bad experience because other companies used to compete with the same home owner , he was interested and heard the entire pitch and wants to know more and he said he can handle 2 to 3 appt set per day 5/22 - ni for now 6/2 | K37: Interested in the pay per appointment, we covered everything + prices and all. He will talk to his partner and get back to me next week. DOC 5/27, Still need to look it over again with his partner. | O37: FALSE
A38: Solar | B38: Selene | C38: Hold | D38: 45799 | E38: Etrecte LLC | F38: Vyacheslav (Alex) A Nechayev | G38: (347) 369-2462 | I38: Thu 4:30 PM | J38: NY, NJ and Long island, heard the intire process and how we operate seems interested | K38: VM | O38: FALSE
A39: Solar | B39: Selene | C39: Hold | D39: 45799 | E39: Solar Me | F39: Nethanial ( Marketing Manager) | G39: (732) 547-1679 (Bill) | H39: nate@solarmeusa. com | I39: Thu 4:00 PM | J39: NJ Based seemed interested heard the entire pitch lol explained everything and he liked that he will not pay unless its for a sitdown appt 5/22 - He will forward our info to his marketing director nathaniel 5/22 | K39: DOC 5/27 Bill said we need to email nathaniel and if he liked it he will reply he said he doesnt deal with this and he doesnt want to be a middle man. | O39: FALSE
A40: Food delivery | B40: Selene | C40: Hold | D40: 45910 | E40: Jahez Group | F40: Mohammed AlQahtani | H40: m.attalah.sa@gmail.com | I40: Mon 5:00PM | J40: Partnership manager at Jahez Corp a food delivery program in KSA agreed to an intro meeting sent email and calender invite meeting at mon 15 5 pm our time -selene 9/11 | O40: FALSE
A41: MVA Claims | B41: Jane | C41: Hold | D41: 45918 | E41: TechMedia Group | F41: Michael Nghiem | G41: 1 713-899-5877 / (713) 364-2220 | I41: THU | J41: TX based he is currently working on MVA Campaign and want us to collaborate with him since we have multilingual agents, hewant to discuss about it on whatsApp | K41: voice mail 09/18/2025 | O41: FALSE
A42: Claims | B42: Selene | C42: Hold | D42: 45856 | E42: Home and Legal | F42: Gary Thomas | G42: 7775 681209 | H42: gary@hdr-UK.co.UK | I42: Fri 6:00:PM | J42: ME | K42: Will talk tomorrow, Waiting for a background check | O42: FALSE
A43: Hospitality | B43: Jane | C43: Hold | D43: 45985 | E43: Cozmo travel | F43: Mahmoud Fadaly | G43: 966 59 553 0966 | H43: Mafadaly@cozmotravel.com Ashaaban@cozmotravel.com | I43: Wed 10:00 AM | J43: -KSA based its travel agency for booking flights and hotels and he is the key account manager and will be in the meeting the manger , interested to speak about customer support | K43: they said they want a proposal from us and might start bussiness on august 2026, we need to follow up with them | O43: FALSE
A44: SUB | B44: Selene | C44: Hold | D44: 45939 | E44: Medical Call centers 4D | F44: Mostafa Ali | H44: mostafa3ali4444@gmail.com | I44: Tues 5:00PM | J44: Mostafa Ali (Operation Manager) - Medical Call centers 4D is an IT Company providing IT solutions and call center in KSA they provide Cx for hospitals and other Governmental organizations and banks . connected with Mostafa Ali he is the Operation manger explained our solutions and that we are looking for a subcontracting opportunity and to support them . meeting tommrow at 6 pm via meet 10/9 | K44: he is video consulting call center, Wants the man power to be in the KSA open to the idea of collaboration in the future by sending each other referrals, Wants a presentation of everything that we do | O44: FALSE
A45: ORT+CGM | B45: Jane | C45: NOT READY | D45: 46100 | E45: NEW YORK RECOVERY DME CORP | F45: TZVI LEBOVITS/ Fraidy | G45: 718-637-7770/ 212) 235-5181 ext 101 | H45: tzvi@nyrecoverydme.com / fraidy@nyrecoverydme.com/ 212) 235-5181 | I45: Fri 6:00 PM | J45: NY based , ort and cgm, medicare liscensed, shipalstates, meeting tomw | K45: spoke with fraidy the one resposible work descisions, she received email and asked about prices and she cant attend any meeting till april the 20th willbe avalible, they have holiday for the next 2 weeks | M45: 46107.769 | O45: FALSE
A46: ORT+CGM+LYMPH W | B46: Jimmy | C46: NOT READY | D46: 46048 | E46: GLACIER MEDICAL SUPPLY, INC. | F46: CHAD EMERY HUFFMYER | G46: (405) 816-6266 | H46: chuffmyer@healthmarkps.com | I46: THU 10:00 PM | J46: OK Based, can provide ORT+CGM+LYMPH W, Can ship nationwide, has his PTAN and lisence ready | K46: left a voice mail | M46: 46092.923 | P46: /
A47: ORT+CGM | B47: Jimmy | C47: NOT READY | D47: 46091 | E47: PRIME PULSE MEDICAL SOLUTIONS LLC | F47: SOHALE HAJI | G47: 561-206-3292 | H47: PRIMEPULSEMEDICALSOLUTIONS@gmail.com | I47: TUE 10:30 PM | J47: FL based, bill medicare, accept pt all states | K47: he is interested in lead gen for the cgm and he would do the chasing on his own, he also wants alot of seats but unfortunately he doesn't have the ptan and he won't be able to get till 5 months from now , he wants us to keep contact on whats app | M47: 46091.967 | O47: FALSE
A48: IMMUNE | B48: Jimmy | C48: NOT READY | D48: 46086 | E48: TOTAL LAB SERVICES LLC | F48: ASHLEY DAVIS | G48: 317-997-0270 | H48: contact@TOTALLABSERVICESLLC.com | I48: WED 11:45 PM | J48: She said she is a collection site but intersted in working with us and see if she can provide us with a reference lab IN based, She still does not have the equips but is very very close to arrive to her lab, she can bill medicare. | K48: I’ve been doing well, thank you. I took some time to review everything, and at this moment I’m not in a position to move forward with this opportunity. I truly appreciate you reaching out and sharing the information with me. I’d definitely like to stay in touch for any future opportunities that may align as my business continues to grow. I sure wish I was suitable to assist I tried and it seems I am not qualified enough. I appreciate the opportunity 4/9/26 | M48: 46122.729 | O48: FALSE
A49: SUB | B49: Ben | C49: Hold | D49: - | E49: Touchstone Comm | F49: Abbas Mohiuddin | H49: amohiuddin@touchstonebpo.com | I49: Wed 9:00:PM | K49: Interested in French speakers. WE covered prices and some details about the project. Will talk again with account manager to discuss pricing points | O49: FALSE
A50: ORT+CGM | B50: Jimmy | C50: No - Show / Callback | D50: 46119 | E50: SFRN VENTURES LLC | F50: SHAH MIR ALI | G50: 832-446-8336 | H50: SFRNVENTURES@gmail.com | I50: MON 9:30 PM | J50: TX Based provide ORT and CGM, Can accept medicare PT | K50: He talked to mike but he does not have medicare license | M50: 46125.913 | O50: FALSE
A51: IMMUNE | B51: Selene | C51: NOT READY | D51: 46139 | E51: RPH LABS CORP. | F51: SHAHBAZ JAVAID CHAUDHARY | G51: 646-463-2226/ 877-373-9600 | H51: sc@rphlabs.com | I51: =HYPERLINK("https://calendar.google.com/calendar/u/0/r/eventedit/NDBqMTJqbWVlNjl2a3J0c3NxczE2NGZsNm8gYzM5ZjIxNjY2YTJjNzBkNjQ0MDI0YmQyOWM3ZmM5ODM3OTY2MmY3OTJlNWEwNDdjZGIzNTdhNDJiM2M1N2QwNEBn?pli=1", "Thu 9:00 PM") -> Thu 9:00 PM | J51: TX Based, does PGX Only ,Medcare liscenced, wants call meeting o thursday 9 pm our time 4/27 | K51: he only wants cash patients, no insurance patient, he asked to call him in 6 months in case he changed his mind | M51: 46142.887 | O51: FALSE | Q51: 1568248581
A52: DMEDESK | B52: Jimmy | C52: NOT READY | D52: 46162 | E52: INFINITY NEXUS LLC | F52: VERLINDA JOHNSON | G52: 572-271-3917 | H52: VERLINDA@INFINITYNEXUSMEDICAL.com | I52: THU 9:00 PM | J52: Cancelled She wants to discover the service, she will be available tomorrow for 30 mins
A53: ORT+CGM | B53: Ben | C53: NOT READY | D53: 46044 | E53: GRACEWOOD MEDICAL SUPPLIES INC | F53: ZUBAIR AHMED MOHAMMED | G53: 214-717-4021 | H53: z48a1r@gmail.com | I53: MON 9:00 PM | J53: TX Based, seems to know what hes doing, willing to dropship 945-324-6189 (Cell) Said He'll Email us | K53: He is working with Dr offices and hesaid that he is not ready to do marketing at the moment but will keep us as in his contact 6/10/26 9:27 VM Sent email - ben | M53: 46183.893 | O53: FALSE | Q53: call back in an hour
A54: ORT | B54: Jimmy | C54: NOT READY | D54: 46163 | E54: FOUR JOHNSON FOUNDATION | F54: LAURI JOHNSON | G54: 972-282-4842 | H54: fjf.prostheses@gmail.com | I54: FRI 9:00 PM | J54: SHe can bill medicare, and ship nationwide - ORT | K54: leg compressions , gaurmets , wheel chairs , ORT , maybe around 20 , she thought that we are more like a medical supplier not a marketing company she is not interested to do marketing right now but i persuaded her to talk to someone that might do a collaboration with her in her business ( long shot ) create a follow up call on tuesday same time | M54: 46164.893
A55: DMEDESK | B55: Jane | C55: NOT READY | D55: 46181 | E55: CARING ANGEL'S UNIFORMS & MEDICAL SUPPLIES, LLC | F55: Joyce Hargrave | G55: 601-807-9132 | H55: axmen2022@yahoo.com | I55: Fri 9:00 PM | J55: TX BASED, SHE DEAL WITH PPO INSURANSE SUPPLY ORT AND CGM, WANTED TO KNOW THE PRICES AND EXPLORE MORE
A56: ORT | B56: Jimmy | C56: NOT READY | D56: 46083 | E56: ODIN MEDICAL SUPPLIES | F56: AHMED ELHENAWY | G56: 201-705-7610 / +201222123227 | H56: ahmed@ODINMEDICALSUPPLIES.com | I56: MON 7:30 PM | J56: PPO, in the process of working with medicare | K56: email for pricing for cpl and cpa medicare insurance, home reinovation 5 stars bath ,angi's list contractor leads , hvac , appointment on bremises , franchises | M56: 46183.857 | O56: FALSE
A57: IMMUNE | B57: Jimmy | C57: NOT READY | D57: 46045 | E57: RAPHA LABORATORIES, LLC | F57: JERMAINE BROOKS | G57: 912-596-7683 | H57: Jbrooks@raphalab.com | I57: MON 9:00 PM 16/02 | J57: I reached him again, and he apologized for not showing up, saying it has been a hectic week. We agreed to have a follow-up meeting today at 9 p.m. ( JIMMY) 2/16/26 5:07 NCBased, Can do Immune and UTI Accept medicare and PT from all state wants to know more in the Email Tuesday 1:00 pm | K57: I reached him again, and he apologized for not showing up, saying it has been a hectic week. We agreed to have a follow-up meeting today at 9 p.m. ( JIMMY) 2/16/26 5:07 he is interested and he will review the document , he wants to follow up in a week , February 10th , send the calender the invite today and he will accept it, he is waiting for his machines to get validated in month and half or to month, set a meeting for him first of april | M57: 46084.92 | O57: FALSE
A58: ORT | B58: Jimmy | C58: NOT READY | D58: 46182 | E58: LAVINA MEDICAL SOLUTION LLC | F58: NOAH GILL | G58: Teams | H58: Teams | I58: Teams | J58: Following up with him on teams in the group
A59: IMMUNE | B59: Jimmy | C59: NOT READY | D59: 46140 | E59: LILLIE'S LAB SOLUTIONS | F59: BRITTNEY JOHNSON | G59: 254-833-5126 | H59: lillieslabsolutions@gmail.com Kajui29_89@hotmail.com | I59: Wed 10:30 PM | J59: TX Based, can accept medicare PT from all 50 states and can do NGS | K59: next thursday, she will be available from 8 am to 12:00, she is interested but she is not very sure that she can fund this, we talked about 50% upfront and maybe finding her an investor, she is still waiting on the new reimbursments, she will talk to the lab director and wants a small presentation next thursday but she might not attend or be available next week because of her daughters graduation , 05/13/2026 meeting next friday , 05/15/2026 she wants to include her lab director email to this so we could discuss our fees i already gave her an example upon the fee forimmuno , next meeting is monday 11:30 CST | M59: 46157.847 | O59: FALSE
A60: IMMUNE | B60: Jimmy | C60: NOT READY | D60: 46108 | E60: EXPERTUS LABORATORIES, INC | F60: JASON WEIL | G60: 407-375-8599 | H60: jason.weil@EXPERTUS.health | I60: MON 8:00 PM | J60: have the equipment and can accept medicare PT | K60: VM is full 6/10/26 10:47 Mike talked to him agreed on sending him the info again and agreed on anoher call next Tuesday 4/7/26 | M60: 46183.949 | O60: FALSE | Q60: left a voice mail
A61: ORT | B61: Jimmy | C61: NOT READY | D61: 46112 | E61: SOURCE DIRECT MEDICAL SUPPLY, INC | F61: CAROLINE JACKSON | G61: 219-472-8091 | H61: SOURCEDIRECTMEDICALSUPPLY@gmail.com | I61: WED 8:00 PM | K61: she said that she will call jimmy again later because she is out of the office right now | M61: 46183.858 | O61: FALSE
A62: IMMUNE | B62: Jimmy | C62: NOT READY | D62: 46070 | E62: WEST COAST LAB SCREENING | F62: MYRON RICHARD BANKS | G62: 323-308-9717 | H62: myron@wclabscreening.com georgie@wclabscreening.com | I62: WED 7:30 PM | J62: He is a collecting site but he is collaborating with a lab called DDC, he wants to ask them if they can do the NGS first and setted the meeting next WED 2/20/26 9:47 | K62: - upfront payment is a nono | M62: 46078.904 | O62: FALSE
A63: IMMUNE | B63: Jimmy | C63: NOT READY | D63: 46083 | E63: RADID RESULTS DNA LABORATORIES LLC | F63: JIMEKA LEVELLE FITZGERALD | G63: 757-800-7301 | H63: rapiddnalabs@gmail.com | I63: THU 4:00 PM | J63: She can do genetic testings | K63: She is afraid that this could put too much liability on her, agreed on discussing a trial phase with Geroge tomorrow 9:00 am EST 4:00 PM 4/29/26 9:17 ( JIMMY ) We need to send her a reference lab and another meeting set on friday 3/2/26 10:24 , she needs a reference lab to work with us | M63: 46141.889 | O63: FALSE
A64: IMMUNE | B64: Jimmy | C64: NOT READY | D64: 46070 | E64: VEIN WHISPERER EXPRESS LABS LLC | F64: CAROLE GILLING | G64: 352-328-8465 | H64: Cahrolle@gmail.com | I64: Thu 6:00 PM 26/02 | J64: she does not if she has the equipment or not, she is gonna reveiw the info and we will follow up with her same time next week 2/20/26 8:11 | K64: she is not sure that she has the equpment wla la , carolle is a nurse her boss is dr chemo and we will follow up m3aha | M64: 46079.759 | O64: FALSE
A65: ORT | B65: Jimmy | C65: NOT READY | D65: 46202 | E65: SUPERIOR SUPPORT STORE CORPORATION | F65: SALAMON ZALMEN BRULL | G65: 917-246-7322 | H65: shloimy7322@gmail.com | I65: THU 10:00 PM | J65: NY Based, can do nationwide, He only do Cash and private insurce at the moment and it might take a whild to start accepting medicare PT
A66: Lab | B66: Selene | C66: NOT READY | D66: 46232 | E66: MEDEX DIAGNOSTIC SERVICES INC | F66: Junaid (office Manager) | G66: 773 552 9901 | H66: healthcareinnovation360@gmail.com | I66: Tue 6:00 PM | J66: IL Based, accepts nationwide medicare patients does NGS,UTI,PGX meeting next tuesday 6 pm our time 7/29 | K66: - He said he spoke to his partner about our service and he said to get back to him around sept or october -8/4 selene | M66: 46238.814 | Q66: 1053122267
A67: Lab | B67: Jasmine | C67: Hold | D67: 46238 | E67: PREVENTIVE GENOMICS, LLC | F67: CHI NGO | G67: 281-857-4491 | H67: clientservices@preventivegx.com | I67: Thu 8:00 PM | J67: TX BASED but can operate nationwide except NY / PGx, UTI, NGS all in-house / private insurances and medicare part B only meeting set for thursday 8:00 our time 12:00 his time / called him to confirm our meeting time he mentioned that they are transitioning ownership and it would be best to discuss business in a month so scheduled a CB for 9/6
A68: ORT+CGM | B68: Selene | C68: Hold | D68: 46240 | E68: BENJAMIN'S DME LLC | F68: BENIAMIN YUNUS | G68: 516-398-8183 | H68: info@benjaminspharmacy.com | I68: Mon 5:00 PM | J68: NY Based ,supply ORT, CGM ,Mediacre liscenced ,ships nationwide ,interested to know more said to give him a call at 10.00 mon 17 am his time on mon 8/6 | K68: Said he is interested to work but he said that if he will start something he will start it in october cb 1/10 | M68: 46251.716 | Q68: 1417816737
A69: ORT+CGM+LYMPH W | B69: Nora | C69: Pending Medicare | D69: 46244 | E69: BRICKTOWNE PHARMACY LLC | F69: KALU NDUKWE | G69: 732-604-5576 | H69: bricktownepharmacy@gmail.com | I69: TUE 7:00 PM | J69: Based in NJ. He supplies ORT, CGM, and Lymph. He has Medicare and PPO and can ship nationwide 8/10 | Q69: 1578059283

Sheet Onboarded
A1: SUB | B1: Opener | C1: Status | D1: Date Added | E1: Company Name | F1: Authorized Person | G1: Phone | H1: EMAIL | I1: Meeting Time | J1: Opener Summary | K1: George's Notes | L1: Auto Scheduler | M1: Last Call | N1: Action | O1: Checkbox | P1: Log | Q1: NPI
A2: ORT | B2: Jane | C2: Onboarded | D2: 45701 | E2: E3 MEDISERVE LLC | F2: Heindel Adu | G2: office832-910-8844 / joyclen no, (346) 408-2478/MR.ADU NO (432) 269-5836 / 3467476708 ( joyclen) | I2: Mon 7:00 PM | J2: joyclen said they have medicare licence and work all states pcp and supply dme and cgm 2/13 send e mail and will call to set a meeting 2/13 WE SET A MEETING ON MONDAY ON 7PM OUR TIME 11AM THEIR TIME 2/13 | K2: Will get back to me today with an answer. | Q2: 1013790195
A3: ORT | C3: Onboarded | E3: OMNIS MEDICAL SERVICES LLC | F3: Jeremy Beck | Q3: 1114282688
A4: ORT | C4: Onboarded | E4: Global Medical Equipment | F4: Oskar Starker | Q4: 1134620537
A5: ORT+CGM | B5: Ben | C5: Onboarded | D5: 45707 | E5: Clayton Medical Supply Inc | F5: Judith Fairclough | G5: 404-808-5118 / 7709975660 | H5: 9493397142 | I5: Mon 6:30 PM | J5: Very Interested does Medicare, All States sent prices Monday 6:30 | K5: Will discuss and get back to me regarding CGM. DOC 2/24/2025 | Q5: 1134722390
A6: ORT+CGM | B6: Ben | C6: Onboarded | D6: 45736 | E6: Healthmed Services Llc | F6: Demetrios Nikoloulis | G6: 708-543-0563 | H6: dn@nexushq.net | I6: Fri 10:30 PM | J6: Explained Process, need a docu sign from the patient, Understands the process seems to know what he's doing, -Has issues IL Based, Ships to all states using his partners company, in utah, getting a new PTAN, but working in the 40 states | K6: Will try PPO, NI in the rest because of compliance. He has a campaign for personal injury that he will give me a proposal for in the future, We should start very soon. | M6: 0.85 | Q6: 1184202699
A7: ORT | B7: Selene | C7: Onboarded | D7: 46009 | E7: BRIGHT PATH DME LLC | F7: JASON COREY GOODMAN | G7: 314-629-5794 | H7: Jason@brightbathdme.com Mike@brightbathdme.com | I7: Thu 5:00 PM | J7: - MO Based , Medicare liscenced , ships around 20 states meeting today 5 pm our time -selene 12/18 | K7: he has a partner ( michael = marketer ) , they are doing consultancy to 10 other dme companies , they wanted discounted prices and a prove that every lead is generated through opt - in data , he is interested in a trial phase and then he might work with us after the holidays , mainly interested in ortho but can do CGM , | Q7: 1184412082
A8: ORT | B8: Selene | C8: Onboarded | D8: 45708 | E8: DELTA MEDICAL EQUIPMENT LLC | F8: MOE MOSTAFA | G8: 248-564-6565 - WA 949-339-7142 | H8: Mohammad Alhaji/ 619-519-6504 info@deltadme.com - Dmedical550@gmail.com | I8: Thu 7:00 PM | J8: - Medicare liscenced , can ship JUR B , CGM and DME, 20 pts per week PCP meeting Thursday at 12 est 7 pm our time -selene 2/20 - CALLED HIS PARTNER MOE MOSTAFA AND THEY SAID THEY GOT BACK THEIR NPI MEETING TMRW 5.30 OUR TIME 4/22 | K8: Interested will discuss with his partner and get back to us on Monday. Spoke today, a bit unexperienced and wanted to go for a trial first. Will check the contract and get back to me tomorrow. In the process of renewal of his license and his NPI is Inactive. I will call at the end of April. DOC 3/26/2025. DOC 4/23/2025 Trial period will start this week and he should place an order next week. | M8: 0.85 | Q8: 1225656291
A9: CGM | B9: Ben | C9: Onboarded | D9: 45658 | E9: Home Care Medical Supplies LLC | F9: George Kaiteris | G9: 818-581-4200 | H9: george@hcmedicalsupplies.com | I9: Fri 5:00 PM | J9: -CA Based but ships to all states, Been talking since january, knows well about the process - he also seem to own an internet company and some other businesses, could be a goof fit to talk with about VAs and CX work | K9: voice mail | Q9: 1235990193
A10: ORT | B10: Ben | C10: Onboarded | D10: 45572 | E10: Pro medical supplies | F10: Michael Girgis | G10: 330-550-0553 | I10: Friday 6:30 | J10: Business : DME & CGM Call Time : {05:09} Very interested, Discussed process, licenced in All States First time dealing with marketing Didn't get into too much details with him as he didnt have any specific concerns | K10: Onboarded | Q10: 1255067385
A11: CGM | B11: Selene | C11: Onboarded | D11: 45792 | E11: Golden Medical Supply Llc | F11: Michael Bitelli | G11: 516-633-6636 | H11: michaelgoldenmed@gmail.com | I11: Mon 8:00:PM | J11: - Medicare Liscenced , all states, PCP, ORT and CGM meeting thursday 11 am est and 5pm our time -selene 3/24 | K11: We covered all the process and prices, we will do demo and onboarding tomorrow DOC 5/19/2025. In trial | M11: 0.9 | Q11: 1316554942
A12: ORT+CGM+LYMPH W | B12: Jimmy | C12: Onboarded | D12: 46034 | E12: RIVAID LLC | F12: Yoel Gross | G12: 718-930-0698 | H12: Ygross0698@gmail.com | I12: Transferred right away | J12: NY based provides ORT+CGM+LYMPH W can ship nationwide has the license | O12: FALSE | Q12: 1356024087
A13: ORT+CGM | B13: Selene | C13: Onboarded | D13: 45755 | E13: MASTECH MEDICAL EQUIPMENT SOLUTIONS LLC | F13: Ramon Taylor | G13: 757-831-7908 | H13: mastechmed99@gmail.com | I13: Wed 4:00:PM | J13: Medicare liscenced , nationwide, PCP ,ORTCGM he said he takes between 10 to 15 pts per week meeting wed 10 am est 4 pm our time -selene 4/8 | K13: Call went well. He will talk to his biller but he is up for it and really interested. Will onboard him for VA for now untill he expand the states. | M13: 0.9 | Q13: 1366260788
A14: ORT | C14: Onboarded | E14: NJ MEDICAL SUPPLIES LLC | F14: Genessa Terrizzi | Q14: 1396208633
A15: Lymphadema | B15: Ben | C15: Onboarded | D15: 45979 | E15: HOLLIS CHEMISTS LLC | F15: DAVID KANDOV | G15: 718-470-2066 | H15: hollischemists@gmail.com | I15: Tue 9:30PM | J15: NY BASED, BILLS MEDICARE FOR LYMPHA | K15: 12/02/2025 10 pm our time a bit skyptical of the fruad situations lately , wants to do biweekly and wants the website to check which states can he work in | Q15: 1407691694
A16: ORT | C16: Onboarded | E16: PRIME ORTHO FITTING, LLC | F16: Mena Fadel | Q16: 1417731795
A17: Lymphadema | B17: Jane | C17: Onboarded | D17: 45973 | E17: OPTIMISTIC HEALTHCARE SOLUTIONS LLC | F17: Deshavonna Jasmine (CEO ) Anthony assistant | G17: 800-674-4440 / 3465514222 direct number | H17: dj@optimistichealthcare.com dj@ohcpharmacy.com | I17: Thu 7:30 PM | J17: Tx BASED i soplke with anthoney her assitant said they are medicare liscensed and ship all states , supply lymph wraps, meetint tomw 7;30 our time | K17: she is interested we sent her the contract and all the information (11/14/2025), she didn't recieve the email and we sent it again and she will respond to the email 11/17/2025 | O17: FALSE | Q17: 1457139768
A18: ORT | B18: Judy | C18: Onboarded | D18: 45694 | E18: Sbs Medical Supplies Llc | F18: Sergey Simcha Suleimanov | G18: 602-612-2000 | J18: all states/ 20 pts/ told him our process/ telemed and pcp | M18: 1 | Q18: 1467205401
A19: ORT+CGM | B19: Ben | C19: Onboarded | D19: 45817 | E19: RAPHA CARE SOLUTIONS LLC | F19: Raheel | G19: 703-930-2669 | H19: info@raphacaresolutions.com | I19: Mon 8:30 PM | J19: -VA Based, Ships all states recently got ptan, works ort and cgm and interested in more products, knows about our scope of workm, onboarding process | K19: Talked to him , explained how they would start with us , new DME , needs guidance , they will probably start with 1 agent and then scale up | M19: 0.75 | Q19: 1497529606
A20: ORT | B20: Jane | C20: Onboarded | D20: 45701 | E20: CPR DME LLC | F20: Gabriel Colmenero | G20: 956-241-0408 | I20: Wed 10:00 PM | J20: tx based and work all states, medicare liscenced DME and for CGM ,(still trying to find a supplier working on it) , PCP , pt intake per week varies meeting mon at 2 pm CST 10 pm our time 2/13 | K20: Trail Phase 07/23/2025 , Waiting for the Trial | Q20: 1538946520
A21: ORT | B21: Selene | C21: Onboarded | D21: 45838 | E21: LIVEWELLDME LLC | F21: Zaman Ali Ansari | G21: 872-806-5630 | H21: livewelldmellc@gmail.com | I21: Wed 8:00:PM | J21: - IL based ship all states medicare liscenced ORT CGM MEETING TMRW AT 12 PM CST 8 PM OUR TIME 6/30 - Talked with him said to cb next monday because he is still discussing it selene 7/10 - zaman gave a cb said prices are expensive but will dicuss it tommrow at 1 pm cst 9 pm our time 8/5 | K21: Zaman was more interested in Braces than CGM, then i convinced him of CGM , But he took the prices with two modules ( pay per prescription and pay per hour ) and he will think about it and get back to me , Call him 07/10/2025 | Q21: 1639992530
A22: ORT | C22: Onboarded | E22: Boca Connections | F22: Khalil Shafiq | Q22: 1679248447
A23: CGM | B23: Ben | C23: Onboarded | D23: 45689 | E23: Adl Ortho Solutions Inc | F23: Jose Tamez | G23: 956-578-2446 | H23: JOSE@ADLORTHO.COM | I23: Mon 9:30:PM | J23: NY Based, interested about cgm, knows about prices and process | K23: Sent an email + contract , Will send him the invoice shortly | M23: 0.8 | Q23: 1710524962
A24: ORT+CGM | B24: Ben | C24: Onboarded | D24: 45590 | E24: Medi Source Medical Supply | F24: Aaron Mosheyev | G24: 646-269-0989 | I24: Mon 6:30 PM | J24: Business : DME & CGM NY based all states, works with medicare, interested spoke about prices, process, Will wait for his partner to come back from his vacation before he takes any step working with us. | K24: NO ANSWER | Q24: 1760247704
A25: CGM | B25: Judy | C25: Onboarded | D25: 45855 | E25: Direct Dme, Inc. | F25: Jennifer Colby | G25: (586) 243-3148 | H25: jcolby@rtdlabs.com | I25: Fri 7:00:PM | J25: Medicare licensed, CGM, ship to most states, seemed intersted scheduled a meeting for tmr at 12pm EST | K25: I had a board meeting with 6 of them , they asked me all the questions , they wanted to have a set up maybe for the first of august , they want us to send them a contract then they will send us BAA to sign , they want to work first in 10 states only and then add more states moving forward | Q25: 1851448120
A26: ORT | B26: George | C26: Onboarded | E26: DEDICATED MEDICAL PROVIDERS LLC | F26: Peter Kuntz | Q26: 1881123271
A27: ORT+CGM | B27: Selene | C27: Onboarded | D27: 45890 | E27: PROSUM DME LLC | F27: Najee | G27: 747-201-9362 EXT 808 / 7472001417 DIRECT LINE | H27: info@prosumhealth.com | I27: Fri 11:00:PM | J27: CA based can ship all states but said want to start with JUR D since they are looking for CGM nad ORT Suppliers Najee said that they are accredited they look new meeting tmrw thu 1 pm pst 11 pm our time -selene 8/21 | K27: Ben Arthur SEND THEM ALL THE INFO FOR cgm / oRTHOPEDIC BRACES , tHE PRICES , tHE WEBSTIE FOR THE FREE STATE ZONE waiting for the account to be sret up for monday , Check on the wednesday 09-24-2025 | Q27: 1932885985
A28: ORT+CGM | B28: Selene | C28: Onboarded | D28: 45785 | E28: CARING MED LLC | F28: BASHAR IMASH | G28: (478) 972-9724 | H28: Bashar@caringmeds.com | I28: Mon 6:30:PM | J28: - Mediacre Liscenced , ships all states have liscencetp supply CGM ORT he feels inexperienced i had to throughly explain what we do but he really like our services and wnated to know more meeting Mon 11.30 est 6.30 pm our time -selene 5/8 | K28: he is waiting for the states that doesn't require a license to work , I will send him today and get back to you | M28: 0.9 | Q28: 1982001384
A29: 2025 -
A30: 2026 -
A31: ORT | C31: Onboarded | E31: PROCARE EQUIPMENT AND SUPPLIES INC | F31: KHALIL SHAFIQ | Q31: 1174356141
A32: ORT | C32: Onboarded | F32: Julio Amorim
A33: ORT | C33: Onboarded | F33: Waqas Chaudhry
A34: ORT | C34: Onboarded | F34: Lahsib Shaf
A35: ORT | C35: Onboarded | E35: PROCARE EQUIPMENT AND SUPPLIES INC | F35: Khalil Shafiq
A36: ORT | C36: Onboarded | E36: Medical Supply Pointe | F36: Vincent Orobosa
A37: ORT | B37: Ben | C37: Onboarded | E37: Dme Direct Inc | F37: David C Ogbolumani
A38: ORT | B38: Jane | C38: Onboarded | D38: 45720 | E38: LIFE DME LLC | F38: Ferass Safadi | G38: 219-795-1296 ext112 | I38: Fri 5:30 PM | J38: il based , pcp , cgm, medicare licensed, meeting 5:30 ou time and friday and 9 :30 am 3/4 | K38: Interested in CGM CPL, will crunch the numbers and we should meet again DOC 3/7/2025. Friday 10 AM follow up, will need a proposal on the pricing and a contract. | M38: 0.9
A39: CGM | B39: Selene | C39: Onboarded | D39: 45757 | E39: READY CARE DME | F39: Brian White | G39: 774-418-4268 / 781-514-5414 WA | H39: readycaredme@gmail.com / brian@readycaredme.com | I39: Fri 6:00 PM | J39: -Medicare Liscenced, all states , CGM but he said if he liked us will expand ORT PCP he said he wants to work with telemarketers he said he will work with us as long as we follow the (medicare sfae harbour guidlines) meeting Fri 12 pm est 6 pm our time -selene 4/10 - He said he is interested to have another call he said to talk on fri 3 pm est 9 pm our time -selene 5/7 | K39: Interested in CGM, will require contract to review. plus the samples... Has concerns with payment and need referenece to check our service with. DOC 4/14/2025 We spoke about his contract and said we should meet in the middle in regards to the script he wants us to use! I will wait for him to get back to me after he talks to his Lawyer. Will call back on Monday because his lawyer didn't get back to him yet. DOC 4/18/2025. DOC 4/21/2025. his lawyer didn't get back to him yet, I will have to CB NO Answer 3 times 4/29/2025 | M39: 0.75 | Q39: 1679327365
A40: ORT+CGM | B40: Jane | C40: Onboarded | D40: 45761 | E40: BESTCHOICE DME, INC. | F40: STEPHANIE | G40: 917736 2207 | H40: ncastro@newsolutionny.com | I40: Tue 6:00:PM | J40: MR NELSON, ny based , ship all states dme and cgm, have medicare licensed and waiting for the medicaid prefer to work with both license but he is intrested to attend meeting to speak about it then will see how it goes from there, pcp orders, meetoing tomw 6 pm ou time and 12 pm his time 4/14 | K40: Very interested, will talk to his team to get them on a DEMO for tomorrow and once we are done we will drop a trial patient and wait for them to process and launch our campaign next week. We had a Demo today 4/16/2025 and we will start the trial potentially next Monday.. DOC 4/21/2025 He is still sitting up accounts with the suppliers, Will give me a call back this week to start trial. Will take trial on Friday because he can't bill before the 6th. DOC 4/29 | M40: 0.95
A41: Solar | B41: Selene | C41: Onboarded | D41: 45798 | E41: Reliable Power and Solar | F41: Chris DiPasquale | G41: (732) 367-1166 | H41: chris@getrpsnow.com | I41: Wed 7:00:PM | J41: NJ Based seemed interested heard the entire pitch lol explained everything and he liked that he will not pay unless its for a sitdown appt 5/21 | K41: we received Zipcode , Team is working on sending the first order, Communication method : Calls or Emails | M41: 0.9
A42: Solar | B42: Jane | C42: Onboarded | D42: 45807 | E42: Direct Solar LLC. | F42: Mr.keith | G42: (973) 901-1233 | H42: keith@localpowerauthority.org | J42: NJ based, serve ny nad nj, 2 appointments a day | K42: Really good prospect, we agreed to pretty much everything and we will finalize the deal next week. and start on Monday the 9th , Waiting on generation to Have him pay for his first appointment | M42: 0.9
A43: Solar | B43: Jane | C43: Onboarded | D43: 45810 | E43: Your Partner in Solar | F43: MR. WAYNE | G43: 718 812 4758 | H43: wayne@yourpartnerinsolar.com | J43: NJ BASED, SEEM INTRESTED, SERVE NJ AND ALITTLE AREAS OF NY, EXPECT 2 PER DAY APPOINTMENTS, THE ZIPCODES HE WORK IN IS, 08873, 08854, 08846, 08901, 08902 WHICH IS AN HOUR AND HAVE FROM HIS PLACE 6/2 | K43: Intersted to start with one app up front, and increase volume moving forward. Will start after EID. | M43: 0.9
A44: CGM | B44: George | C44: Onboarded | D44: 45835 | E44: MORNING LIGHT DME LLC | F44: Tofi sakris | H44: MorningLightDME@gmail.com
A45: CGM | B45: Jane | C45: Onboarded | D45: 45874 | E45: TLC MEDICAL SUPPLIES INC | F45: Yemane Woldegabriel | G45: 323 861 6800 | H45: tlcmedicalsuppliesla@gmail.com | I45: Wed 9:00:PM | J45: CA BASED , MEDICARE LICENSED, SHIP ALL STATES,CGM, PCP he is will to work with us in manay other thing such as electric wheelcharis , meeting tomw 9 pm our time | K45: Ben please send an email with scenarios / products / sample / recording / typt of items / billing Codes and 3 months of supply | Q45: 1487129714
A46: Lymphadema | B46: Selene | C46: Onboarded | D46: 45973 | E46: TIGHTLYNX LLC | F46: Gyasi Jackson | G46: 347-854-9137 / 3477912558 | H46: Gjackson@TIGHTLYNX.com | I46: Thu 8:00 PM | J46: NY based , Medicare liscenced , ships all states supplies lymph wraps interested to know more meeting tmrw at 8 pm our time 1 am est 11/12 | K46: meeting monday and tuesday same time we need to send him a contract and price list for a pay per hour or per wrap | Q46: 1164831053
A47: Lymphadema | B47: Jane | C47: Onboarded | D47: 45973 | E47: ON THE GO MEDICAL SUPPLY LLC | F47: Nicole Wilson | G47: 888-914-6633 | H47: nwilson@onthegomedicalsupply.net | I47: Wed 10:00PM | J47: TX-based, medicare lisenced, supplu mainley tx and la ,but can shipp other states, she was ni about marketing company scared of scams, but i told her our process and send email, she was okay send email and call nback late aftrnoon 2pm her time nwilson@onthegomedicalsupply.net | K47: wound care products, nurse practioner multiple wound care, tx La , mo, nv . pending MS & florida she is accreditated and can work in them she would need a sample recordings prescriptions and the Fees that we will charge | Q47: 1942060702
A48: ORT+CGM | B48: Selene | C48: Onboarded | D48: 45876 | E48: ANTIOCH CARE DME | F48: Christopher Albert | G48: 925-350-0184 | H48: INFO@ANTIOCHCAREDME.com | I48: Mon 10:00:PM | J48: - CA based medicare liscenced ORT CGM ships locally but willing to expand interested in other campaigns too meeting 12 PDT 10 pm our time today -selene 8/7 - Meeting set for mon 15th 10.30 pm still wants CGM 12/11 | K48: HE is interested he wants an email contains everything regardings CGM "- He needs contract, Scope of work stating compliance ,pricing and credintialing of lymph 11/13 - VM 11/25 - hUNG UP CB MONDAY 11/25 ", he said he will do the payment in an hour | M48: 46059.781 | O48: FALSE | Q48: 1710871637
A49: CGM | B49: Jane | C49: Onboarded | D49: 46037 | E49: ABACOA MEDICAL SUPPLIES INC | F49: JP Dickson | G49: 561-843-8286 | H49: jp@abacoamedical.com | I49: Fri 7:30 PM | J49: FL BASED, SUPPLY ONLY CGM ALL STATES AND BILL MEDICARE , SET METTING TOM W 7:30 OUR TIME, | K49: nation wide , freestyle + dexcom g7 | M49: 46087.849 | O49: FALSE | Q49: 1619465689
A50: ORT | B50: Selene | C50: Onboarded | D50: 46043 | E50: PAYBACK TIME | F50: CHESKY FRIEDMAN | G50: 845-866-1121 | H50: chesky3048@gmail.com | I50: Thu 7:15 PM | J50: - NY Based, Medicare Liscenced Ships locally but willing expand all states ORT meeting tmrw 6our time 1/21 | K50: Send Price list , contract template , he has no problem to work in other , next thursday 7:00 pm ,he is waiting to verify some stuff and talk to his consultant and get back to us - DOC said that he is interested but wants us to contact him next week fri -selene 2/5 , Mail box is full and he is not available -spoke to chesky said that when he sets up his company and ready to bill medicare he will call us he said he really wants to work with us and he said he was telling his friend about us and our work yesterday cb in 2 weeks -selene 2/25 cben 25/3 when he's ready he'll get back to george - ben we signed the contract waiting for him to pay the invoice | M50: 46223.966 | O50: FALSE | Q50: 1316800741
A51: ORT+CGM | B51: Ben | C51: Onboarded | D51: 46070 | E51: MO MED SUPPLY LLC | F51: SYED KIDWAI | G51: 224-409-7428 | H51: momedsupplies@gmail.com | I51: =HYPERLINK("https://calendar.google.com/calendar/u/0/r/eventedit/NjJpcjVrNWVoazhma2U0aG9pZW4wdGg0YTYgYzM5ZjIxNjY2YTJjNzBkNjQ0MDI0YmQyOWM3ZmM5ODM3OTY2MmY3OTJlNWEwNDdjZGIzNTdhNDJiM2M1N2QwNEBn", "Wed 18:30 PM") -> Wed 18:30 PM | J51: IL, Interested, confirmed email asked for prices, sent it 2/17 | K51: - 5 to 6 weeks to get paid VM - ben send an email to find which states he can bill for so we can send a trial - ben -VM Reschedule - call in 2 hours | M51: 46139.512 | O51: FALSE | Q51: 1972383388
A52: ORT | B52: George | C52: Onboarded | D52: 46008 | E52: DME HEALTH SOLUTIONS LLC | F52: NAYAN S PATEL | G52: 888-454-5526 | O52: FALSE | Q52: 1376472001
A53: ORT | B53: Jimmy | C53: Onboarded | D53: 46080 | E53: ALLIED MEDICAL HEALTH LLC | F53: FERMON GRAYS | G53: 305-788-0000 | H53: fermon.grays@me.com | I53: TUE 7:30 PM | J53: He said he is not ready for Medicare, can do PPO FL based just got his medicare license and ready now | K53: Ex software engineer, no expereince in DME, had issues before is very scared, wants to do JUR A,B &C not interested in paying upfront sent an email anyways, george; he will have a followup call on wednesday same time , he would pay 50% upfront we didn't say anything about some trials and on wednesday we would decide the starting date, we need to send him a contract / scope of work 4/20/26 | M53: 46132.868 | O53: FALSE | Q53: 1841989019
A54: ORT+CGM | B54: Selene | C54: Onboarded | D54: 46196 | E54: RAPID REACH MED SUPPLIES LLC | F54: USMAN MOHAMMAD | G54: 409-302-2640 | H54: rapidreachmedsupplies@gmail.com | I54: THU 9:00 PM (Wednesday) | J54: IN Based, PPO (Humana ,Wellmed, Bluecross) , provides ORT CGM dropshisp nationwide wants a video meeting thursday at 9 pm our time 6/10 | K54: he has the insurances written + anthem + he can work in all states but he only wants to start with 2-3 patients only as it's a new DME , I told him i will check with the team about this possibility and get back to you and also we will talk around monday 8 pm our time if it's not available choose a slot from 8 pm to 10 pm our time - Will create a whatsapp group to discus the prices and see when to start he said they might start second week of july and george will send the prices 6/29 | M54: 46202.849 | Q54: 1568396620
A55: ORT+CGM | B55: Jimmy | C55: Onboarded | E55: PLATINUMCARE DME LLC | F55: OMAIDULLAH NOORI | G55: 978-227-7910 | H55: usmc.force1991@gmail.com 5/22 | I55: FRI 11:00 PM | J55: He can bill medicare, and ship nationwide - ORT/CGM | K55: he is not really understanding the business he has partners from overseas that handles everything but he is interested to open another llc and apply for other insurance ( i will send him an email to find a way that we can work together) / he will call the partners because they are claiming before shipping / he is asking about whether he needsto get preapproved before shipping the item , he got humana insurance He will talk to his partner and get back to george / humana optim all states 5 patients, | M55: 46198.948 | Q55: 1457288326

Sheet No-Show
A1: SUB | B1: Opener | C1: Status | D1: Date Added | E1: Company Name | F1: Authorized Person | G1: Phone | H1: EMAIL | I1: Meeting Time | J1: Opener Summary | K1: George's Notes | L1: Auto Scheduler | M1: Last Call | N1: Action | O1: Checkbox | P1: Log | Q1: NPI
A2: ORT+CGM | B2: Jimmy | C2: No - Show / Callback | D2: 46008 | E2: QUIKCPAY COM LLC | F2: Meeting is with SYED NAJAM UL HASSAN ( Manager ) ANILA KIRMANI MBR | G2: 346-219-9911 | H2: Quickpaycomllc@gmail.com | I2: =HYPERLINK("https://calendar.google.com/calendar/u/0/r/eventedit/MTcxYmEyazk5OTJ2bG03aDAxOHZvaTRucGIgYzM5ZjIxNjY2YTJjNzBkNjQ0MDI0YmQyOWM3ZmM5ODM3OTY2MmY3OTJlNWEwNDdjZGIzNTdhNDJiM2M1N2QwNEBn", "Thu 8:30 PM") -> Thu 8:30 PM | J2: Meeting is with MR. Hassan ( Manager ) ANILA KIRMANI MBR TX based medicare licensed,supply lemphadema wrap + CGM + ORTHO, can ship to all states meeting 8:30 PM | N2: FALSE
A3: ORT+CGM | B3: Jane | C3: No - Show / Callback | D3: 46052 | E3: Acute Medical Supply | F3: Joseph Kanefsky | G3: 954-804-2825 | H3: joe@acutemedsupply.com | I3: Mon 8:30 PM | J3: FL BASED, SUPPLY ORT, SHIP ALL STATES AND BILL MEDICARE, MEETING MONDAY | K3: i called back he said he dont carry enough of those kind of items in stock, he thought he can full fill them 2/10 | M3: 46063.691 | N3: FALSE
A4: ORT+CGM+LYMPH W | B4: Selene | C4: No - Show / Callback | D4: 46049 | E4: 3M MEDICAL ASSOCIATES | F4: Atta Shahid/ BOB | G4: 618-554-3683 | H4: attashahid@shmatallc.com | I4: Wed 5:30 PM | J4: -OH Based , Medicare liscenced , nationwide supplies ORT ,CGM ,Lymph, spoke to Atta he said Bob the decison maker will speak to george meeting tmrw 5.30 our time -selene 1/27 salem - GK Left a message -selene 2/5 | N4: FALSE | Q4: 1851124671
A5: ORT | B5: Selene | C5: No - Show / Callback | D5: 46045 | E5: MIRACLES MEDICAL SUPPLIES LLC | F5: LATASHA LOOPER | G5: 904-574-7180 | H5: latashalooper@gmail.com | I5: Mon 8:00 PM | J5: - FL Based, Medicare Liscenced Ships all states ORT meeting mon 8 pm our time 1/23 - doc 2/5 sAID TO RESEND EMAIL CB TMRW -selene 2/5 | N5: FALSE | Q5: 1821897471
A6: ORT | B6: Selene | C6: No - Show / Callback | D6: 46041 | E6: GROVER MED LLC | F6: RAVI GROVER | G6: 516-882-7473/ 917-299-6051 | H6: Grovermedllc@gmail.com | I6: Tue 7:30 PM | J6: - NY Based, Medicare Liscenced Ships all states ORT meeting tmrw 7.30 our time 1/19 cb fri 1/22 | K6: i spoke to the operator he is not available today he told me to try tomorrow | N6: FALSE | Q6: 1649807454
A7: ORT | B7: Selene | C7: No - Show / Callback | D7: 46035 | E7: ICON MEDICAL SUPPLIES, LLC | F7: DANIEL PICARD | G7: 631-673-1984 | H7: iconmedicalsuppliesllc@gmail.com | I7: Wed 6:00 PM | J7: NY Based , Medicare liscenced ships nationwide supplies ORT meeting video tmrw 6 pm our time -selene 1/13 - gk left a mesage 2/5 - cb on fri 3/4 | K7: didn't show up | N7: FALSE | Q7: 1922683069
A8: ORT+CGM | B8: Jane | C8: No - Show / Callback | D8: 46034 | E8: XO DME LLC | F8: CARLOS BONILLA | G8: 951-490-8450 | H8: carlos@nexuspt.com | I8: TUE 10:30 PM | J8: Ca based, medicare licensed, can bilL, but dont have the supply he will get it by END week of january, the we could work together, asked him to send email ,and want to see how we work meeting tomw 10:30pm/ HE ASKED TO CALL BACK BY END OF MARCH | K8: asked cb end of march | N8: FALSE
A9: IMMUNE | B9: Selene | C9: No - Show / Callback | D9: 46028 | E9: MEDEX DIAGNOSTIC SERVICES INC | F9: MOHAMMAD SIDDIQUI | G9: 773-544-0201 | H9: junaid 773 552 9901 healthcareinnovation360@gmail.com | I9: Thu 5:30 PM | J9: ILL bases , accepts nationwide medicare patients provides immune genetic testing said wants to speak to george before sending email said to call him thursday 5,30 our time -selene 1/6 said to give hima call tmrw we 21st 1 pmcst 1/12 | K9: Does uti/ pgx | M9: 46224.884 | N9: FALSE | Q9: 1053122267
A10: ORT+CGM | B10: Jane | C10: No - Show / Callback | D10: 46027 | E10: ODESSA MEDICAL SUPPLY INC. | F10: Mariet Torosian | G10: 818-426-4815 | H10: info@odessamedicalsupply.com, | I10: Thu 8:30 PM | J10: ca basesd ship all states, medicare licensed , supply ort and cgm, send email | N10: FALSE
A11: ORT | B11: Selene | C11: No - Show / Callback | D11: 46007 | E11: VM HEALTHCARE SUPPLY | F11: MARTA VISCOMI | G11: 786-409-1864 | H11: martaviscomi@hotmail.com | I11: Wed 8:00 PM | J11: FL Based , Medicare, Ships all states supplies ORT she said she will speak to her office manager to see how much ORT in stock they have. Not the best english ,she is very busy today because she is travelling she said to call her tmrw meeting wed 1 pm EST 8 pm our time 12/15 | K11: Voicemail 12/17/2025 | N11: FALSE | Q11: 1386412153
A12: ORT+CGM+LYMPH W | B12: Ben | C12: No - Show / Callback | D12: 45985 | E12: Marquis Health Solutions Inc | F12: Kyle Webb | G12: 415-710-4094 | H12: kwebb@marquishealthinc.com | I12: Tue 11:00 PM | J12: wants to talks to his Compliance Officer, meeting tuesday VM 2/5 | K12: Voice mail 01/13/2025 VM | M12: 46155.979 | N12: FALSE
A13: Lymphadema | B13: Jane | C13: No - Show / Callback | D13: 45973 | E13: HEIDE'S MASTECTOMY SERVICES, INC. | F13: KATHLEEN HEIDE-WRAZIDLO | G13: 952-925-7837 | H13: kathyheide@aol.com | I13: Thu 9:30 PM | J13: MN based, works with the whole B jursdiction I don't know if they can expand more than that. Spoke about the process, sent her an email and google invite. | N13: FALSE
A14: RE | B14: Selene | C14: No - Show / Callback | D14: 45958 | E14: Next Step Home Deals | F14: Ollie Garcia | G14: (717) 790-1735/(717) 827-6916 | H14: ollie.garcia696@gmail.com | I14: Thu 11:00PM | J14: - Ollie the owner provides fair cash offers Interested to know more about our lead generation process and how we operates explained process and qulaity check and payment module meeting Thursday 4 pm EST 11 pm our time -selene 10/28 - I was able to reach out to him he said he thought about it he seems hesistant to enter meeting he asked prices he said he was ni because he found another way but i convinced him to review what we have he said he will review the email will reach out on monday 10/31 | N14: FALSE
A15: ORT+CGM | B15: Ben | C15: No - Show / Callback | D15: 45897 | E15: Care First Equipments Llc | F15: Azher Farooq | G15: 270-293-7849 | H15: azherf04@gmail.com | I15: Fri 11:00PM | J15: Medicare licensed, all states, spoke about our process but not deeply, didn't send him an email about our company just the meeting -called again he had a fraud concern, that what we do is fraudulent, I handled him and meeting is today at 2pm their time | K15: direct to Voice mail 08/29/2025 | N15: FALSE
A16: ORT+CGM | B16: Selene | C16: No - Show / Callback | D16: 45925 | E16: Novamed Care Llc | F16: Muhammad Qamar | G16: 718-249-9690 | H16: novamedcare@gmail.com | I16: Wed 9:00PM | J16: Medicare licensed, all states, told him our process, he was not rude at all sent only the calendar invitation | K16: DOC 2/5 VM | M16: 46058.802 | N16: FALSE | Q16: 1396635629
A17: ORT+CGM | B17: Jane | C17: No - Show / Callback | D17: 45919 | E17: Family Medical Supply Inc | F17: Ruslan Musaev | G17: 347-708-3333 | H17: familymedicalsupply@gmail.com | I17: Mon 6:30PM | J17: Tristate based, willing to do all states, he seemed interested and wanted to have a call he even checked on the phone with me his calendar to make sure that he's free | K17: not available ight now assistant took a message and will call me back | N17: FALSE
A18: Home Improvement | B18: Jane | C18: No - Show / Callback | D18: 45916 | E18: TBH Remodeling LLC. | F18: Mr.aquiles | G18: 713-269-3492 | H18: texashomeremodeling9@gmail.com | I18: Wed 6:30PM | J18: he is intrested and he do all the remodelinmg but he works in texas only | K18: interested | N18: FALSE
A19: Auto Insurance | B19: Selene | C19: No - Show / Callback | D19: 45882 | E19: Southland Auto Insurance Services | F19: Christopher Gomez | G19: 623-882-4574 | H19: info@southlandinsurancesvcs.com | I19: Tue 10:00:PM | J19: - AZ based chris is a partner at the agency he said he needs VAs in the next couple of months and he was interested to have an email and get an intro call next tuesday 11 pm our time 1 pmm MST | K19: AZ TX ALL INUSRACCE EXPECT INSUERANCE CREATE PRESTATION | N19: FALSE
A20: ORT+CGM | B20: Selene | C20: DNC | D20: 45897 | E20: MO MED SUPPLY LLC | F20: Syed H Kidwai | G20: 224-409-7428 | H20: momedsupplies@gmail.com | I20: Tues 7:30PM | J20: -MO Based , Medicare liscenced , CGM ORT sent email has issues with optin forms want legit stuff he said he wants the opt in forms stuff to be included in the contract he said he wants to works only if its legit meeting tuesday 9/2 7.20 our time 11.30 AM CST -selene 8/28 | K20: he said he will call me back later 09/02/2025 - Meeting moved to Mon same time 9/4 | O20: FALSE
A21: ORT+CGM | B21: Jane | C21: No - Show / Callback | D21: 45895 | E21: Allboro One Medsupply Inc. | F21: Josephine Prinston | G21: 347-247-7696 | H21: jprinston6@yahoo.com | I21: Wed 6:30PM | J21: NY based but can ship to all states, Medicare licensed, spoke about the process, she told me that she's the decision maker however she tried to transfer me to someone else so I'm not sure if she's the only decision maker or not | K21: she wanted to reviewe the email with me for us to explain everything for her , that she will call me and discuss with me | O21: FALSE
A22: ORT+CGM | B22: Ben | C22: No - Show / Callback | D22: 45888 | E22: Lula Bell Medical Supplies & Equipment Llc | F22: Troyetta Howard | G22: 346-329-8888 | H22: LULABELLMEDICALSUPPLIESLLC@GMAIL.COM misstrhoward85@gmail.com | I22: Thu 9:15 | J22: - TX Based, licensed interested in both cgm & ort, sent her info with ort prices | K22: voice mail | O22: FALSE
A23: ORT | B23: Selene | C23: No - Show / Callback | D23: 45891 | E23: Active Therapy Supply, Inc | F23: Roza Minazova | G23: 718-544-2850 | H23: ectivebraces@gmail.com | I23: Mon 7:30PM | J23: ERROR: Invalid date format | K23: on a vacation and will be back in two weeks (09/19/2025) | O23: FALSE | Q23: 1033116447
A24: ORT | B24: Jane | C24: No - Show / Callback | D24: 45891 | E24: WEST COAST DME & SUPPLIES LLC | F24: Mr. Michael Gregory Wells | G24: 909 908 3920 | H24: mwells@orthoxpress.com | I24: Wed 9:30PM | J24: CA based, medicare licensed, suppply ortho ship allsttaes, meeting on monday 7:30 our time | K24: Hanged up on me | O24: FALSE
A25: Auto Insurance | B25: George | C25: No - Show / Callback | D25: 45880 | E25: AffordableONE Kirkendall Insurance | F25: Donald ( Don) | G25: (407) 359-5904 | H25: insuranceman@affordableone.com | I25: monday 11:00 | J25: winter park FL Based he wants some cold caller ( outbound callers ) to get him more clients for his Company | K25: call him back friday 08/15/2025 | O25: FALSE
A26: SUB | B26: Selene | C26: No - Show / Callback | D26: 45859 | E26: Customer Contact Panel | F26: Phil Kitchen | H26: phil.kitchen@customercontactpanel.com | I26: Fri 2:00:PM | J26: -Phil was interested to have a meeting with us on friday 25th 11 am uk time and 1 pm our time -selene 7/21 | K26: we need to sign a contract to start working with them | O26: FALSE
A27: ORT+CGM | B27: Ben | C27: No - Show / Callback | D27: 45925 | E27: Greater Hills Med Supply Llc | F27: Ron Hill | G27: 214-900-7284 | H27: greaterhillstransportation@yahoo.com | I27: Mon 10:30PM | J27: TX BASED, All States, knows about process | O27: FALSE
A28: ORT+CGM | B28: Jane | C28: No - Show / Callback | D28: 45847 | E28: Swift Medical Equipment, Inc. | F28: Tarique Pervez | G28: (734) 752-5822 | H28: Swiftms2023@gmail.com | I28: Mon 7:00PM | J28: ASKED TO THE BE CALLED ON MONDAY NEXT WEEK , he asked to call him after 2 pm like 9 pm he called me backa nd apologized for late call back , mi based, ship allstates , cgn ort,medicare licensed, meeting monday 11:30 am , he was concerened that medicare doesnt pay for them when supply cgm for patients, he was like if do diabetic shoes also | K28: voice mail | M28: 0.75 | O28: FALSE
A29: Home Improvement | B29: Selene | C29: No - Show / Callback | D29: 45909 | E29: PZ Solutions | F29: Kashif Ali | G29: 92 319327005 | H29: kashifhussaindhakan5@gmail.com | I29: Fri 7:00PM | J29: Home improvement and auto insurance AND PCP ORDERS | K29: he didn't attend the meeting | O29: FALSE
A30: RE | B30: Selene | C30: No - Show / Callback | D30: 45722 | E30: Kings Home Realty Advisory Group | F30: Mr. Gregory King | G30: (718) 314-2100 | I30: Fri 5:00 PM | K30: 0.4 wants a callback on Friday because he is out of cash at the moment but may close a deal on Friday and asked me to call back then when he have thte liquidity | O30: FALSE
A31: Lymphadema | B31: Selene | C31: No - Show / Callback | D31: 45973 | E31: NATIONAL DIABETES CARE, LLC. | F31: Hunter Tully | G31: 954-621-6887 | H31: HTULLY@NATDIACARE.COM | I31: Thu 5:00 PM | J31: FL based , Medicare liscenced , ships all states supplies lymph wraps interested to know more meeting tmrw at 5 pm our time 10 am est 11/12 | K31: voice mail 11/13/2025 I will call him back in an hour - called him he said he was waiting our call he agreed on a meeting time tmrw at 8 pm our time selene 12/1 | O31: FALSE | Q31: 1083367015
A32: IMMUNE | B32: Selene | C32: No - Show / Callback | D32: 45982 | E32: FIELD LABS DIAGNOSTICS | F32: APRIL PAULK | G32: 404-452-2817 | H32: Fieldlabsdiagnostics@gmail.com | I32: Tue 5:30PM | J32: - GA Based , medicare liscenced and accept patients all states does Immuno defiency and PGX meeting tuesday 5.30 our time 10.30 est (note lab under construction will reopen dec 15 ) - cb next monday 11/25 - said to cb next week 1/7 always busy aghh | K32: SHE Told me that she wants to reschedule after the holidays , and she was a bit rude as she hanged up after saying this | O32: FALSE | Q32: 1609692128
A33: ORT+CGM | B33: Ben | C33: No - Show / Callback | D33: 45784 | E33: Primary Care Medical Supply | F33: James Blair | G33: 770-881-8010 | H33: primarycareusa@att.net | I33: Fri 10:00PM | J33: GA Based, Medicare Liscenced, ships to georgia only atm but willing to ship to all states spoke to a gatekeeper 2/5 | K33: DOC 5/9/2025 Didnt see the email and prefered to speak on Monday same time. Said that he is interested and want to go for a trial first. I send him the prices and we will talk again on Monday Reconnected and scheduled a meeting 10/16 VM (09/19/2025) | O33: FALSE
A34: IMMUNE | B34: Selene | C34: No - Show / Callback | D34: 46066 | E34: TOTAL SCREENING SOLUTIONS INC | F34: TERESA KING | G34: 708-829-6193 | H34: TERESA@TOTALSCREENINGSOLUTIONSINC.COM | I34: =HYPERLINK("https://calendar.google.com/calendar/u/0/r/eventedit/NGFwaHJwZm9nbTdjNDA0MjltY3MwNWpzZnYgYzM5ZjIxNjY2YTJjNzBkNjQ0MDI0YmQyOWM3ZmM5ODM3OTY2MmY3OTJlNWEwNDdjZGIzNTdhNDJiM2M1N2QwNEBn?pli=1", "Tues 8:00 PM") -> Tues 8:00 PM | J34: -IL Based , Medicare liscenced,nationwide meeting tuesday 8.00 pm our time video meeting -selene 2/13 - Called and hung up staright to vm 2/25 | O34: FALSE | Q34: 1376371294
A35: Auto Insurance | B35: Selene | C35: No - Show / Callback | D35: 45882 | E35: Southland Auto Insurance Services | F35: Christopher Gomez | G35: 623-882-4574 | H35: info@southlandinsurancesvcs.com | I35: Tue 10:00:PM | J35: - AZ based chris is a partner at the agency he said he needs VAs in the next couple of months and he was interested to have an email and get an intro call next tuesday 11 pm our time 1 pmm MST | K35: AZ TX ALL INUSRACCE EXPECT INSUERANCE CREATE PRESTATION | O35: FALSE
A36: IMMUNE | B36: Jimmy | C36: No - Show / Callback | D36: 46080 | E36: COMPASSIONATE TOUCH LAB SERVICES LLC | F36: D'ANDRA HAWKINS | G36: 586-328-7287 | H36: info@COMPASSIONATETOUCHLAB.com | I36: FRI 8:00 PM | O36: FALSE
A37: ORT+CGM | B37: Jimmy | C37: No - Show / Callback | D37: 46066 | E37: COASTAL1 MEDICAL EQUIPMENT LLC | F37: ERIC DEWAYNE RUFFIN | G37: 877-436-8095 | H37: info@COASTAL1DME.com | I37: THU 9:00 PM | J37: He can shipt 18 to 20 states | K37: we sent him the price list and he will look at it, call back thursday 1:00 CT | M37: 46070.878 | O37: FALSE
A38: ORT+CGM+LYMPH W | B38: Ben | C38: No - Show / Callback | D38: 45992 | E38: MEDQ MEDICAL SUPPLY | F38: STEVE PIERRE | G38: 561-859-8322 | H38: medqmedicalsupply@gmail.com | I38: Tue 9:00PM | J38: SC Based, MEDICARE ALL STATES, not sure if he can do lymphedema interesday in all but mostly interested in CGM, told him we are at cap said he wants to be on the waitlist | K38: voice mail rescheduled for jan 6 vm ben vm again - ben | M38: 46112.904 | O38: FALSE
A39: ORT+CGM | B39: Ben | C39: No - Show / Callback | D39: 45869 | E39: Gulf Coast Medical FL | F39: Mark Peterson | G39: 201-736-3819 | H39: gulfcoastmedicalfl@gmail.com | I39: Fri 6:00:PM | J39: FL Based, knows what he's doing, we spoke about everything process / prices, interested about ort but discussed CGM as well but he doesnt seem that keen on it | K39: wanted to see a contract + sample Patient for the orthobedic braces and recordings Vm ( 09/19/2025 VM - BEN disconnected - ben | M39: 46112.93 | O39: FALSE
A40: ORT | B40: Jane | C40: No - Show / Callback | D40: 45778 | E40: APEX MED SUPPLIES LLC | F40: Haris Khan | G40: 437-826-9690 | H40: tk5678@hotmail.com | I40: Mon 4:30:PM | J40: VA based, dme, medicare licsenced, ships for now just va , but he is willing to expand to all states when i told him we have suppliers will help you with this, pcp meeting 4;30 pm and 9:30am his time 5/1 recheduled on monday same time, he has dr appt and very busy 5/2 | K40: Wants to do PPO LT, will talk tomorrow and see how we can collaborate on that DOC 5/5/2025 unavailable - ben Number temporary unavailable, again - ben | M40: 46112.93 | O40: FALSE
A41: CGM | B41: Ben | C41: No - Show / Callback | D41: 45595 | E41: Wellcare Dme Inc | F41: David Rozner | G41: 516-850-7699 | H41: david@wellcaredme.com | I41: Wed 10:00 PM | J41: Business : CGM NY based all states, works with medicare, interested spoke about prices, waiting for Medicare to re-approve his business and then he would be able to work with us DOC 11/4/2024. Should follow up on Monday the 11th. | K41: david@wellcaredme.com. Working on his Software so he can take patients from us. DOC 3/26/2025. Interested in VA too, wants me to call first week of may he wants to touch base in 3 months (07/21/2025) Call back in march VM - sent email ben VM- ben | M41: 46112.953 | O41: FALSE
A42: Campaigns | B42: Ben | C42: No - Show / Callback | D42: 46001 | E42: WellSpring Egypt | F42: Maron Maged | I42: Thu 5:00 PM | O42: FALSE
A43: CGM | B43: Ben | C43: No - Show / Callback | D43: 46113 | E43: GALAXY TECH 786 LLC | F43: ALI RAZA | G43: 239-504-1237 | H43: galaxytech786@gmail.com | I43: THU 8:00 PM | J43: NJ Based (number showed another dme in NC, different comp name and auth), Knows what he's doing,MedB/Nationwide | K43: no show up | M43: 46114.849 | O43: FALSE
A44: ORT+CGM | B44: Jane | C44: No - Show / Callback | D44: 46056 | E44: HOMETOWN MEDICAL EQUIPMENT | F44: KATINA MILES | G44: 706-507-2222 | H44: info@htmeq.com | I44: Mon 8:30 PM | J44: Ga based, ort, cgm supply, medicare licensed, ship allstates, meeting on monday | K44: she just stepped out of the office, she is out on a vacation call back next week, spoke with katina reschduled next week on wednesday | M44: 46107.766 | O44: FALSE
A45: ORT+CGM | B45: Jane | C45: No - Show / Callback | D45: 46105 | E45: LEGACY MEDICAL CONCEPTS LLC | F45: HILDA MARSEILLE | G45: 800-869-5428 | H45: legacymedicalconceptsllc@gmail.com | I45: WED 5:00 PM | J45: FL based ort and cgm, , medicare liscenced, ship allstates, meeting tomw | K45: Ben Arthur can you send her the intro email | M45: 46106.716 | O45: FALSE
A46: ORT | B46: Selene | C46: No - Show / Callback | D46: 46105 | E46: DURAMED MEDICAL EQUIPMENT LLC | F46: MUSSA RAHIMEE | G46: 313-578-1911 | H46: DURAMEDDME@GMAIL.COM | I46: =HYPERLINK("https://calendar.google.com/calendar/u/0/r/eventedit/NmY4MDQwMHFlZGI2YXJqN2xnYjFhMjVldWYgYzM5ZjIxNjY2YTJjNzBkNjQ0MDI0YmQyOWM3ZmM5ODM3OTY2MmY3OTJlNWEwNDdjZGIzNTdhNDJiM2M1N2QwNEBn?pli=1", "WED 8:00 PM") -> WED 8:00 PM | J46: MI based, Medicare liscenced , ships locally but interested to expand nationwide he said he wants acall meeting at wed 8 pm 2 pm est -selene 3/24 | K46: keeps hanging up | M46: 46134.706 | O46: FALSE | Q46: 1679345375
A47: IMMUNE | B47: Selene | C47: No - Show / Callback | D47: 46108 | E47: BEYOND BIO LAB LLC | F47: CONSTANCE GOVERNALE | G47: 954-663-0040 | H47: kkochinski@beyondbiolab.com | I47: =HYPERLINK("https://calendar.google.com/calendar/u/0/r/eventedit/MjFyZTg3dGk5aG5qYWx1NnZmdGNuNzdlYzIgYzM5ZjIxNjY2YTJjNzBkNjQ0MDI0YmQyOWM3ZmM5ODM3OTY2MmY3OTJlNWEwNDdjZGIzNTdhNDJiM2M1N2QwNEBn?pli=1", "MON 4:00 PM") -> MON 4:00 PM | J47: Fl based, has NGS machine and does immuno defiency ,accept nationwide medicare patients sounds experienced and knows what is she doing knows that we are a marketing group she knows that we do telemedicne but she is interested in pcp orders too. She was also asking if we work with a lab in florida because she doesnt want competitors and to cross with other lab meeting monay 10 am est video call 4 pm our time -selene 3/27 | K47: vm several times | M47: 46134.706 | O47: FALSE | Q47: 1720800188
A48: ORT+CGM | B48: Selene | C48: No - Show / Callback | D48: 46108 | E48: AN AMAZING PLACE MEDICAL EQUIPMENT & SUPPLIES LLC | F48: LINDA TAYLOR | G48: 318-450-9852 | H48: lt121957@gmail.com | I48: =HYPERLINK("https://calendar.google.com/calendar/u/0/r/eventedit/M25pZWFlbjdqZ2xiaGFwN29pc3BrajVkZTggYzM5ZjIxNjY2YTJjNzBkNjQ0MDI0YmQyOWM3ZmM5ODM3OTY2MmY3OTJlNWEwNDdjZGIzNTdhNDJiM2M1N2QwNEBn?pli=1", "TUE 8:00 PM") -> TUE 8:00 PM | J48: LA Based, Medicare liscenced, drops ships nationwide ORT CGM meeting 1 pm CST 8 pm our time -selene 3/27 | K48: vm several times | M48: 46134.706 | O48: FALSE | Q48: 1952024077
A49: ORT | B49: Selene | C49: No - Show / Callback | D49: 46115 | E49: ORTHO-AID DISTRIBUTION INC | F49: VIKTOR KOZHANOV | G49: 718-541-3216 | H49: ortho-aid@gmail.com | I49: =HYPERLINK("https://calendar.google.com/calendar/u/0/r/eventedit/M25pZWFlbjdqZ2xiaGFwN29pc3BrajVkZTggYzM5ZjIxNjY2YTJjNzBkNjQ0MDI0YmQyOWM3ZmM5ODM3OTY2MmY3OTJlNWEwNDdjZGIzNTdhNDJiM2M1N2QwNEBn?pli=1", "MON 5:30 PM") -> MON 5:30 PM | J49: Ny Based, Medicare liscenced ort said to give him a call on monday at 11.30 am est 4/3 | K49: vm several times | M49: 46134.706 | O49: FALSE | Q49: 1053114413
A50: IMMUNE | B50: Selene | C50: No - Show / Callback | D50: 46092 | E50: NANO SOLUTIONS LABORATORY LLC | F50: AHMAD TINEH | G50: 469-267-0087 / (903) 808-0339 ( personal ) | H50: said to call him back in 2029 ??? | I50: =HYPERLINK("https://calendar.google.com/calendar/u/0/r/eventedit/MDc2aDQ5YXNvZGdkNDNtbWM3bTJmcDF1OTEgYzM5ZjIxNjY2YTJjNzBkNjQ0MDI0YmQyOWM3ZmM5ODM3OTY2MmY3OTJlNWEwNDdjZGIzNTdhNDJiM2M1N2QwNEBn?pli=1", "Fri 9:00 PM") -> Fri 9:00 PM | J50: TX Based Mediacre liscenced accept nationwide does NGS and immunodefiency test meeting fri 9 pm 2 pm cst -selene 2/27 | K50: (903) 808-0339 | M50: 46094.918 | O50: FALSE | Q50: 1134070212
A51: IMMUNE | B51: Jane | C51: No - Show / Callback | D51: 46121 | E51: EASY STICKS & PRICKS LLC | F51: AALIYAH GARZA | G51: 229-201-0781 | H51: garzaaaliyah316@gmail.com | I51: Fri 7:00 PM | J51: GA based, do ngs immune test, has the machine, bill medicare and accept patient nationwide, send email tome meeting either call or goole meet 7 pm | K51: reschedules meeting on 23rd april | M51: 46125.881 | O51: FALSE
A52: IMMUNE | B52: Jane | C52: No - Show / Callback | D52: 46122 | E52: ADVENTUS LABS | F52: Justin Thompson | G52: 561-577-7641 | H52: justin@adventuslabs.com | I52: MON 11:00 PM | J52: TN based , do the ngs test by sending it to there refrence lab,bill medicare, accept patients nation wide meeting on monday 11pn ourtime | O52: FALSE
A53: IMMUNE | B53: Jimmy | C53: No - Show / Callback | D53: 46122 | E53: VITALTOUCH COLLECTIONS | F53: BRITTANY WILLIAMS | G53: 689-465-6752 | H53: info@VITALTOUCHLABS.com | I53: TUE 8:00 PM | J53: FL BASED She operates as a collection site and works with a reference lab that performs the testing. Typically, the lab handles the billing; however, she also has the capability to manage billing on her end if needed. | O53: FALSE
A54: IMMUNE | B54: Jimmy | C54: No - Show / Callback | D54: 46141 | E54: SAFEPATH DIAGNOSTICS LLC | F54: SHAMEKA BROWN | G54: 336-726-1658 | H54: SAFEPATHDIAGNOSTICSLLC@GMAIL.COM | I54: FRI 9:00 PM | J54: NC based, can do NGS, can accept medicare PT | K54: She wants to know the average reimbursment then talk to her team about and get back to us | M54: 46146.743 | O54: FALSE
A55: ORT+CGM | B55: Jane | C55: No - Show / Callback | D55: 46141 | E55: LINCOLN MEDICAL SUPPLIES LLC | F55: Harry Pervaiz | G55: 267) 327-9722 | H55: LINCOLNMEDSUPPLY@GMAIL.COM | I55: Thu 10:00 PM | J55: Pa based,supply ort and cgm, bill medicare and do ppo ,ship allsttaes | O55: FALSE
A56: ORT+CGM | B56: Selene | C56: No - Show / Callback | D56: 46157 | E56: CAREFIRST RX INC | F56: Mr Rafael | G56: 718-994-4444 | H56: ambarpharmacy@live.com | I56: Fri 7:30 PM | J56: NY Based, Medicare liscenced, ships locally but willing to expand has ort cgm spoke to dr shirin husband he said he handles the work but his wife is the decesion maker said he wants a pnone call tmrw at 12.30 est 4/23 | K56: i spoke to lydia, She said that she is not in the office and her husband is not in the office, and asked to check in again on wednesday | M56: 46136.815 | O56: FALSE | Q56: 1720819006
A57: ORT+CGM | B57: Selene | C57: No - Show / Callback | D57: 46141 | E57: AJIMI INC | F57: JABEEN AHMED | G57: 973-772-7600 | H57: cliftonave@sheefa.com | I57: =HYPERLINK("https://calendar.google.com/calendar/u/0/r/eventedit/N2loODVkbnNnOXA1ZWVoMXU1dXFoMTgydWUgYzM5ZjIxNjY2YTJjNzBkNjQ0MDI0YmQyOWM3ZmM5ODM3OTY2MmY3OTJlNWEwNDdjZGIzNTdhNDJiM2M1N2QwNEBn?pli=1", "TUE 9:00 PM") -> TUE 9:00 PM | J57: NJ Based, Medicare Liscenced, Nationwide ,ORT CGM Video meeting next tuesday at 6 pm our time -selene 4/29 | O57: FALSE | Q57: 1316968381
A58: IMMUNE | B58: Selene | C58: No - Show / Callback | D58: 46146 | E58: PREMIER LABORATORIES LLC | F58: DAVID DEL VECCHIO | G58: 973-508-8319 | H58: david.delvecchio@premier-healthgroup.com | I58: Tue 10:00 PM | J58: NJ Based, Medicare Liscenced, Immune meeting tmrw 10pm our time -selene 5/4 | K58: didn't attend ( VM ) | M58: 46147.922 | O58: FALSE | Q58: 1073326211
A59: DMEDESK | B59: Jimmy | C59: No - Show / Callback | D59: 46149 | E59: SFRN VENTURES LLC | F59: SHAH MIR ALI | G59: 832-446-8336 | H59: SFRNVENTURES@gmail.com | I59: =HYPERLINK("https://calendar.google.com/calendar/u/0/r/eventedit/MzA0MjkwdGtscmRwYnY3aDgwdWhyanVwbWcgYzM5ZjIxNjY2YTJjNzBkNjQ0MDI0YmQyOWM3ZmM5ODM3OTY2MmY3OTJlNWEwNDdjZGIzNTdhNDJiM2M1N2QwNEBn", "WED 9:30 PM 05/13/26") -> WED 9:30 PM 05/13/26 | J59: 05/13/26 She wants to know more about the service and how it can help her business
A60: ORT+CGM | B60: Jane | C60: No - Show / Callback | D60: 46164 | E60: EQUIMED GLOBAL LLC | F60: LAKEISHA MONIQUE JACKSON | G60: 229-349-3363 | H60: jivesmcd@gmail.com | I60: Tue 6:00 PM | J60: GA based supply ort and cgm, bill mediacre ship allstates meetind next monday 5/22
A61: IMMUNE | B61: Jimmy | C61: No - Show / Callback | D61: 46177 | E61: ANGELIC MEDCERTS & LAB SOLUTIONS, LLC | F61: DONNITA A REYNOLDS | G61: 770-899-7102 | H61: info@angelicmedcertslab.org | I61: MON 7:00 PM | J61: GA based, can accept private insurance ( Humana ) Can run NGS
A62: ORT | B62: Jane | C62: No - Show / Callback | D62: 46188 | E62: PROCARE ORTHOTICS &PROSTHETICS | F62: BILL | G62: 2816105387 | H62: procare123@yahoo.com | I62: Tue 6:00 PM | J62: TX based supply only ort , he dont have lymphadema wraps but can order some, billmediare , ship , fax 7137991260 nationwide. meeting tomw 6pm | K62: didn't show up | M62: 46189.773
A63: ORT+CGM | B63: Selene | C63: No - Show / Callback | D63: 46184 | E63: NEXUS DME INC | F63: ABDUL MOIZ | G63: 315-202-9404 | H63: aspiredmecorp@gmail.com | I63: Mon 8:00 PM | J63: NY Based, PPO deals with Eitna Humana Bluecross Blueshield and many more suplies all braces and CGM meeting mon 8 pm -selene 6/11 | K63: will be back tmrw in office | M63: 46188.868 | Q63: 1164355863
A64: DMEDESK | B64: Selene | C64: No - Show / Callback | D64: 46183 | E64: EXCELLENCE MEDICAL EQUIPMENT LLC | F64: Juan Ibarra | G64: 956-459-7266 | H64: JCIBARRA1@HOTMAIL.COM | I64: THU 9:30 PM | J64: TX Based, supplies ORT , CGM he is setting up another DME interested to know more about our services 6/10 | Q64: 1659149417
A65: CGM | B65: Selene | C65: No - Show / Callback | D65: 46168 | E65: QASIM PHARMACY INC | F65: SHAHEER AHMAD | G65: 718-919-5075 | H65: Qasimpharmacy934@gmail.com | I65: Wed 7:00 PM | J65: NY Based, Medicare liscenced CGM meeting wednesday 7 pm our time call meeting -selene 5/26 | K65: wants to postpone meeting because he is very busy today will tell me new timing via email 6/3 | M65: 46176.788 | Q65: 1235297094
A66: ORT+CGM+LYMPH W | B66: Selene | C66: No - Show / Callback | D66: 46183 | E66: EPOCH HEALTH CARE LLC. | F66: ERNST APPOLON | G66: 781-709-6317 | H66: ernst.a@epochhealthcareservice.com | I66: THU 9:00 PM | J66: MA Based, PPO , provides ORT CGM Lymph wants a call tmrw at 9 pm our time 6/10 never billed before 7/22 | K66: - Assistant said stuck in a meeting that will take till end of the day , said cb on mon 6/12 | M66: 46185.877 | Q66: 1114861861
A67: ORT+CGM | B67: Ben | C67: No - Show / Callback | D67: 46190 | E67: INPAK MEDICALS LLC | F67: INNOCENT UBAK | G67: 240-701-3882 | H67: inpakmedicals@gmail.com inpakhealthcare@yahoo.com | I67: FRI 9:30 PM | J67: MD BASED, ort mainly and cgm, meeting with his partner, no medicare , discussed ppo/hmo
A68: DMEDESK | B68: Ben | C68: No - Show / Callback | D68: 46178 | E68: SNOREIX PLLC (Zennity Sleep) | F68: KRISTINA ROGOZHKINA Meeting with Ryan, Head of operations | G68: 303-421-4820 | H68: ryan@zennitysleep.com | I68: Wed 8:00 PM | J68: Got a call back from him, CO Based website : zennitysleep.com
A69: ORT+CGM | B69: Jimmy | C69: No - Show / Callback | D69: 46184 | E69: CLEARCLAIM MEDICAL BILLING INC. | F69: ABDULRAFAY MAHMOOD | G69: 307-289-2158 | H69: CLEARCLAIMMBI@GMAIL.COM | I69: Mon 7:00 PM | J69: I are currently planning to acquire an existing Medicare store that is already operational and has all the necessary credentials, including a PTAN and other required registrations. At this stage, we are in the evaluation and discussion phase, and the acquisition has not yet been finalized. If the deal is successfully completed, we will proceed with taking over the store. In the meantime, we would like to discuss potential lead generation opportunities and AI-driven marketing strategies that could help us grow the business 6/11/26 7:44 | O69: FALSE
A70: ORT+CGM+LYMPH W | B70: Ben | C70: No - Show / Callback | D70: 46197 | E70: BEAUREGARD MEDICAL SOLUTIONS LLC | F70: CWENTEENIA LACOLE WILSON | G70: 702-463-8850 | H70: cwenwilson@icloud.com | I70: Wed 9:00 PM | J70: relocating out of lousiana, moving into dropshipping ,asked abt amt of patients, suggested starting from 10-30 then scaling to whatever she would get into agrreem,ent with you, seems v interested ,
A71: IMMUNE | B71: Jimmy | C71: No - Show / Callback | D71: 46191 | E71: HAZELS TOUCH LABORATORY SERVICES L.L.C | F71: DIAMOND DILLARD | G71: 252-484-5413 | H71: hazelstouchlab@gmail.com | I71: FRI 7:30 PM | J71: NC based Can do NGS and PGx want to discuss further info
A72: ORT+CGM | B72: Jane | C72: No - Show / Callback | D72: 46190 | E72: LOVE CARE DME | F72: LARRY LOVE | G72: 817-681-5354 | H72: lovecaredme@gmail.com | I72: Tue 9:00 PM | J72: Tx based supply ort and cgm, ship nation wide, bill medicare and ppo, asked to send email,meeting | K72: voice mail, rescheduled on monday 1 pm cst, he asked to call him on thursday to rescduled her is out of the office these days | M72: 46196.817
A73: ORT + Lymphedema | B73: Jimmy | C73: No - Show / Callback | D73: 45662 | E73: RADIANCE TECH LLC | F73: Hammad Ali | G73: (307) 655-1490 | H73: HammadAli6085@gmail.com | I73: THU 6:30 PM | J73: I talked to him again and we discussed sth about doing the business but for private insurance, he wants to know the prices, he thought that we just give him the PTs, but I told him that we do the quality, the chasing and the marketing from our side and we provide a complete lead for him 6/29/26 10:15 IL based, supply ort+ lymph , PPO liscensed ,ship nationwide, meeting MON 01/05/25 8:30 | K73: "He said he is out of service for now, and now he can't take our leads, he said we might check with him again after a couple of month 1/21/25 10:12 NA 1/19/26 4:37 He stated that he attended the meeting but while talking to me He sounded confused. He added that he was busy at the time and would follow up later. 1/13/25 5:23 " voice mail 03/18/2026 | M73: 46099.906 | N73: FALSE
A74: ORT | B74: Jane | C74: No - Show / Callback | D74: 46203 | E74: TIM'S HOME MEDICAL LLC | F74: TIMOTHY SLOAN | G74: 912-294-1284 | H74: tls70@yahoo.com | I74: Tue 7:30 AM | J74: Ga based, supply ort , medicare licenced,able to ship jurcdiction C only MEETING 12:30 TUESDAY | K74: no answer vmail | M74: 46210.886
A75: ORT+CGM+LYMPH W | B75: Ben | C75: No - Show / Callback | D75: 46198 | E75: PRIMECARE MEDICAL SUPPLY INC | F75: MAHMOUD ZAYED | G75: 470-298-8992 | H75: primecaremedical26@gmail.com | I75: Mon 7:30 PM | J75: GA Based, new dme, does private insurance waiting for medicare | K75: Rescheduled for today | M75: 46211.704
A76: ORT+CGM | B76: Jimmy | C76: No - Show / Callback | D76: 46209 | E76: MEGA MEDICAL SUPPLY LLC | F76: KENNETH EKIKO | G76: 720-400-8979 | H76: MEGAMEDICAL22@gmail.com | I76: TUE 8:00 PM | J76: CO Based He is just having some concerns on how we operate and whether it is safe or not, he had another company reaching out to him for the same reason, but he said that he is a bit okay with us because we shared with him all the docs that he might need. Can accept medicare PT.
A77: ORT+CGM+LYMPH W | B77: Jane | C77: No - Show / Callback | D77: 46211 | E77: DME-NOW, LLC | F77: Dr.DAWSHEEN T HAYNES | G77: 817-710-4220 | H77: drdhaynesdc@gmail.com | I77: Tue 7:30 PM | J77: Tx based can order all items ort, cgm,lymphedema, waiting on his medicare licensed to be approved in next 3 months, but works with blue sheild and blue cross, ship localt but if reimberstment good in other states he said he can meeting next tuesday 11:30 central | K77: no show | M77: 46217.815 | Q77: 1740800176
A78: ORT+CGM | B78: Jimmy | C78: No - Show / Callback | D78: 46223 | E78: PRISTINE MEDICAL EQUIPMENT AND ACCESSORIES INC | F78: Kacey | G78: 410-720-9002 | H78: info@pmeACCESSORIES.com | I78: WED 10:00 PM | J78: She can do private insirace PPO | Q78: 1265249098
A79: ORT+CGM | B79: Selene | C79: No - Show / Callback | D79: 46210 | E79: SUREPATH MEDICAL SUPPLY LLC | F79: ANAM SADDAM | G79: 832-757-3030 | H79: anam.saddam@outlook.com | I79: =HYPERLINK("https://calendar.google.com/calendar/u/0/r/eventedit/MXFrc2JiYXA1MTY1aWppOG5qZG0xbW44ZzQgYzM5ZjIxNjY2YTJjNzBkNjQ0MDI0YmQyOWM3ZmM5ODM3OTY2MmY3OTJlNWEwNDdjZGIzNTdhNDJiM2M1N2QwNEBn?pli=1", "THU 10:00 PM") -> THU 10:00 PM | J79: TX Based, PPO LIscenced , ORT CGM , nationwide , worked with marketing before meeting thursday 10 pm our time 7/7 | Q79: 1730034315
A80: IMMUNE | B80: Jimmy | C80: No - Show / Callback | D80: 46094 | E80: ACT FAST LAB LLC | F80: DERISHA L LINSEY | G80: 903-386-5486 | H80: actfastlab@gmail.com | I80: WED 7:00 PM | J80: TX based She has the equipment and can accept medicare PT | K80: no show | M80: 46099.799 | O80: FALSE | Q80: 1154089241

Sheet Dead Leads
B1: Opener | C1: Status | D1: Date Added | E1: Company Name | F1: Authorized Person | G1: Phone | H1: EMAIL | I1: Meeting Time | J1: Opener Summary | K1: George's Notes | L1: Auto Scheduler | M1: Last Call | N1: Action | O1: Checkbox | P1: Log | Q1: NPI
A2: ORT+CGM | B2: Ben | C2: NI | D2: 45593 | E2: ASTRA GO INC (Parent Company) | F2: Pinchas Kalantarov | G2: 718-415-9028 | I2: Thu 7:00 PM | J2: Business : DME & CGM Call Time : {03:31} one company with 6 dme's under him, he was the one to ask or a meeting after discussing process, works All States, VM 11/25 | K2: We met again on the 21th nov. Talked a lot about a telehealth network of his (Astro go) and then we discussed DME. Wants to work with us and compare prices. Will talk again so. | L2: We met again on the 21th nov. Talked a lot about a telehealth network of his (Astro go) and then we discussed DME. Wants to work with us and compare prices. Will talk again so. | O2: FALSE
A3: ORT | B3: Ben | C3: NI | D3: 45610 | E3: All Health Dme Inc | F3: Eduard Katanov / ALBERT | G3: 347-808-7441(EDDY) 917-612-2879 (ALBERT) | I3: Thu 8:30 PM | J3: Business : DME called eduard he gave me alberts number, spoke to albert the manager about process, location,dme prices, has a concern about the kickback law wanted to know if we do fixed rate for braces allmed.m.t@gmail.com | K3: We spoke today 12/4/2024 he said his payemnts from medicare are being issued but he can't receive them.. he is waiting to solve that problem and then will talk again before christmas | L3: We spoke today 12/4/2024 he said his payemnts from medicare are being issued but he can't receive them.. he is waiting to solve that problem and then will talk again before christmas | M3: talked to him again after two weeks on DME Desk 06/09/2026 | O3: FALSE
A4: ORT | B4: Ben | C4: NI | D4: 45616 | E4: N J Planet Medical & Surgical Supply | F4: Aamir Siddiqui | G4: 844-305-3428 | H4: AAMIR@PLANETMEDSUPPLY.COM | I4: Thu 10:30 PM | J4: Business : DME & CGM Interested, spoke about process,Loctation Discussed prices, wants suppliers' info for CGM NJ Based All States + Medicare,First time doing Marketing, | K4: Decided to pass 12/4/2024 | L4: Decided to pass 12/4/2024 | M4: he has another campaign going on , and he believes about face to face encounters, he has already a campaign going on | O4: FALSE
A5: ORT+CGM | B5: Ben | C5: DNC | D5: 45622 | E5: Care DME | F5: Krishna | G5: 321-402-6716 | I5: second week of JAN | J5: Will resume in Jan Wants subjective PCP and CGM | O5: FALSE
A6: ORT+CGM | B6: Ben | C6: No Medicare | D6: 45631 | E6: Ak Jersey Inc | F6: Asif Khan | G6: 888-632-1074 EXT.101 | I6: Fri 8:00 PM | J6: Interested, Spoke about prices, Loctaion, has multiple DMEs Doesn't have Medicare yet, only works with PPO | K6: Doesn't have Medicare yet, only works with PPO | L6: Doesn't have Medicare yet, only works with PPO | O6: FALSE
A7: ORT+CGM | B7: Ben | C7: NI | D7: 45635 | E7: Purecure Medical, Inc | F7: Joseph F Dunn | G7: 215-542-9220 | I7: Thu 9th Jan 25 | J7: Works Medicare, Wants to know if he can speak with some of our clients, had issue with reimbursements (quality of patients) , first time called him around 8pm cairo NO CGM NO ORT NO LYMPH 12/12/2025 | K7: Stupid and said he will never get paid for off the shelf, not experienced. | L7: Stupid and said he will never get paid for off the shelf, not experienced. | O7: FALSE
A8: ORT+CGM | B8: Ben | C8: NI | D8: 45639 | E8: Park Avenue Medical Equipment Llc | F8: Puccini Inokon | G8: 646-244-8595 | I8: Wed 6:00 PM | J8: "NY Based , supply All States, Medicare, doesn't do medicare but said he has affiliates sent email resent mail, Recheduled for wednesday 11 am | K8: May signup ofr PPO Patients per lead Tristate | L8: May signup ofr PPO Patients per lead Tristate | O8: FALSE
A9: ORT+CGM | B9: Ben | C9: NI | D9: 8/22/2024(no show) 1/2/2025 | E9: Star Dme Inc | F9: Arik Malakov | G9: 888-918-0373 | I9: Mon 10:30 PM | J9: NY Based, Interested CGM&DME, no show -Spoke again, has concerns with compliance | O9: FALSE
A10: ORT+CGM | B10: Ben | C10: NI | D10: 45684 | E10: Z Z Best Inc | F10: Keith Brown | G10: 706-945-7913 | I10: Wed 9:15 PM | J10: CGM & DME / GA based / Interested / all states, works medicare - Called him said they were busy with renovations | O10: FALSE
A11: ORT+CGM | B11: Ben | C11: NI | D11: 45674 | E11: Elated Medical Supplies Llc | F11: Shekelia Stokes | G11: 313-414-3120 | H11: info@elatedmedical.com | I11: FEB 20TH | J11: Interested spoke about process,location. MI ONLY A FIRST, HIGH CHANCE FOR JUR B works with medicare / Call her monday left a VM She spoke to bassam cb in a month | K11: We are waiting for her license and she should start as soon as she consult her team and get her license (EMAIL on 2/7/2025) She needs more time and when call when ready. Can't reach her, no answer 2 calls DOC 2/20/2025 | L11: We are waiting for her license and she should start as soon as she consult her team and get her license (EMAIL on 2/7/2025) She needs more time and when call when ready. Can't reach her, no answer 2 calls DOC 2/20/2025 | O11: FALSE
A12: ORT | B12: Selene | C12: NI | D12: 45693 | E12: DHAMIR MED SUPPLIES LLC | F12: Kamilah Beyah spoke to Natalie (office manager ) | G12: 512-425-0744 | I12: Mon 10:00 PM | J12: operator didnt know when she will be back she will call her husband and will let us know -selene 2/4 - left vm -selene 2/4 - i spoke to natalie the office manager she said they are medicare liscenced and they provide DME and CGM they provide all states except 7 and they can take as much patient we can provide- natalie@dhamirmedsupplies.net meeting friday at 2 pm their time and 10 pm our time -selene 2/5 - i called x2 times and they hung up -selene 2/11 | O12: FALSE | Q12: 1164355863
A13: ORT | B13: Selene | C13: NI | D13: 45693 | E13: CASPIAN MEDICAL SUPPLY HEALTH CARE | F13: Siyavash Ziae (I spoke office Manager/Owner Mahboba ) | G13: 747-323-7378 - 818 358-7080 | I13: Thu 10:00 PM | J13: - owner mahboba said they are medicare licecensed , she said they deliver all states but most likely CA only they work with telemed she said cb in 20 min -selene 2/5 - i spoke to mahboba i calrified again that they are liscenced and work for all states she said yes caspiandme@gmail.com tmrw meeting at 2 pm but she wanted to have a meeting in 20 min she was very interested -selene 2/5 | O13: FALSE | Q13: 1689409575
A14: ORT | B14: Ben | C14: NI | D14: 45694 | E14: Ally Medical Supply Inc | F14: Firas Abolgar | G14: 312-493-5657 | H14: allymedindiana@gmail.com | I14: Fri 7:00 PM | J14: Spoke to the guy, DON'T CALL EVER AGAIN He works in jur B, bills medicare, he gets like 100 pt per week. | O14: FALSE
A15: ORT+CGM | B15: Ben | C15: NI | D15: 45695 | E15: Best American Medical Supplies Llc | F15: Emmanuel E Dekpe | G15: 919-896-7222 | I15: Tue 8:30 PM | J15: NC Based, Explained Process,ships All States, no concerns, sent email scheduled meeting tue | O15: FALSE
A16: ORT | B16: Selene | C16: NI | D16: 45695 | E16: NOVUS MEDICAL INC | F16: Dwayne Dale Sharp | G16: 559-660-6295 | I16: Mon 10.00PM | J16: - LEFT A VM -SELENE 2/6 - dwayne gave a cb he said he works primarly california and wotld be willing to work all states he would like 100 pts per week and he filed 6 months ago he will be getting it in a few days and he was very intersted email dwayne@nusolutions-inc.com and wanted a meeting monday 2/10 around 10 pm our time works pcp and knows we are in cairo suppl;y DME and CGM -selene 2/7 - Dwayne gave a cb gave an email he said he doesnt want to deal with us because he doesnt want to deal with referrals and he doesnt want to deal with the FBI and he felt that we are fishy he said i do everything straight -selene 2/7 | O16: FALSE | Q16: 1619716743
